Workbook

Sheet 01 Executive Summary
A1: CostProof — finance model
A2: The output of a causal cost-measurement engine, delivered as an FP&A workbook.
A3: SIMULATED DATA. The estate is synthetic (FOCUS 1.2, 400 resources, 540 days). Figures illustrate the method; ground truth exists only because the data is simulated.
A5: The problem
A6: Every cloud cost tool reports what was spent. None can prove what an optimisation saved,
A7: because teams act on spikes and spikes revert on their own. Before/after comparison
A8: credits the team for gravity. This workbook shows what changes when the saving is
A9: measured against a control group instead.
A11: Two workbooks, two questions
A12: costproof-business-case.xlsx asks: should an organisation buy the measurement layer?
A13: Its NPV counts only decision quality -- effort not wasted on fixes that did nothing.
A14: This workbook asks: what did the optimisation programme itself deliver, measured
... A19: Headline figures (formulas; active scenario)
A20: Measure | B20: Value | C20: Where it comes from
A21: Events measured | B21: ='04 Savings Attribution'!$D$127 -> 117 | C21: Savings Attribution
A22: Passing the parallel-trends check | B22: ='04 Savings Attribution'!$D$128 -> 103 | C22: Savings Attribution
A23: Before/after would report, per year | B23: ='04 Savings Attribution'!$D$131 -> 1693741 | C23: Savings Attribution — the industry's number
A24: Credited savings, per year | B24: ='04 Savings Attribution'!$D$133 -> 1872634 | C24: Savings Attribution — identified, gated
A25: Difference the method makes | B25: ='07 ROI Analysis'!$B$38 -> 178893.04 | C25: ROI Analysis
A26: Programme NPV, five years | B26: ='07 ROI Analysis'!$B$26 -> 2833109.4 | C26: ROI Analysis
A27: Benefit-to-cost ratio | B27: ='07 ROI Analysis'!$B$29 -> 2.8634267 | C27: ROI Analysis
A28: Payback, months | B28: ='07 ROI Analysis'!$B$32 -> 6.54707 | C28: ROI Analysis
A29: Budget variance over the period | B29: ='05 Budget vs Actual'!$Z$18 -> 0.071979076 | C29: Budget vs Actual
A30: SIMULATED: gross misattribution in before/after | B30: ='04 Savings Attribution'!$D$135 -> 450967.84 | C30: Savings Attribution — needs ground truth
A31: Active scenario / attribution policy | B31: ='10 Assumptions'!$B$27&" / "&IF('10 Assumptions'!$B$24="Yes","all","PT gate") -> Base / PT gate | C31: Assumptions
A33: How to read this workbook
A34: Blue cells are inputs; black cells are formulas; green cells link to another sheet.
A35: Only estimates that pass the parallel-trends check are credited, unless you flip the
A36: policy switch on Assumptions. Bear/Bull/Base are execution scenarios, not measurement
A37: scenarios: the estimator's own error is quantified on Savings Attribution.
A38: Peach cells use simulated ground truth. They are the reason the method can be
A39: validated here and the reason it would be needed on real data, where they do not exist.
A41: Sheets
A42: 02 Raw Cost Data | C42: monthly cost by business unit; the pivot is formulas
A43: 03 Optimization Events | C43: the intervention register
A44: 04 Savings Attribution | C44: per-event estimates, the gate, the credited total
A45: 05 Budget vs Actual | C45: run-rate budget vs actual, by unit and month
A46: 06 Forecast | C46: twelve months forward, two methods
A47: 07 ROI Analysis | C47: programme cash flows, NPV, ROI, IRR, payback
A48: 08 Scenario Analysis | C48: Base / Bull / Bear side by side
A49: 09 Sensitivity Analysis | C49: NPV grids over four drivers
A50: 10 Assumptions | C50: every input, in one place
A51: 11 KPI Dashboard | C51: tiles and charts
A53: Generated by scripts/build_finance_model.py from the pipeline's own outputs. Regenerate after `costproof study`; nothing here is typed in.

Sheet 02 Raw Cost Data
A1: Raw cost data
A2: Monthly effective, billed and list cost by business unit, from the silver layer (Usage rows, complete months only). The pivot on the right is formulas.
A3: SIMULATED DATA. The estate is synthetic (FOCUS 1.2, 400 resources, 540 days). Figures illustrate the method; ground truth exists only because the data is simulated.
G4: Effective cost by month and business unit (SUMIFS over the table)
A5: Month | B5: Business unit | C5: Effective cost | D5: Billed cost | E5: List cost | G5: Month | H5: # | I5: bu-assist | J5: bu-checkout | K5: bu-datalake | L5: bu-datasci | M5: bu-platform | N5: bu-search | O5: unallocated | P5: Total
A6: 45658 | B6: bu-assist | C6: 141869.63 | D6: 116240.39 | E6: 158448.04 | G6: 45658 | H6: 1 | I6: =SUMIFS($C$6:$C$124,$A$6:$A$124,$G6,$B$6:$B$124,I$5) -> 141869.63 | J6: =SUMIFS($C$6:$C$124,$A$6:$A$124,$G6,$B$6:$B$124,J$5) -> 77461.639 | K6: =SUMIFS($C$6:$C$124,$A$6:$A$124,$G6,$B$6:$B$124,K$5) -> 57576.421 | L6: =SUMIFS($C$6:$C$124,$A$6:$A$124,$G6,$B$6:$B$124,L$5) -> 114791.87 | M6: =SUMIFS($C$6:$C$124,$A$6:$A$124,$G6,$B$6:$B$124,M$5) -> 70348.918 | N6: =SUMIFS($C$6:$C$124,$A$6:$A$124,$G6,$B$6:$B$124,N$5) -> 80411.691 | O6: =SUMIFS($C$6:$C$124,$A$6:$A$124,$G6,$B$6:$B$124,O$5) -> 69283.921 | P6: =SUM(I6:O6) -> 611744.09
A7: 45658 | B7: bu-checkout | C7: 77461.639 | D7: 45232.614 | E7: 93014.008 | G7: 45689 | H7: 2 | I7: =SUMIFS($C$6:$C$124,$A$6:$A$124,$G7,$B$6:$B$124,I$5) -> 131285.97 | J7: =SUMIFS($C$6:$C$124,$A$6:$A$124,$G7,$B$6:$B$124,J$5) -> 71395.969 | K7: =SUMIFS($C$6:$C$124,$A$6:$A$124,$G7,$B$6:$B$124,K$5) -> 55351.038 | L7: =SUMIFS($C$6:$C$124,$A$6:$A$124,$G7,$B$6:$B$124,L$5) -> 129367.1 | M7: =SUMIFS($C$6:$C$124,$A$6:$A$124,$G7,$B$6:$B$124,M$5) -> 68187.358 | N7: =SUMIFS($C$6:$C$124,$A$6:$A$124,$G7,$B$6:$B$124,N$5) -> 75021.547 | O7: =SUMIFS($C$6:$C$124,$A$6:$A$124,$G7,$B$6:$B$124,O$5) -> 64715.596 | P7: =SUM(I7:O7) -> 595324.58
A8: 45658 | B8: bu-datalake | C8: 57576.421 | D8: 47000.025 | E8: 64010.931 | G8: 45717 | H8: 3 | I8: =SUMIFS($C$6:$C$124,$A$6:$A$124,$G8,$B$6:$B$124,I$5) -> 170694.11 | J8: =SUMIFS($C$6:$C$124,$A$6:$A$124,$G8,$B$6:$B$124,J$5) -> 87880.492 | K8: =SUMIFS($C$6:$C$124,$A$6:$A$124,$G8,$B$6:$B$124,K$5) -> 61084.426 | L8: =SUMIFS($C$6:$C$124,$A$6:$A$124,$G8,$B$6:$B$124,L$5) -> 199666.2 | M8: =SUMIFS($C$6:$C$124,$A$6:$A$124,$G8,$B$6:$B$124,M$5) -> 69367.665 | N8: =SUMIFS($C$6:$C$124,$A$6:$A$124,$G8,$B$6:$B$124,N$5) -> 87877.055 | O8: =SUMIFS($C$6:$C$124,$A$6:$A$124,$G8,$B$6:$B$124,O$5) -> 75572.938 | P8: =SUM(I8:O8) -> 752142.89
A9: 45658 | B9: bu-datasci | C9: 114791.87 | D9: 112932.93 | E9: 118048.31 | G9: 45748 | H9: 4 | I9: =SUMIFS($C$6:$C$124,$A$6:$A$124,$G9,$B$6:$B$124,I$5) -> 173641.2 | J9: =SUMIFS($C$6:$C$124,$A$6:$A$124,$G9,$B$6:$B$124,J$5) -> 91758.287 | K9: =SUMIFS($C$6:$C$124,$A$6:$A$124,$G9,$B$6:$B$124,K$5) -> 68648.745 | L9: =SUMIFS($C$6:$C$124,$A$6:$A$124,$G9,$B$6:$B$124,L$5) -> 155580.08 | M9: =SUMIFS($C$6:$C$124,$A$6:$A$124,$G9,$B$6:$B$124,M$5) -> 72773.121 | N9: =SUMIFS($C$6:$C$124,$A$6:$A$124,$G9,$B$6:$B$124,N$5) -> 89750.976 | O9: =SUMIFS($C$6:$C$124,$A$6:$A$124,$G9,$B$6:$B$124,O$5) -> 73834.677 | P9: =SUM(I9:O9) -> 725987.08
A10: 45658 | B10: bu-platform | C10: 70348.918 | D10: 59598.308 | E10: 77787.228 | G10: 45778 | H10: 5 | I10: =SUMIFS($C$6:$C$124,$A$6:$A$124,$G10,$B$6:$B$124,I$5) -> 168584.86 | J10: =SUMIFS($C$6:$C$124,$A$6:$A$124,$G10,$B$6:$B$124,J$5) -> 96378.562 | K10: =SUMIFS($C$6:$C$124,$A$6:$A$124,$G10,$B$6:$B$124,K$5) -> 70552.176 | L10: =SUMIFS($C$6:$C$124,$A$6:$A$124,$G10,$B$6:$B$124,L$5) -> 161497.27 | M10: =SUMIFS($C$6:$C$124,$A$6:$A$124,$G10,$B$6:$B$124,M$5) -> 72013.672 | N10: =SUMIFS($C$6:$C$124,$A$6:$A$124,$G10,$B$6:$B$124,N$5) -> 94285.115 | O10: =SUMIFS($C$6:$C$124,$A$6:$A$124,$G10,$B$6:$B$124,O$5) -> 84541.533 | P10: =SUM(I10:O10) -> 747853.19
A11: 45658 | B11: bu-search | C11: 80411.691 | D11: 63621.62 | E11: 91372.071 | G11: 45809 | H11: 6 | I11: =SUMIFS($C$6:$C$124,$A$6:$A$124,$G11,$B$6:$B$124,I$5) -> 157180.44 | J11: =SUMIFS($C$6:$C$124,$A$6:$A$124,$G11,$B$6:$B$124,J$5) -> 92478.419 | K11: =SUMIFS($C$6:$C$124,$A$6:$A$124,$G11,$B$6:$B$124,K$5) -> 70541.829 | L11: =SUMIFS($C$6:$C$124,$A$6:$A$124,$G11,$B$6:$B$124,L$5) -> 140313.55 | M11: =SUMIFS($C$6:$C$124,$A$6:$A$124,$G11,$B$6:$B$124,M$5) -> 73722.175 | N11: =SUMIFS($C$6:$C$124,$A$6:$A$124,$G11,$B$6:$B$124,N$5) -> 90268.734 | O11: =SUMIFS($C$6:$C$124,$A$6:$A$124,$G11,$B$6:$B$124,O$5) -> 77440.757 | P11: =SUM(I11:O11) -> 701945.9
A12: 45658 | B12: unallocated | C12: 69283.921 | D12: 50164.525 | E12: 79175.308 | G12: 45839 | H12: 7 | I12: =SUMIFS($C$6:$C$124,$A$6:$A$124,$G12,$B$6:$B$124,I$5) -> 157484.7 | J12: =SUMIFS($C$6:$C$124,$A$6:$A$124,$G12,$B$6:$B$124,J$5) -> 93742.453 | K12: =SUMIFS($C$6:$C$124,$A$6:$A$124,$G12,$B$6:$B$124,K$5) -> 71220.469 | L12: =SUMIFS($C$6:$C$124,$A$6:$A$124,$G12,$B$6:$B$124,L$5) -> 154568.58 | M12: =SUMIFS($C$6:$C$124,$A$6:$A$124,$G12,$B$6:$B$124,M$5) -> 70392.849 | N12: =SUMIFS($C$6:$C$124,$A$6:$A$124,$G12,$B$6:$B$124,N$5) -> 97421.955 | O12: =SUMIFS($C$6:$C$124,$A$6:$A$124,$G12,$B$6:$B$124,O$5) -> 78358.728 | P12: =SUM(I12:O12) -> 723189.72
A13: 45689 | B13: bu-assist | C13: 131285.97 | D13: 108775.44 | E13: 145911.61 | G13: 45870 | H13: 8 | I13: =SUMIFS($C$6:$C$124,$A$6:$A$124,$G13,$B$6:$B$124,I$5) -> 164579.11 | J13: =SUMIFS($C$6:$C$124,$A$6:$A$124,$G13,$B$6:$B$124,J$5) -> 97362.162 | K13: =SUMIFS($C$6:$C$124,$A$6:$A$124,$G13,$B$6:$B$124,K$5) -> 63816.123 | L13: =SUMIFS($C$6:$C$124,$A$6:$A$124,$G13,$B$6:$B$124,L$5) -> 143516.31 | M13: =SUMIFS($C$6:$C$124,$A$6:$A$124,$G13,$B$6:$B$124,M$5) -> 73737.598 | N13: =SUMIFS($C$6:$C$124,$A$6:$A$124,$G13,$B$6:$B$124,N$5) -> 100098.44 | O13: =SUMIFS($C$6:$C$124,$A$6:$A$124,$G13,$B$6:$B$124,O$5) -> 77229.281 | P13: =SUM(I13:O13) -> 720339.02
A14: 45689 | B14: bu-checkout | C14: 71395.969 | D14: 40575.811 | E14: 85967.485 | G14: 45901 | H14: 9 | I14: =SUMIFS($C$6:$C$124,$A$6:$A$124,$G14,$B$6:$B$124,I$5) -> 158979.41 | J14: =SUMIFS($C$6:$C$124,$A$6:$A$124,$G14,$B$6:$B$124,J$5) -> 92261.506 | K14: =SUMIFS($C$6:$C$124,$A$6:$A$124,$G14,$B$6:$B$124,K$5) -> 61211.517 | L14: =SUMIFS($C$6:$C$124,$A$6:$A$124,$G14,$B$6:$B$124,L$5) -> 159667.6 | M14: =SUMIFS($C$6:$C$124,$A$6:$A$124,$G14,$B$6:$B$124,M$5) -> 77160.957 | N14: =SUMIFS($C$6:$C$124,$A$6:$A$124,$G14,$B$6:$B$124,N$5) -> 95928.862 | O14: =SUMIFS($C$6:$C$124,$A$6:$A$124,$G14,$B$6:$B$124,O$5) -> 81095.158 | P14: =SUM(I14:O14) -> 726305.01
A15: 45689 | B15: bu-datalake | C15: 55351.038 | D15: 45654.664 | E15: 61360.855 | G15: 45931 | H15: 10 | I15: =SUMIFS($C$6:$C$124,$A$6:$A$124,$G15,$B$6:$B$124,I$5) -> 173558.54 | J15: =SUMIFS($C$6:$C$124,$A$6:$A$124,$G15,$B$6:$B$124,J$5) -> 111068.97 | K15: =SUMIFS($C$6:$C$124,$A$6:$A$124,$G15,$B$6:$B$124,K$5) -> 61411.786 | L15: =SUMIFS($C$6:$C$124,$A$6:$A$124,$G15,$B$6:$B$124,L$5) -> 164202.51 | M15: =SUMIFS($C$6:$C$124,$A$6:$A$124,$G15,$B$6:$B$124,M$5) -> 87267.349 | N15: =SUMIFS($C$6:$C$124,$A$6:$A$124,$G15,$B$6:$B$124,N$5) -> 109009.59 | O15: =SUMIFS($C$6:$C$124,$A$6:$A$124,$G15,$B$6:$B$124,O$5) -> 85190.819 | P15: =SUM(I15:O15) -> 791709.56
A16: 45689 | B16: bu-datasci | C16: 129367.1 | D16: 127972.22 | E16: 132211.37 | G16: 45962 | H16: 11 | I16: =SUMIFS($C$6:$C$124,$A$6:$A$124,$G16,$B$6:$B$124,I$5) -> 170043.12 | J16: =SUMIFS($C$6:$C$124,$A$6:$A$124,$G16,$B$6:$B$124,J$5) -> 132965.8 | K16: =SUMIFS($C$6:$C$124,$A$6:$A$124,$G16,$B$6:$B$124,K$5) -> 58841.39 | L16: =SUMIFS($C$6:$C$124,$A$6:$A$124,$G16,$B$6:$B$124,L$5) -> 144469.26 | M16: =SUMIFS($C$6:$C$124,$A$6:$A$124,$G16,$B$6:$B$124,M$5) -> 85378.466 | N16: =SUMIFS($C$6:$C$124,$A$6:$A$124,$G16,$B$6:$B$124,N$5) -> 119213.62 | O16: =SUMIFS($C$6:$C$124,$A$6:$A$124,$G16,$B$6:$B$124,O$5) -> 90806.45 | P16: =SUM(I16:O16) -> 801718.11
A17: 45689 | B17: bu-platform | C17: 68187.358 | D17: 57902.004 | E17: 75400.181 | G17: 45992 | H17: 12 | I17: =SUMIFS($C$6:$C$124,$A$6:$A$124,$G17,$B$6:$B$124,I$5) -> 196719.21 | J17: =SUMIFS($C$6:$C$124,$A$6:$A$124,$G17,$B$6:$B$124,J$5) -> 126834.23 | K17: =SUMIFS($C$6:$C$124,$A$6:$A$124,$G17,$B$6:$B$124,K$5) -> 67374.564 | L17: =SUMIFS($C$6:$C$124,$A$6:$A$124,$G17,$B$6:$B$124,L$5) -> 179764.62 | M17: =SUMIFS($C$6:$C$124,$A$6:$A$124,$G17,$B$6:$B$124,M$5) -> 77821.171 | N17: =SUMIFS($C$6:$C$124,$A$6:$A$124,$G17,$B$6:$B$124,N$5) -> 113922.09 | O17: =SUMIFS($C$6:$C$124,$A$6:$A$124,$G17,$B$6:$B$124,O$5) -> 93942.017 | P17: =SUM(I17:O17) -> 856377.91
... A22: 45717 | B22: bu-datalake | C22: 61084.426 | D22: 49295.274 | E22: 68135.704 | G22: 46143 | H22: 17 | I22: =SUMIFS($C$6:$C$124,$A$6:$A$124,$G22,$B$6:$B$124,I$5) -> 199289.57 | J22: =SUMIFS($C$6:$C$124,$A$6:$A$124,$G22,$B$6:$B$124,J$5) -> 107902.82 | K22: =SUMIFS($C$6:$C$124,$A$6:$A$124,$G22,$B$6:$B$124,K$5) -> 79901.899 | L22: =SUMIFS($C$6:$C$124,$A$6:$A$124,$G22,$B$6:$B$124,L$5) -> 182830.56 | M22: =SUMIFS($C$6:$C$124,$A$6:$A$124,$G22,$B$6:$B$124,M$5) -> 77319.347 | N22: =SUMIFS($C$6:$C$124,$A$6:$A$124,$G22,$B$6:$B$124,N$5) -> 102550.65 | O22: =SUMIFS($C$6:$C$124,$A$6:$A$124,$G22,$B$6:$B$124,O$5) -> 87225.165 | P22: =SUM(I22:O22) -> 837020.01
A23: 45717 | B23: bu-datasci | C23: 199666.2 | D23: 197792.74 | E23: 203002.03 | G23: Total | I23: =SUM(I6:I22) -> 2957101.1 | J23: =SUM(J6:J22) -> 1682818.3 | K23: =SUM(K6:K22) -> 1133940.4 | L23: =SUM(L6:L22) -> 2815330.8 | M23: =SUM(M6:M22) -> 1268389.3 | N23: =SUM(N6:N22) -> 1630794.6 | O23: =SUM(O6:O22) -> 1367224.9 | P23: =SUM(P6:P22) -> 12855600
A24: 45717 | B24: bu-platform | C24: 69367.665 | D24: 56372.595 | E24: 77787.487
A25: 45717 | B25: bu-search | C25: 87877.055 | D25: 69395.702 | E25: 99862.84 | G25: Effective cost is used throughout: it amortises commitments across the period they cover. Billed cost would show prepaid resources as free.
A26: 45717 | B26: unallocated | C26: 75572.938 | D26: 57307.597 | E26: 85723.992
A27: 45748 | B27: bu-assist | C27: 173641.2 | D27: 147917.62 | E27: 190473.95
A28: 45748 | B28: bu-checkout | C28: 91758.287 | D28: 51592.344 | E28: 110942.46
A29: 45748 | B29: bu-datalake | C29: 68648.745 | D29: 54663.854 | E29: 76776.671
A30: 45748 | B30: bu-datasci | C30: 155580.08 | D30: 153718.36 | E30: 158961.84
A31: 45748 | B31: bu-platform | C31: 72773.121 | D31: 60406.694 | E31: 81046.82
A32: 45748 | B32: bu-search | C32: 89750.976 | D32: 69717.822 | E32: 102308.97
A33: 45748 | B33: unallocated | C33: 73834.677 | D33: 56369.364 | E33: 83769.131
A34: 45778 | B34: bu-assist | C34: 168584.86 | D34: 143013.4 | E34: 185353.09
A35: 45778 | B35: bu-checkout | C35: 96378.562 | D35: 54302.444 | E35: 116714.19
A36: 45778 | B36: bu-datalake | C36: 70552.176 | D36: 55686.552 | E36: 79130.746
A37: 45778 | B37: bu-datasci | C37: 161497.27 | D37: 159412.58 | E37: 165662.2
... A124: 46143 | B124: unallocated | C124: 87225.165 | D124: 71175.996 | E124: 98652.246

Sheet 03 Optimization Events
A1: Optimisation events
A2: Every intervention the study measured: what was done, to which resource, when, and what it was costing beforehand. The register the attribution sheet reads.
A3: SIMULATED DATA. The estate is synthetic (FOCUS 1.2, 400 resources, 540 days). Figures illustrate the method; ground truth exists only because the data is simulated.
L4: Events by action
A5: Event | B5: Resource | C5: Business unit | D5: Action | E5: Action date | F5: Trigger z | G5: Donors | H5: Pre-period daily run-rate | I5: Annualised run-rate | L5: Action | M5: Count | N5: Annualised run-rate
A6: i-114 | B6: r-0026 | C6: bu-search | D6: delete_orphaned_volume | E6: 45779 | F6: 2.3954552 | G6: 40 | H6: 125.34635 | I6: =H6*365 -> 45751.417 | L6: cache_inference_results | M6: =COUNTIF($D$6:$D$122,L6) -> 20 | N6: =SUMIF($D$6:$D$122,L6,$I$6:$I$122) -> 724939.68
A7: i-028 | B7: r-0059 | C7: bu-datasci | D7: delete_orphaned_volume | E7: 45793 | F7: 0.71197622 | G7: 40 | H7: 20.056545 | I7: =H7*365 -> 7320.639 | L7: consolidate_cluster | M7: =COUNTIF($D$6:$D$122,L7) -> 14 | N7: =SUMIF($D$6:$D$122,L7,$I$6:$I$122) -> 408333.09
A8: i-088 | B8: r-0260 | C8: bu-platform | D8: cache_inference_results | E8: 45793 | F8: 2.7694056 | G8: 40 | H8: 8.8429833 | I8: =H8*365 -> 3227.6889 | L8: delete_orphaned_volume | M8: =COUNTIF($D$6:$D$122,L8) -> 17 | N8: =SUMIF($D$6:$D$122,L8,$I$6:$I$122) -> 514985.12
A9: i-027 | B9: r-0374 | C9: bu-platform | D9: cache_inference_results | E9: 45793 | F9: 0.72023353 | G9: 40 | H9: 47.16402 | I9: =H9*365 -> 17214.867 | L9: enable_autoscaling | M9: =COUNTIF($D$6:$D$122,L9) -> 13 | N9: =SUMIF($D$6:$D$122,L9,$I$6:$I$122) -> 497301.63
A10: i-030 | B10: r-0097 | C10: bu-checkout | D10: enable_autoscaling | E10: 45797 | F10: 0.70693398 | G10: 40 | H10: 66.663108 | I10: =H10*365 -> 24332.034 | L10: migrate_storage_class | M10: =COUNTIF($D$6:$D$122,L10) -> 17 | N10: =SUMIF($D$6:$D$122,L10,$I$6:$I$122) -> 831654.43
A11: i-049 | B11: r-0372 | C11: bu-checkout | D11: cache_inference_results | E11: 45801 | F11: 0.63210692 | G11: 40 | H11: 182.71683 | I11: =H11*365 -> 66691.642 | L11: rightsize_instance | M11: =COUNTIF($D$6:$D$122,L11) -> 14 | N11: =SUMIF($D$6:$D$122,L11,$I$6:$I$122) -> 409554.87
A12: i-029 | B12: r-0164 | C12: bu-platform | D12: tune_batch_size | E12: 45801 | F12: 0.71166163 | G12: 40 | H12: 24.751056 | I12: =H12*365 -> 9034.1356 | L12: schedule_shutdown | M12: =COUNTIF($D$6:$D$122,L12) -> 12 | N12: =SUMIF($D$6:$D$122,L12,$I$6:$I$122) -> 403691.31
A13: i-011 | B13: r-0352 | C13: bu-datalake | D13: consolidate_cluster | E13: 45805 | F13: 0.89201822 | G13: 40 | H13: 64.279136 | I13: =H13*365 -> 23461.885 | L13: tune_batch_size | M13: =COUNTIF($D$6:$D$122,L13) -> 10 | N13: =SUMIF($D$6:$D$122,L13,$I$6:$I$122) -> 334141.69
A14: i-014 | B14: r-0227 | C14: bu-assist | D14: migrate_storage_class | E14: 45808 | F14: 0.88304188 | G14: 40 | H14: 445.07706 | I14: =H14*365 -> 162453.13 | L14: Total | M14: =SUM(M6:M13) -> 117 | N14: =SUM(N6:N13) -> 4124601.8
A15: i-042 | B15: r-0295 | C15: bu-search | D15: enable_autoscaling | E15: 45815 | F15: 0.65998359 | G15: 40 | H15: 47.877922 | I15: =H15*365 -> 17475.441
A16: i-067 | B16: r-0307 | C16: bu-assist | D16: consolidate_cluster | E16: 45822 | F16: 0.44301192 | G16: 40 | H16: 23.312213 | I16: =H16*365 -> 8508.9576 | L16: Run-rate = mean daily effective cost over the 84 days before the action, the same window the estimator uses.
A17: i-093 | B17: r-0155 | C17: bu-assist | D17: schedule_shutdown | E17: 45824 | F17: 2.6764013 | G17: 40 | H17: 2.108424 | I17: =H17*365 -> 769.57477
A18: i-019 | B18: r-0041 | C18: bu-search | D18: schedule_shutdown | E18: 45825 | F18: 0.79736558 | G18: 40 | H18: 98.729541 | I18: =H18*365 -> 36036.283
A19: i-043 | B19: r-0375 | C19: bu-platform | D19: enable_autoscaling | E19: 45826 | F19: 0.65251775 | G19: 40 | H19: 58.561577 | I19: =H19*365 -> 21374.976
A20: i-034 | B20: r-0314 | C20: bu-assist | D20: enable_autoscaling | E20: 45828 | F20: 0.69057882 | G20: 40 | H20: 448.78342 | I20: =H20*365 -> 163805.95
A21: i-055 | B21: r-0376 | C21: bu-datalake | D21: cache_inference_results | E21: 45828 | F21: 0.55398301 | G21: 40 | H21: 193.65231 | I21: =H21*365 -> 70683.093
A22: i-036 | B22: r-0350 | C22: bu-assist | D22: rightsize_instance | E22: 45831 | F22: 0.68710147 | G22: 40 | H22: 8.9017495 | I22: =H22*365 -> 3249.1386
A23: i-003 | B23: r-0092 | C23: bu-checkout | D23: delete_orphaned_volume | E23: 45832 | F23: 0.99799938 | G23: 40 | H23: 253.43038 | I23: =H23*365 -> 92502.089
A24: i-111 | B24: r-0282 | C24: bu-checkout | D24: rightsize_instance | E24: 45841 | F24: 2.4319834 | G24: 40 | H24: 14.88424 | I24: =H24*365 -> 5432.7477
A25: i-015 | B25: r-0131 | C25: bu-platform | D25: enable_autoscaling | E25: 45842 | F25: 0.85325146 | G25: 40 | H25: 8.1295874 | I25: =H25*365 -> 2967.2994
A26: i-054 | B26: r-0255 | C26: bu-datalake | D26: migrate_storage_class | E26: 45846 | F26: 0.56649971 | G26: 40 | H26: 116.10159 | I26: =H26*365 -> 42377.08
A27: i-090 | B27: r-0000 | C27: bu-search | D27: migrate_storage_class | E27: 45848 | F27: 2.7565139 | G27: 40 | H27: 69.799614 | I27: =H27*365 -> 25476.859
A28: i-097 | B28: r-0005 | C28: bu-platform | D28: delete_orphaned_volume | E28: 45852 | F28: 2.5948097 | G28: 40 | H28: 21.633101 | I28: =H28*365 -> 7896.0818
... A122: i-108 | B122: r-0087 | C122: bu-search | D122: schedule_shutdown | E122: 46150 | F122: 2.468269 | G122: 40 | H122: 48.97083 | I122: =H122*365 -> 17874.353

Sheet 04 Savings Attribution
A1: Savings attribution
A2: What each event is credited with, on what evidence. Before/after is what the industry reports; the identified estimate is difference-in-differences with randomisation inference; the parallel-trends check decides whether it is credible.
A3: SIMULATED DATA. The estate is synthetic (FOCUS 1.2, 400 resources, 540 days). Figures illustrate the method; ground truth exists only because the data is simulated.
A4: Peach columns use ground truth, which exists only because the estate is simulated. A real deployment would not have them -- that is the point of needing an estimator at all.
A5: Event | B5: Business unit | C5: Action | D5: Annualised run-rate | E5: Before/after effect (log) | F5: Before/after annual $ | G5: Identified effect (log) | H5: CI low | I5: CI high | J5: p-value | K5: Parallel trends passed | L5: Credited? | M5: Identified annual $ | N5: Credited annual $ | O5: SIMULATED true effect (log) | P5: SIMULATED true annual $ | Q5: |Before/after − true| | R5: Null event?
A6: ='03 Optimization Events'!A6 -> i-114 | B6: ='03 Optimization Events'!C6 -> bu-search | C6: ='03 Optimization Events'!D6 -> delete_orphaned_volume | D6: ='03 Optimization Events'!I6 -> 45751.417 | E6: -0.1018259 | F6: =-(EXP(E6)-1)*D6 -> 4429.342 | G6: -0.19258744 | H6: =EXP(-0.459706669454089)-1 -> -0.36853115 | I6: =EXP(0.0745317882950329)-1 -> 0.077379591 | J6: 0.17073171 | K6: =TRUE() -> TRUE | L6: =IF('10 Assumptions'!$B$24="Yes",TRUE(),K6) -> TRUE | M6: =-(EXP(G6)-1)*D6 -> 8014.6329 | N6: =IF(L6,M6,0) -> 8014.6329 | O6: 0 | P6: =-(EXP(O6)-1)*D6 -> 0 | Q6: =ABS(F6-P6) -> 4429.342 | R6: =TRUE() -> TRUE
A7: ='03 Optimization Events'!A7 -> i-028 | B7: ='03 Optimization Events'!C7 -> bu-datasci | C7: ='03 Optimization Events'!D7 -> delete_orphaned_volume | D7: ='03 Optimization Events'!I7 -> 7320.639 | E7: -1.111053 | F7: =-(EXP(E7)-1)*D7 -> 4910.5959 | G7: -1.1042475 | H7: =EXP(-1.47780584943431)-1 -> -0.77186229 | I7: =EXP(-0.730689203597679)-1 -> -0.51842303 | J7: 0.024390244 | K7: =TRUE() -> TRUE | L7: =IF('10 Assumptions'!$B$24="Yes",TRUE(),K7) -> TRUE | M7: =-(EXP(G7)-1)*D7 -> 4894.1385 | N7: =IF(L7,M7,0) -> 4894.1385 | O7: -0.94161877 | P7: =-(EXP(O7)-1)*D7 -> 4465.619 | Q7: =ABS(F7-P7) -> 444.97693 | R7: =FALSE() -> FALSE
A8: ='03 Optimization Events'!A8 -> i-088 | B8: ='03 Optimization Events'!C8 -> bu-platform | C8: ='03 Optimization Events'!D8 -> cache_inference_results | D8: ='03 Optimization Events'!I8 -> 3227.6889 | E8: 0.082522121 | F8: =-(EXP(E8)-1)*D8 -> -277.6545 | G8: -0.0040726654 | H8: =EXP(-0.236238693848157)-1 -> -0.21040782 | I8: =EXP(0.228093363012354)-1 -> 0.2562026 | J8: 0.95121951 | K8: =TRUE() -> TRUE | L8: =IF('10 Assumptions'!$B$24="Yes",TRUE(),K8) -> TRUE | M8: =-(EXP(G8)-1)*D8 -> 13.118565 | N8: =IF(L8,M8,0) -> 13.118565 | O8: 0 | P8: =-(EXP(O8)-1)*D8 -> 0 | Q8: =ABS(F8-P8) -> 277.6545 | R8: =TRUE() -> TRUE
A9: ='03 Optimization Events'!A9 -> i-027 | B9: ='03 Optimization Events'!C9 -> bu-platform | C9: ='03 Optimization Events'!D9 -> cache_inference_results | D9: ='03 Optimization Events'!I9 -> 17214.867 | E9: -0.59643523 | F9: =-(EXP(E9)-1)*D9 -> 7733.4087 | G9: -0.69141514 | H9: =EXP(-0.94473403500977)-1 -> -0.61121704 | I9: =EXP(-0.438096243067447)-1 -> -0.35473632 | J9: 0.024390244 | K9: =TRUE() -> TRUE | L9: =IF('10 Assumptions'!$B$24="Yes",TRUE(),K9) -> TRUE | M9: =-(EXP(G9)-1)*D9 -> 8592.5122 | N9: =IF(L9,M9,0) -> 8592.5122 | O9: -1.0258456 | P9: =-(EXP(O9)-1)*D9 -> 11043.454 | Q9: =ABS(F9-P9) -> 3310.0457 | R9: =FALSE() -> FALSE
A10: ='03 Optimization Events'!A10 -> i-030 | B10: ='03 Optimization Events'!C10 -> bu-checkout | C10: ='03 Optimization Events'!D10 -> enable_autoscaling | D10: ='03 Optimization Events'!I10 -> 24332.034 | E10: -1.0068344 | F10: =-(EXP(E10)-1)*D10 -> 15441.747 | G10: -1.0603992 | H10: =EXP(-1.3078909391039)-1 -> -0.72961028 | I10: =EXP(-0.812907457209481)-1 -> -0.55643346 | J10: 0.024390244 | K10: =TRUE() -> TRUE | L10: =IF('10 Assumptions'!$B$24="Yes",TRUE(),K10) -> TRUE | M10: =-(EXP(G10)-1)*D10 -> 15905.424 | N10: =IF(L10,M10,0) -> 15905.424 | O10: -0.960414 | P10: =-(EXP(O10)-1)*D10 -> 15019.328 | Q10: =ABS(F10-P10) -> 422.41881 | R10: =FALSE() -> FALSE
A11: ='03 Optimization Events'!A11 -> i-049 | B11: ='03 Optimization Events'!C11 -> bu-checkout | C11: ='03 Optimization Events'!D11 -> cache_inference_results | D11: ='03 Optimization Events'!I11 -> 66691.642 | E11: -0.83427843 | F11: =-(EXP(E11)-1)*D11 -> 37734.953 | G11: -0.88509515 | H11: =EXP(-1.08292600132974)-1 -> -0.66139668 | I11: =EXP(-0.687264307105471)-1 -> -0.49704989 | J11: 0.024390244 | K11: =TRUE() -> TRUE | L11: =IF('10 Assumptions'!$B$24="Yes",TRUE(),K11) -> TRUE | M11: =-(EXP(G11)-1)*D11 -> 39169.675 | N11: =IF(L11,M11,0) -> 39169.675 | O11: -0.90210242 | P11: =-(EXP(O11)-1)*D11 -> 39633.79 | Q11: =ABS(F11-P11) -> 1898.837 | R11: =FALSE() -> FALSE
A12: ='03 Optimization Events'!A12 -> i-029 | B12: ='03 Optimization Events'!C12 -> bu-platform | C12: ='03 Optimization Events'!D12 -> tune_batch_size | D12: ='03 Optimization Events'!I12 -> 9034.1356 | E12: -0.70813382 | F12: =-(EXP(E12)-1)*D12 -> 4584.2587 | G12: -0.65936562 | H12: =EXP(-0.981535275628546)-1 -> -0.62526467 | I12: =EXP(-0.337195956285617)-1 -> -0.28623104 | J12: 0.024390244 | K12: =TRUE() -> TRUE | L12: =IF('10 Assumptions'!$B$24="Yes",TRUE(),K12) -> TRUE | M12: =-(EXP(G12)-1)*D12 -> 4361.8675 | N12: =IF(L12,M12,0) -> 4361.8675 | O12: -0.78101059 | P12: =-(EXP(O12)-1)*D12 -> 4897.0166 | Q12: =ABS(F12-P12) -> 312.75786 | R12: =FALSE() -> FALSE
A13: ='03 Optimization Events'!A13 -> i-011 | B13: ='03 Optimization Events'!C13 -> bu-datalake | C13: ='03 Optimization Events'!D13 -> consolidate_cluster | D13: ='03 Optimization Events'!I13 -> 23461.885 | E13: -1.2933233 | F13: =-(EXP(E13)-1)*D13 -> 17024.941 | G13: -1.2686402 | H13: =EXP(-1.65030056852937)-1 -> -0.80800781 | I13: =EXP(-0.886979798820441)-1 -> -0.58810211 | J13: 0.024390244 | K13: =TRUE() -> TRUE | L13: =IF('10 Assumptions'!$B$24="Yes",TRUE(),K13) -> TRUE | M13: =-(EXP(G13)-1)*D13 -> 16864.08 | N13: =IF(L13,M13,0) -> 16864.08 | O13: -1.2375593 | P13: =-(EXP(O13)-1)*D13 -> 16655.795 | Q13: =ABS(F13-P13) -> 369.14633 | R13: =FALSE() -> FALSE
A14: ='03 Optimization Events'!A14 -> i-014 | B14: ='03 Optimization Events'!C14 -> bu-assist | C14: ='03 Optimization Events'!D14 -> migrate_storage_class | D14: ='03 Optimization Events'!I14 -> 162453.13 | E14: -1.2301074 | F14: =-(EXP(E14)-1)*D14 -> 114974.38 | G14: -1.1727474 | H14: =EXP(-1.59372946483018)-1 -> -0.79683351 | I14: =EXP(-0.751765345174508)-1 -> -0.5284666 | J14: 0.024390244 | K14: =TRUE() -> TRUE | L14: =IF('10 Assumptions'!$B$24="Yes",TRUE(),K14) -> TRUE | M14: =-(EXP(G14)-1)*D14 -> 112171.38 | N14: =IF(L14,M14,0) -> 112171.38 | O14: -1.0058833 | P14: =-(EXP(O14)-1)*D14 -> 103040.53 | Q14: =ABS(F14-P14) -> 11933.849 | R14: =FALSE() -> FALSE
A15: ='03 Optimization Events'!A15 -> i-042 | B15: ='03 Optimization Events'!C15 -> bu-search | C15: ='03 Optimization Events'!D15 -> enable_autoscaling | D15: ='03 Optimization Events'!I15 -> 17475.441 | E15: -0.44275322 | F15: =-(EXP(E15)-1)*D15 -> 6251.5651 | G15: -0.41317792 | H15: =EXP(-0.842249150766249)-1 -> -0.56925937 | I15: =EXP(0.0158933191841399)-1 -> 0.01602029 | J15: 0.12195122 | K15: =FALSE() -> FALSE | L15: =IF('10 Assumptions'!$B$24="Yes",TRUE(),K15) -> FALSE | M15: =-(EXP(G15)-1)*D15 -> 5914.658 | N15: =IF(L15,M15,0) -> 0 | O15: -0.72587963 | P15: =-(EXP(O15)-1)*D15 -> 9019.0975 | Q15: =ABS(F15-P15) -> 2767.5324 | R15: =FALSE() -> FALSE
A16: ='03 Optimization Events'!A16 -> i-067 | B16: ='03 Optimization Events'!C16 -> bu-assist | C16: ='03 Optimization Events'!D16 -> consolidate_cluster | D16: ='03 Optimization Events'!I16 -> 8508.9576 | E16: -0.62766739 | F16: =-(EXP(E16)-1)*D16 -> 3966.5733 | G16: -0.57325453 | H16: =EXP(-0.993374541074759)-1 -> -0.6296751 | I16: =EXP(-0.153134515973858)-1 -> -0.1419857 | J16: 0.024390244 | K16: =TRUE() -> TRUE | L16: =IF('10 Assumptions'!$B$24="Yes",TRUE(),K16) -> TRUE | M16: =-(EXP(G16)-1)*D16 -> 3712.5611 | N16: =IF(L16,M16,0) -> 3712.5611 | O16: -0.83057537 | P16: =-(EXP(O16)-1)*D16 -> 4800.7669 | Q16: =ABS(F16-P16) -> 834.19363 | R16: =FALSE() -> FALSE
A17: ='03 Optimization Events'!A17 -> i-093 | B17: ='03 Optimization Events'!C17 -> bu-assist | C17: ='03 Optimization Events'!D17 -> schedule_shutdown | D17: ='03 Optimization Events'!I17 -> 769.57477 | E17: 0.67254197 | F17: =-(EXP(E17)-1)*D17 -> -738.18479 | G17: 0.69502651 | H17: =EXP(0.267326956452451)-1 -> 0.30646753 | I17: =EXP(1.12272606426671)-1 -> 2.0732206 | J17: 0.024390244 | K17: =FALSE() -> FALSE | L17: =IF('10 Assumptions'!$B$24="Yes",TRUE(),K17) -> FALSE | M17: =-(EXP(G17)-1)*D17 -> -772.47006 | N17: =IF(L17,M17,0) -> 0 | O17: 0 | P17: =-(EXP(O17)-1)*D17 -> 0 | Q17: =ABS(F17-P17) -> 738.18479 | R17: =TRUE() -> TRUE
A18: ='03 Optimization Events'!A18 -> i-019 | B18: ='03 Optimization Events'!C18 -> bu-search | C18: ='03 Optimization Events'!D18 -> schedule_shutdown | D18: ='03 Optimization Events'!I18 -> 36036.283 | E18: -0.80533933 | F18: =-(EXP(E18)-1)*D18 -> 19930.362 | G18: -0.89976003 | H18: =EXP(-1.08969635379483)-1 -> -0.6636814 | I18: =EXP(-0.709823699894466)-1 -> -0.50826912 | J18: 0.024390244 | K18: =TRUE() -> TRUE | L18: =IF('10 Assumptions'!$B$24="Yes",TRUE(),K18) -> TRUE | M18: =-(EXP(G18)-1)*D18 -> 21381.507 | N18: =IF(L18,M18,0) -> 21381.507 | O18: -0.86920234 | P18: =-(EXP(O18)-1)*D18 -> 20926.779 | Q18: =ABS(F18-P18) -> 996.41676 | R18: =FALSE() -> FALSE
A19: ='03 Optimization Events'!A19 -> i-043 | B19: ='03 Optimization Events'!C19 -> bu-platform | C19: ='03 Optimization Events'!D19 -> enable_autoscaling | D19: ='03 Optimization Events'!I19 -> 21374.976 | E19: -0.60170707 | F19: =-(EXP(E19)-1)*D19 -> 9664.1485 | G19: -0.64540852 | H19: =EXP(-0.894314900052785)-1 -> -0.59111237 | I19: =EXP(-0.39650214473697)-1 -> -0.32733117 | J19: 0.024390244 | K19: =TRUE() -> TRUE | L19: =IF('10 Assumptions'!$B$24="Yes",TRUE(),K19) -> TRUE | M19: =-(EXP(G19)-1)*D19 -> 10164.907 | N19: =IF(L19,M19,0) -> 10164.907 | O19: -0.85609698 | P19: =-(EXP(O19)-1)*D19 -> 12294.524 | Q19: =ABS(F19-P19) -> 2630.3758 | R19: =FALSE() -> FALSE
A20: ='03 Optimization Events'!A20 -> i-034 | B20: ='03 Optimization Events'!C20 -> bu-assist | C20: ='03 Optimization Events'!D20 -> enable_autoscaling | D20: ='03 Optimization Events'!I20 -> 163805.95 | E20: -0.38426936 | F20: =-(EXP(E20)-1)*D20 -> 52262.619 | G20: -0.36486612 | H20: =EXP(-0.807185402010445)-1 -> -0.55388807 | I20: =EXP(0.0774531573204561)-1 -> 0.080531616 | J20: 0.19512195 | K20: =FALSE() -> FALSE | L20: =IF('10 Assumptions'!$B$24="Yes",TRUE(),K20) -> FALSE | M20: =-(EXP(G20)-1)*D20 -> 50077.183 | N20: =IF(L20,M20,0) -> 0 | O20: -0.77597352 | P20: =-(EXP(O20)-1)*D20 -> 88413.361 | Q20: =ABS(F20-P20) -> 36150.742 | R20: =FALSE() -> FALSE
A21: ='03 Optimization Events'!A21 -> i-055 | B21: ='03 Optimization Events'!C21 -> bu-datalake | C21: ='03 Optimization Events'!D21 -> cache_inference_results | D21: ='03 Optimization Events'!I21 -> 70683.093 | E21: -0.78331463 | F21: =-(EXP(E21)-1)*D21 -> 38388.759 | G21: -0.78998953 | H21: =EXP(-1.10274952830287)-1 -> -0.6680429 | I21: =EXP(-0.47722952854347)-1 -> -0.37949991 | J21: 0.024390244 | K21: =TRUE() -> TRUE | L21: =IF('10 Assumptions'!$B$24="Yes",TRUE(),K21) -> TRUE | M21: =-(EXP(G21)-1)*D21 -> 38603.603 | N21: =IF(L21,M21,0) -> 38603.603 | O21: -0.82358533 | P21: =-(EXP(O21)-1)*D21 -> 39663.437 | Q21: =ABS(F21-P21) -> 1274.6773 | R21: =FALSE() -> FALSE
A22: ='03 Optimization Events'!A22 -> i-036 | B22: ='03 Optimization Events'!C22 -> bu-assist | C22: ='03 Optimization Events'!D22 -> rightsize_instance | D22: ='03 Optimization Events'!I22 -> 3249.1386 | E22: -1.2255938 | F22: =-(EXP(E22)-1)*D22 -> 2295.2457 | G22: -1.2088499 | H22: =EXP(-1.43907270289978)-1 -> -0.76285244 | I22: =EXP(-0.978627170355868)-1 -> -0.62417331 | J22: 0.024390244 | K22: =TRUE() -> TRUE | L22: =IF('10 Assumptions'!$B$24="Yes",TRUE(),K22) -> TRUE | M22: =-(EXP(G22)-1)*D22 -> 2279.1394 | N22: =IF(L22,M22,0) -> 2279.1394 | O22: -1.0937074 | P22: =-(EXP(O22)-1)*D22 -> 2160.7671 | Q22: =ABS(F22-P22) -> 134.47859 | R22: =FALSE() -> FALSE
A23: ='03 Optimization Events'!A23 -> i-003 | B23: ='03 Optimization Events'!C23 -> bu-checkout | C23: ='03 Optimization Events'!D23 -> delete_orphaned_volume | D23: ='03 Optimization Events'!I23 -> 92502.089 | E23: -1.1978992 | F23: =-(EXP(E23)-1)*D23 -> 64582.402 | G23: -1.2453427 | H23: =EXP(-1.49428739641576)-1 -> -0.77559154 | I23: =EXP(-0.996397963183087)-1 -> -0.63079305 | J23: 0.024390244 | K23: =TRUE() -> TRUE | L23: =IF('10 Assumptions'!$B$24="Yes",TRUE(),K23) -> TRUE | M23: =-(EXP(G23)-1)*D23 -> 65876.079 | N23: =IF(L23,M23,0) -> 65876.079 | O23: -1.2483525 | P23: =-(EXP(O23)-1)*D23 -> 65956.097 | Q23: =ABS(F23-P23) -> 1373.695 | R23: =FALSE() -> FALSE
A24: ='03 Optimization Events'!A24 -> i-111 | B24: ='03 Optimization Events'!C24 -> bu-checkout | C24: ='03 Optimization Events'!D24 -> rightsize_instance | D24: ='03 Optimization Events'!I24 -> 5432.7477 | E24: -0.02872515 | F24: =-(EXP(E24)-1)*D24 -> 153.83643 | G24: -0.10681438 | H24: =EXP(-0.272007869891729)-1 -> -0.23815173 | I24: =EXP(0.0583791157011727)-1 -> 0.060116826 | J24: 0.24390244 | K24: =FALSE() -> FALSE | L24: =IF('10 Assumptions'!$B$24="Yes",TRUE(),K24) -> FALSE | M24: =-(EXP(G24)-1)*D24 -> 550.37822 | N24: =IF(L24,M24,0) -> 0 | O24: 0 | P24: =-(EXP(O24)-1)*D24 -> 0 | Q24: =ABS(F24-P24) -> 153.83643 | R24: =TRUE() -> TRUE
A25: ='03 Optimization Events'!A25 -> i-015 | B25: ='03 Optimization Events'!C25 -> bu-platform | C25: ='03 Optimization Events'!D25 -> enable_autoscaling | D25: ='03 Optimization Events'!I25 -> 2967.2994 | E25: -1.0403725 | F25: =-(EXP(E25)-1)*D25 -> 1918.8842 | G25: -1.0226787 | H25: =EXP(-1.27906004265867)-1 -> -0.72170123 | I25: =EXP(-0.766297445158814)-1 -> -0.53526942 | J25: 0.024390244 | K25: =TRUE() -> TRUE | L25: =IF('10 Assumptions'!$B$24="Yes",TRUE(),K25) -> TRUE | M25: =-(EXP(G25)-1)*D25 -> 1900.1687 | N25: =IF(L25,M25,0) -> 1900.1687 | O25: -1.1358284 | P25: =-(EXP(O25)-1)*D25 -> 2014.3335 | Q25: =ABS(F25-P25) -> 95.449299 | R25: =FALSE() -> FALSE
A26: ='03 Optimization Events'!A26 -> i-054 | B26: ='03 Optimization Events'!C26 -> bu-datalake | C26: ='03 Optimization Events'!D26 -> migrate_storage_class | D26: ='03 Optimization Events'!I26 -> 42377.08 | E26: -1.0294728 | F26: =-(EXP(E26)-1)*D26 -> 27240.189 | G26: -1.0634189 | H26: =EXP(-1.39852654753326)-1 -> -0.75303942 | I26: =EXP(-0.728311244810419)-1 -> -0.5172765 | J26: 0.024390244 | K26: =TRUE() -> TRUE | L26: =IF('10 Assumptions'!$B$24="Yes",TRUE(),K26) -> TRUE | M26: =-(EXP(G26)-1)*D26 -> 27745.404 | N26: =IF(L26,M26,0) -> 27745.404 | O26: -0.90785851 | P26: =-(EXP(O26)-1)*D26 -> 25282.71 | Q26: =ABS(F26-P26) -> 1957.4783 | R26: =FALSE() -> FALSE
A27: ='03 Optimization Events'!A27 -> i-090 | B27: ='03 Optimization Events'!C27 -> bu-search | C27: ='03 Optimization Events'!D27 -> migrate_storage_class | D27: ='03 Optimization Events'!I27 -> 25476.859 | E27: 0.17652457 | F27: =-(EXP(E27)-1)*D27 -> -4918.6578 | G27: 0.14463481 | H27: =EXP(-0.0914332288552578)-1 -> -0.087377749 | I27: =EXP(0.380702852991075)-1 -> 0.46331272 | J27: 0.14634146 | K27: =TRUE() -> TRUE | L27: =IF('10 Assumptions'!$B$24="Yes",TRUE(),K27) -> TRUE | M27: =-(EXP(G27)-1)*D27 -> -3964.6445 | N27: =IF(L27,M27,0) -> -3964.6445 | O27: 0 | P27: =-(EXP(O27)-1)*D27 -> 0 | Q27: =ABS(F27-P27) -> 4918.6578 | R27: =TRUE() -> TRUE
A28: ='03 Optimization Events'!A28 -> i-097 | B28: ='03 Optimization Events'!C28 -> bu-platform | C28: ='03 Optimization Events'!D28 -> delete_orphaned_volume | D28: ='03 Optimization Events'!I28 -> 7896.0818 | E28: 0.083566987 | F28: =-(EXP(E28)-1)*D28 -> -688.207 | G28: 0.031886179 | H28: =EXP(-0.292498788829419)-1 -> -0.25360385 | I28: =EXP(0.356271146249154)-1 -> 0.42799469 | J28: 0.95121951 | K28: =TRUE() -> TRUE | L28: =IF('10 Assumptions'!$B$24="Yes",TRUE(),K28) -> TRUE | M28: =-(EXP(G28)-1)*D28 -> -255.83297 | N28: =IF(L28,M28,0) -> -255.83297 | O28: 0 | P28: =-(EXP(O28)-1)*D28 -> 0 | Q28: =ABS(F28-P28) -> 688.207 | R28: =TRUE() -> TRUE
A29: ='03 Optimization Events'!A29 -> i-075 | B29: ='03 Optimization Events'!C29 -> bu-platform | C29: ='03 Optimization Events'!D29 -> tune_batch_size | D29: ='03 Optimization Events'!I29 -> 7165.3189 | E29: -0.56318877 | F29: =-(EXP(E29)-1)*D29 -> 3085.4543 | G29: -0.59799103 | H29: =EXP(-0.82865767349973)-1 -> -0.563365 | I29: =EXP(-0.367324393786616)-1 -> -0.30741506 | J29: 0.024390244 | K29: =TRUE() -> TRUE | L29: =IF('10 Assumptions'!$B$24="Yes",TRUE(),K29) -> TRUE | M29: =-(EXP(G29)-1)*D29 -> 3225.0005 | N29: =IF(L29,M29,0) -> 3225.0005 | O29: -0.58631919 | P29: =-(EXP(O29)-1)*D29 -> 3178.7403 | Q29: =ABS(F29-P29) -> 93.285938 | R29: =FALSE() -> FALSE
A30: ='03 Optimization Events'!A30 -> i-070 | B30: ='03 Optimization Events'!C30 -> bu-search | C30: ='03 Optimization Events'!D30 -> migrate_storage_class | D30: ='03 Optimization Events'!I30 -> 15149.339 | E30: -0.62345999 | F30: =-(EXP(E30)-1)*D30 -> 7027.9848 | G30: -0.60291621 | H30: =EXP(-0.851655304037839)-1 -> -0.57329198 | I30: =EXP(-0.354177109585918)-1 -> -0.29824933 | J30: 0.024390244 | K30: =TRUE() -> TRUE | L30: =IF('10 Assumptions'!$B$24="Yes",TRUE(),K30) -> TRUE | M30: =-(EXP(G30)-1)*D30 -> 6859.4158 | N30: =IF(L30,M30,0) -> 6859.4158 | O30: -0.61376735 | P30: =-(EXP(O30)-1)*D30 -> 6948.8847 | Q30: =ABS(F30-P30) -> 79.100081 | R30: =FALSE() -> FALSE
A31: ='03 Optimization Events'!A31 -> i-079 | B31: ='03 Optimization Events'!C31 -> bu-datasci | C31: ='03 Optimization Events'!D31 -> consolidate_cluster | D31: ='03 Optimization Events'!I31 -> 24354.612 | E31: -0.71271701 | F31: =-(EXP(E31)-1)*D31 -> 12413.297 | G31: -0.67857179 | H31: =EXP(-0.973573708624723)-1 -> -0.62226928 | I31: =EXP(-0.383569861668891)-1 -> -0.31857553 | J31: 0.024390244 | K31: =TRUE() -> TRUE | L31: =IF('10 Assumptions'!$B$24="Yes",TRUE(),K31) -> TRUE | M31: =-(EXP(G31)-1)*D31 -> 11998.517 | N31: =IF(L31,M31,0) -> 11998.517 | O31: -0.61785884 | P31: =-(EXP(O31)-1)*D31 -> 11225.102 | Q31: =ABS(F31-P31) -> 1188.1955 | R31: =FALSE() -> FALSE
A32: ='03 Optimization Events'!A32 -> i-005 | B32: ='03 Optimization Events'!C32 -> bu-platform | C32: ='03 Optimization Events'!D32 -> tune_batch_size | D32: ='03 Optimization Events'!I32 -> 16912.919 | E32: -0.82039874 | F32: =-(EXP(E32)-1)*D32 -> 9466.9035 | G32: -0.82625157 | H32: =EXP(-1.11231679036596)-1 -> -0.67120367 | I32: =EXP(-0.540186357433524)-1 -> -0.41736034 | J32: 0.024390244 | K32: =TRUE() -> TRUE | L32: =IF('10 Assumptions'!$B$24="Yes",TRUE(),K32) -> TRUE | M32: =-(EXP(G32)-1)*D32 -> 9510.3565 | N32: =IF(L32,M32,0) -> 9510.3565 | O32: -1.0556884 | P32: =-(EXP(O32)-1)*D32 -> 11028.021 | Q32: =ABS(F32-P32) -> 1561.1176 | R32: =FALSE() -> FALSE
A33: ='03 Optimization Events'!A33 -> i-002 | B33: ='03 Optimization Events'!C33 -> bu-checkout | C33: ='03 Optimization Events'!D33 -> tune_batch_size | D33: ='03 Optimization Events'!I33 -> 11589.513 | E33: -1.133623 | F33: =-(EXP(E33)-1)*D33 -> 7859.2541 | G33: -1.1807293 | H33: =EXP(-1.45450359792976)-1 -> -0.76648375 | I33: =EXP(-0.906955056912496)-1 -> -0.59624824 | J33: 0.024390244 | K33: =TRUE() -> TRUE | L33: =IF('10 Assumptions'!$B$24="Yes",TRUE(),K33) -> TRUE | M33: =-(EXP(G33)-1)*D33 -> 8030.8986 | N33: =IF(L33,M33,0) -> 8030.8986 | O33: -1.3353975 | P33: =-(EXP(O33)-1)*D33 -> 8540.8502 | Q33: =ABS(F33-P33) -> 681.59611 | R33: =FALSE() -> FALSE
A34: ='03 Optimization Events'!A34 -> i-026 | B34: ='03 Optimization Events'!C34 -> bu-search | C34: ='03 Optimization Events'!D34 -> enable_autoscaling | D34: ='03 Optimization Events'!I34 -> 4349.0941 | E34: -0.77409375 | F34: =-(EXP(E34)-1)*D34 -> 2343.6334 | G34: -0.7994295 | H34: =EXP(-1.08646207121041)-1 -> -0.66259189 | I34: =EXP(-0.512396918988007)-1 -> -0.40094204 | J34: 0.024390244 | K34: =TRUE() -> TRUE | L34: =IF('10 Assumptions'!$B$24="Yes",TRUE(),K34) -> TRUE | M34: =-(EXP(G34)-1)*D34 -> 2393.805 | N34: =IF(L34,M34,0) -> 2393.805 | O34: -0.92327601 | P34: =-(EXP(O34)-1)*D34 -> 2621.566 | Q34: =ABS(F34-P34) -> 277.9326 | R34: =FALSE() -> FALSE
A35: ='03 Optimization Events'!A35 -> i-076 | B35: ='03 Optimization Events'!C35 -> bu-datasci | C35: ='03 Optimization Events'!D35 -> rightsize_instance | D35: ='03 Optimization Events'!I35 -> 139435.03 | E35: -0.36768334 | F35: =-(EXP(E35)-1)*D35 -> 42899.086 | G35: -0.28204118 | H35: =EXP(-0.593903561551567)-1 -> -0.44783235 | I35: =EXP(0.0298212106553653)-1 -> 0.030270316 | J35: 0.073170732 | K35: =TRUE() -> TRUE | L35: =IF('10 Assumptions'!$B$24="Yes",TRUE(),K35) -> TRUE | M35: =-(EXP(G35)-1)*D35 -> 34267.187 | N35: =IF(L35,M35,0) -> 34267.187 | O35: -0.40393074 | P35: =-(EXP(O35)-1)*D35 -> 46335.605 | Q35: =ABS(F35-P35) -> 3436.5186 | R35: =FALSE() -> FALSE
A36: ='03 Optimization Events'!A36 -> i-056 | B36: ='03 Optimization Events'!C36 -> bu-search | C36: ='03 Optimization Events'!D36 -> migrate_storage_class | D36: ='03 Optimization Events'!I36 -> 7423.0138 | E36: -0.35282599 | F36: =-(EXP(E36)-1)*D36 -> 2206.866 | G36: -0.42827614 | H36: =EXP(-0.819109698773683)-1 -> -0.55917605 | I36: =EXP(-0.0374425755300337)-1 -> -0.03675027 | J36: 0.12195122 | K36: =FALSE() -> FALSE | L36: =IF('10 Assumptions'!$B$24="Yes",TRUE(),K36) -> FALSE | M36: =-(EXP(G36)-1)*D36 -> 2585.9445 | N36: =IF(L36,M36,0) -> 0 | O36: -0.65934113 | P36: =-(EXP(O36)-1)*D36 -> 3583.8906 | Q36: =ABS(F36-P36) -> 1377.0246 | R36: =FALSE() -> FALSE
A37: ='03 Optimization Events'!A37 -> i-035 | B37: ='03 Optimization Events'!C37 -> bu-platform | C37: ='03 Optimization Events'!D37 -> consolidate_cluster | D37: ='03 Optimization Events'!I37 -> 10768.238 | E37: -0.96709449 | F37: =-(EXP(E37)-1)*D37 -> 6674.304 | G37: -0.93369618 | H37: =EXP(-1.31344241563948)-1 -> -0.73110718 | I37: =EXP(-0.553949937313814)-1 -> -0.42532461 | J37: 0.024390244 | K37: =TRUE() -> TRUE | L37: =IF('10 Assumptions'!$B$24="Yes",TRUE(),K37) -> TRUE | M37: =-(EXP(G37)-1)*D37 -> 6535.2646 | N37: =IF(L37,M37,0) -> 6535.2646 | O37: -1.0040153 | P37: =-(EXP(O37)-1)*D37 -> 6822.6991 | Q37: =ABS(F37-P37) -> 148.39512 | R37: =FALSE() -> FALSE
A38: ='03 Optimization Events'!A38 -> i-044 | B38: ='03 Optimization Events'!C38 -> bu-search | C38: ='03 Optimization Events'!D38 -> enable_autoscaling | D38: ='03 Optimization Events'!I38 -> 13007.061 | E38: -0.8250467 | F38: =-(EXP(E38)-1)*D38 -> 7307.178 | G38: -0.84960215 | H38: =EXP(-1.03819559800658)-1 -> -0.64590697 | I38: =EXP(-0.661008702523781)-1 -> -0.48366975 | J38: 0.024390244 | K38: =TRUE() -> TRUE | L38: =IF('10 Assumptions'!$B$24="Yes",TRUE(),K38) -> TRUE | M38: =-(EXP(G38)-1)*D38 -> 7445.4367 | N38: =IF(L38,M38,0) -> 7445.4367 | O38: -0.85787993 | P38: =-(EXP(O38)-1)*D38 -> 7491.2846 | Q38: =ABS(F38-P38) -> 184.10662 | R38: =FALSE() -> FALSE
A39: ='03 Optimization Events'!A39 -> i-094 | B39: ='03 Optimization Events'!C39 -> bu-platform | C39: ='03 Optimization Events'!D39 -> tune_batch_size | D39: ='03 Optimization Events'!I39 -> 61120.375 | E39: 0.094824384 | F39: =-(EXP(E39)-1)*D39 -> -6079.3842 | G39: -0.012108413 | H39: =EXP(-0.419832833021877)-1 -> -0.34284333 | I39: =EXP(0.395616007330647)-1 -> 0.48529886 | J39: 0.87804878 | K39: =TRUE() -> TRUE | L39: =IF('10 Assumptions'!$B$24="Yes",TRUE(),K39) -> TRUE | M39: =-(EXP(G39)-1)*D39 -> 735.60822 | N39: =IF(L39,M39,0) -> 735.60822 | O39: 0 | P39: =-(EXP(O39)-1)*D39 -> 0 | Q39: =ABS(F39-P39) -> 6079.3842 | R39: =TRUE() -> TRUE
A40: ='03 Optimization Events'!A40 -> i-080 | B40: ='03 Optimization Events'!C40 -> bu-checkout | C40: ='03 Optimization Events'!D40 -> schedule_shutdown | D40: ='03 Optimization Events'!I40 -> 9665.808 | E40: -0.47328806 | F40: =-(EXP(E40)-1)*D40 -> 3644.4871 | G40: -0.5541449 | H40: =EXP(-0.709551548481789)-1 -> -0.50813527 | I40: =EXP(-0.398738246352189)-1 -> -0.32883364 | J40: 0.024390244 | K40: =TRUE() -> TRUE | L40: =IF('10 Assumptions'!$B$24="Yes",TRUE(),K40) -> TRUE | M40: =-(EXP(G40)-1)*D40 -> 4112.1889 | N40: =IF(L40,M40,0) -> 4112.1889 | O40: -0.47783794 | P40: =-(EXP(O40)-1)*D40 -> 3671.8212 | Q40: =ABS(F40-P40) -> 27.334059 | R40: =FALSE() -> FALSE
A41: ='03 Optimization Events'!A41 -> i-061 | B41: ='03 Optimization Events'!C41 -> bu-platform | C41: ='03 Optimization Events'!D41 -> delete_orphaned_volume | D41: ='03 Optimization Events'!I41 -> 1131.3362 | E41: -0.62200298 | F41: =-(EXP(E41)-1)*D41 -> 523.95795 | G41: -0.69430226 | H41: =EXP(-0.983564970677505)-1 -> -0.62602449 | I41: =EXP(-0.405039558008002)-1 -> -0.33304957 | J41: 0.024390244 | K41: =TRUE() -> TRUE | L41: =IF('10 Assumptions'!$B$24="Yes",TRUE(),K41) -> TRUE | M41: =-(EXP(G41)-1)*D41 -> 566.3211 | N41: =IF(L41,M41,0) -> 566.3211 | O41: -0.83046272 | P41: =-(EXP(O41)-1)*D41 -> 638.24605 | Q41: =ABS(F41-P41) -> 114.2881 | R41: =FALSE() -> FALSE
A42: ='03 Optimization Events'!A42 -> i-018 | B42: ='03 Optimization Events'!C42 -> bu-assist | C42: ='03 Optimization Events'!D42 -> rightsize_instance | D42: ='03 Optimization Events'!I42 -> 3070.769 | E42: -2.131101 | F42: =-(EXP(E42)-1)*D42 -> 2706.2487 | G42: -2.0123143 | H42: =EXP(-2.36127097155564)-1 -> -0.90569971 | I42: =EXP(-1.66335772271909)-1 -> -0.81049838 | J42: 0.024390244 | K42: =TRUE() -> TRUE | L42: =IF('10 Assumptions'!$B$24="Yes",TRUE(),K42) -> TRUE | M42: =-(EXP(G42)-1)*D42 -> 2660.2718 | N42: =IF(L42,M42,0) -> 2660.2718 | O42: -1.202302 | P42: =-(EXP(O42)-1)*D42 -> 2147.9978 | Q42: =ABS(F42-P42) -> 558.25087 | R42: =FALSE() -> FALSE
A43: ='03 Optimization Events'!A43 -> i-012 | B43: ='03 Optimization Events'!C43 -> bu-datalake | C43: ='03 Optimization Events'!D43 -> rightsize_instance | D43: ='03 Optimization Events'!I43 -> 43215.969 | E43: -1.0234411 | F43: =-(EXP(E43)-1)*D43 -> 27686.042 | G43: -0.90823787 | H43: =EXP(-1.18380872252231)-1 -> -0.69388937 | I43: =EXP(-0.632667008097409)-1 -> -0.46882673 | J43: 0.024390244 | K43: =TRUE() -> TRUE | L43: =IF('10 Assumptions'!$B$24="Yes",TRUE(),K43) -> TRUE | M43: =-(EXP(G43)-1)*D43 -> 25789.814 | N43: =IF(L43,M43,0) -> 25789.814 | O43: -0.96676792 | P43: =-(EXP(O43)-1)*D43 -> 26780.493 | Q43: =ABS(F43-P43) -> 905.54835 | R43: =FALSE() -> FALSE
A44: ='03 Optimization Events'!A44 -> i-046 | B44: ='03 Optimization Events'!C44 -> bu-assist | C44: ='03 Optimization Events'!D44 -> rightsize_instance | D44: ='03 Optimization Events'!I44 -> 43393.148 | E44: -0.92234872 | F44: =-(EXP(E44)-1)*D44 -> 26140.721 | G44: -0.87597791 | H44: =EXP(-1.11056291175308)-1 -> -0.6706265 | I44: =EXP(-0.64139289897905)-1 -> -0.47344153 | J44: 0.024390244 | K44: =TRUE() -> TRUE | L44: =IF('10 Assumptions'!$B$24="Yes",TRUE(),K44) -> TRUE | M44: =-(EXP(G44)-1)*D44 -> 25321.873 | N44: =IF(L44,M44,0) -> 25321.873 | O44: -0.97896909 | P44: =-(EXP(O44)-1)*D44 -> 27090.42 | Q44: =ABS(F44-P44) -> 949.6988 | R44: =FALSE() -> FALSE
A45: ='03 Optimization Events'!A45 -> i-087 | B45: ='03 Optimization Events'!C45 -> bu-checkout | C45: ='03 Optimization Events'!D45 -> migrate_storage_class | D45: ='03 Optimization Events'!I45 -> 107190.6 | E45: 0.38164922 | F45: =-(EXP(E45)-1)*D45 -> -49811.278 | G45: 0.24125942 | H45: =EXP(-0.0573143693751691)-1 -> -0.055702835 | I45: =EXP(0.539833216078448)-1 -> 0.71572068 | J45: 0.14634146 | K45: =FALSE() -> FALSE | L45: =IF('10 Assumptions'!$B$24="Yes",TRUE(),K45) -> FALSE | M45: =-(EXP(G45)-1)*D45 -> -29247.083 | N45: =IF(L45,M45,0) -> 0 | O45: 0 | P45: =-(EXP(O45)-1)*D45 -> 0 | Q45: =ABS(F45-P45) -> 49811.278 | R45: =TRUE() -> TRUE
A46: ='03 Optimization Events'!A46 -> i-037 | B46: ='03 Optimization Events'!C46 -> bu-datalake | C46: ='03 Optimization Events'!D46 -> migrate_storage_class | D46: ='03 Optimization Events'!I46 -> 28532.007 | E46: -0.97792436 | F46: =-(EXP(E46)-1)*D46 -> 17801.379 | G46: -0.98490795 | H46: =EXP(-1.23900147970255)-1 -> -0.71032668 | I46: =EXP(-0.730814420616451)-1 -> -0.51848333 | J46: 0.024390244 | K46: =TRUE() -> TRUE | L46: =IF('10 Assumptions'!$B$24="Yes",TRUE(),K46) -> TRUE | M46: =-(EXP(G46)-1)*D46 -> 17876.056 | N46: =IF(L46,M46,0) -> 17876.056 | O46: -1.0994655 | P46: =-(EXP(O46)-1)*D46 -> 19029.449 | Q46: =ABS(F46-P46) -> 1228.0705 | R46: =FALSE() -> FALSE
A47: ='03 Optimization Events'!A47 -> i-059 | B47: ='03 Optimization Events'!C47 -> bu-checkout | C47: ='03 Optimization Events'!D47 -> migrate_storage_class | D47: ='03 Optimization Events'!I47 -> 1365.9815 | E47: -0.36227089 | F47: =-(EXP(E47)-1)*D47 -> 415.13029 | G47: -0.41637944 | H47: =EXP(-0.655644980806071)-1 -> -0.48089286 | I47: =EXP(-0.177113904629447)-1 -> -0.16231564 | J47: 0.048780488 | K47: =TRUE() -> TRUE | L47: =IF('10 Assumptions'!$B$24="Yes",TRUE(),K47) -> TRUE | M47: =-(EXP(G47)-1)*D47 -> 465.21232 | N47: =IF(L47,M47,0) -> 465.21232 | O47: -0.60538332 | P47: =-(EXP(O47)-1)*D47 -> 620.33983 | Q47: =ABS(F47-P47) -> 205.20954 | R47: =FALSE() -> FALSE
A48: ='03 Optimization Events'!A48 -> i-116 | B48: ='03 Optimization Events'!C48 -> bu-platform | C48: ='03 Optimization Events'!D48 -> schedule_shutdown | D48: ='03 Optimization Events'!I48 -> 14530.618 | E48: 0.021144805 | F48: =-(EXP(E48)-1)*D48 -> -310.51843 | G48: 0.032451101 | H48: =EXP(-0.30023429743725)-1 -> -0.25935533 | I48: =EXP(0.365136498553498)-1 -> 0.44071065 | J48: 0.7804878 | K48: =TRUE() -> TRUE | L48: =IF('10 Assumptions'!$B$24="Yes",TRUE(),K48) -> TRUE | M48: =-(EXP(G48)-1)*D48 -> -479.26888 | N48: =IF(L48,M48,0) -> -479.26888 | O48: 0 | P48: =-(EXP(O48)-1)*D48 -> 0 | Q48: =ABS(F48-P48) -> 310.51843 | R48: =TRUE() -> TRUE
A49: ='03 Optimization Events'!A49 -> i-089 | B49: ='03 Optimization Events'!C49 -> bu-platform | C49: ='03 Optimization Events'!D49 -> migrate_storage_class | D49: ='03 Optimization Events'!I49 -> 6259.4221 | E49: 0.59423787 | F49: =-(EXP(E49)-1)*D49 -> -5080.4581 | G49: 0.61050048 | H49: =EXP(0.110934103211983)-1 -> 0.11732128 | I49: =EXP(1.11006686554277)-1 -> 2.0345613 | J49: 0.024390244 | K49: =FALSE() -> FALSE | L49: =IF('10 Assumptions'!$B$24="Yes",TRUE(),K49) -> FALSE | M49: =-(EXP(G49)-1)*D49 -> -5266.3819 | N49: =IF(L49,M49,0) -> 0 | O49: 0 | P49: =-(EXP(O49)-1)*D49 -> 0 | Q49: =ABS(F49-P49) -> 5080.4581 | R49: =TRUE() -> TRUE
A50: ='03 Optimization Events'!A50 -> i-085 | B50: ='03 Optimization Events'!C50 -> bu-datalake | C50: ='03 Optimization Events'!D50 -> migrate_storage_class | D50: ='03 Optimization Events'!I50 -> 5404.2321 | E50: -0.23309987 | F50: =-(EXP(E50)-1)*D50 -> 1123.6778 | G50: -0.23496876 | H50: =EXP(-0.501595192597264)-1 -> -0.3944361 | I50: =EXP(0.0316576715378505)-1 -> 0.032164106 | J50: 0.12195122 | K50: =TRUE() -> TRUE | L50: =IF('10 Assumptions'!$B$24="Yes",TRUE(),K50) -> TRUE | M50: =-(EXP(G50)-1)*D50 -> 1131.6703 | N50: =IF(L50,M50,0) -> 1131.6703 | O50: -0.27641293 | P50: =-(EXP(O50)-1)*D50 -> 1305.1239 | Q50: =ABS(F50-P50) -> 181.44606 | R50: =FALSE() -> FALSE
A51: ='03 Optimization Events'!A51 -> i-086 | B51: ='03 Optimization Events'!C51 -> bu-datasci | C51: ='03 Optimization Events'!D51 -> consolidate_cluster | D51: ='03 Optimization Events'!I51 -> 81082.081 | E51: -0.2872188 | F51: =-(EXP(E51)-1)*D51 -> 20242.342 | G51: -0.24150589 | H51: =EXP(-0.502384683673019)-1 -> -0.394914 | I51: =EXP(0.019372907949768)-1 -> 0.01956178 | J51: 0.14634146 | K51: =TRUE() -> TRUE | L51: =IF('10 Assumptions'!$B$24="Yes",TRUE(),K51) -> TRUE | M51: =-(EXP(G51)-1)*D51 -> 17396.632 | N51: =IF(L51,M51,0) -> 17396.632 | O51: -0.34207804 | P51: =-(EXP(O51)-1)*D51 -> 23490.065 | Q51: =ABS(F51-P51) -> 3247.7235 | R51: =FALSE() -> FALSE
A52: ='03 Optimization Events'!A52 -> i-001 | B52: ='03 Optimization Events'!C52 -> bu-assist | C52: ='03 Optimization Events'!D52 -> rightsize_instance | D52: ='03 Optimization Events'!I52 -> 64023.333 | E52: -1.1736418 | F52: =-(EXP(E52)-1)*D52 -> 44224.84 | G52: -1.1310795 | H52: =EXP(-1.42847988828891)-1 -> -0.76032702 | I52: =EXP(-0.833679016096122)-1 -> -0.565552 | J52: 0.024390244 | K52: =TRUE() -> TRUE | L52: =IF('10 Assumptions'!$B$24="Yes",TRUE(),K52) -> TRUE | M52: =-(EXP(G52)-1)*D52 -> 43363.98 | N52: =IF(L52,M52,0) -> 43363.98 | O52: -1.2175648 | P52: =-(EXP(O52)-1)*D52 -> 45075.628 | Q52: =ABS(F52-P52) -> 850.78784 | R52: =FALSE() -> FALSE
A53: ='03 Optimization Events'!A53 -> i-038 | B53: ='03 Optimization Events'!C53 -> bu-search | C53: ='03 Optimization Events'!D53 -> rightsize_instance | D53: ='03 Optimization Events'!I53 -> 9391.4792 | E53: -0.66977003 | F53: =-(EXP(E53)-1)*D53 -> 4584.6735 | G53: -0.77632993 | H53: =EXP(-1.03255505587571)-1 -> -0.64390405 | I53: =EXP(-0.520104813022649)-1 -> -0.40554176 | J53: 0.024390244 | K53: =TRUE() -> TRUE | L53: =IF('10 Assumptions'!$B$24="Yes",TRUE(),K53) -> TRUE | M53: =-(EXP(G53)-1)*D53 -> 5070.5396 | N53: =IF(L53,M53,0) -> 5070.5396 | O53: -0.73966229 | P53: =-(EXP(O53)-1)*D53 -> 4909.1603 | Q53: =ABS(F53-P53) -> 324.48687 | R53: =FALSE() -> FALSE
A54: ='03 Optimization Events'!A54 -> i-068 | B54: ='03 Optimization Events'!C54 -> bu-platform | C54: ='03 Optimization Events'!D54 -> tune_batch_size | D54: ='03 Optimization Events'!I54 -> 6615.1218 | E54: -0.42674262 | F54: =-(EXP(E54)-1)*D54 -> 2297.8849 | G54: -0.48538725 | H54: =EXP(-0.858545612706266)-1 -> -0.57622203 | I54: =EXP(-0.112228890953607)-1 -> -0.10616036 | J54: 0.048780488 | K54: =TRUE() -> TRUE | L54: =IF('10 Assumptions'!$B$24="Yes",TRUE(),K54) -> TRUE | M54: =-(EXP(G54)-1)*D54 -> 2543.7868 | N54: =IF(L54,M54,0) -> 2543.7868 | O54: -0.54505408 | P54: =-(EXP(O54)-1)*D54 -> 2779.6052 | Q54: =ABS(F54-P54) -> 481.7203 | R54: =FALSE() -> FALSE
A55: ='03 Optimization Events'!A55 -> i-102 | B55: ='03 Optimization Events'!C55 -> bu-assist | C55: ='03 Optimization Events'!D55 -> rightsize_instance | D55: ='03 Optimization Events'!I55 -> 21771.206 | E55: 0.33353017 | F55: =-(EXP(E55)-1)*D55 -> -8618.9409 | G55: 0.32907364 | H55: =EXP(-0.0465808124256294)-1 -> -0.045512577 | I55: =EXP(0.704728097228755)-1 -> 1.0232965 | J55: 0.12195122 | K55: =TRUE() -> TRUE | L55: =IF('10 Assumptions'!$B$24="Yes",TRUE(),K55) -> TRUE | M55: =-(EXP(G55)-1)*D55 -> -8483.8077 | N55: =IF(L55,M55,0) -> -8483.8077 | O55: 0 | P55: =-(EXP(O55)-1)*D55 -> 0 | Q55: =ABS(F55-P55) -> 8618.9409 | R55: =TRUE() -> TRUE
A56: ='03 Optimization Events'!A56 -> i-000 | B56: ='03 Optimization Events'!C56 -> bu-assist | C56: ='03 Optimization Events'!D56 -> rightsize_instance | D56: ='03 Optimization Events'!I56 -> 13571.043 | E56: -1.0221131 | F56: =-(EXP(E56)-1)*D56 -> 8687.7236 | G56: -0.97375479 | H56: =EXP(-1.46170271523512)-1 -> -0.76815882 | I56: =EXP(-0.485806868531391)-1 -> -0.38479939 | J56: 0.024390244 | K56: =TRUE() -> TRUE | L56: =IF('10 Assumptions'!$B$24="Yes",TRUE(),K56) -> TRUE | M56: =-(EXP(G56)-1)*D56 -> 8445.7716 | N56: =IF(L56,M56,0) -> 8445.7716 | O56: -1.2388098 | P56: =-(EXP(O56)-1)*D56 -> 9639.1207 | Q56: =ABS(F56-P56) -> 951.39709 | R56: =FALSE() -> FALSE
A57: ='03 Optimization Events'!A57 -> i-041 | B57: ='03 Optimization Events'!C57 -> bu-platform | C57: ='03 Optimization Events'!D57 -> migrate_storage_class | D57: ='03 Optimization Events'!I57 -> 19871.289 | E57: -0.79386725 | F57: =-(EXP(E57)-1)*D57 -> 10887.617 | G57: -0.89791109 | H57: =EXP(-1.24770685334551)-1 -> -0.71283745 | I57: =EXP(-0.548115318723912)-1 -> -0.4219618 | J57: 0.024390244 | K57: =TRUE() -> TRUE | L57: =IF('10 Assumptions'!$B$24="Yes",TRUE(),K57) -> TRUE | M57: =-(EXP(G57)-1)*D57 -> 11775.332 | N57: =IF(L57,M57,0) -> 11775.332 | O57: -0.77328192 | P57: =-(EXP(O57)-1)*D57 -> 10700.769 | Q57: =ABS(F57-P57) -> 186.84834 | R57: =FALSE() -> FALSE
A58: ='03 Optimization Events'!A58 -> i-110 | B58: ='03 Optimization Events'!C58 -> bu-platform | C58: ='03 Optimization Events'!D58 -> schedule_shutdown | D58: ='03 Optimization Events'!I58 -> 14453.307 | E58: 0.29640524 | F58: =-(EXP(E58)-1)*D58 -> -4986.609 | G58: 0.16748924 | H58: =EXP(-0.330982751053229)-1 -> -0.28178244 | I58: =EXP(0.6659612261509)-1 -> 0.94636052 | J58: 0.63414634 | K58: =TRUE() -> TRUE | L58: =IF('10 Assumptions'!$B$24="Yes",TRUE(),K58) -> TRUE | M58: =-(EXP(G58)-1)*D58 -> -2635.3085 | N58: =IF(L58,M58,0) -> -2635.3085 | O58: 0 | P58: =-(EXP(O58)-1)*D58 -> 0 | Q58: =ABS(F58-P58) -> 4986.609 | R58: =TRUE() -> TRUE
A59: ='03 Optimization Events'!A59 -> i-109 | B59: ='03 Optimization Events'!C59 -> bu-platform | C59: ='03 Optimization Events'!D59 -> delete_orphaned_volume | D59: ='03 Optimization Events'!I59 -> 7578.699 | E59: 0.19580507 | F59: =-(EXP(E59)-1)*D59 -> -1639.1952 | G59: 0.090869313 | H59: =EXP(-0.158529532940896)-1 -> -0.14660224 | I59: =EXP(0.340268159329087)-1 -> 0.40532439 | J59: 0.3902439 | K59: =FALSE() -> FALSE | L59: =IF('10 Assumptions'!$B$24="Yes",TRUE(),K59) -> FALSE | M59: =-(EXP(G59)-1)*D59 -> -720.93039 | N59: =IF(L59,M59,0) -> 0 | O59: 0 | P59: =-(EXP(O59)-1)*D59 -> 0 | Q59: =ABS(F59-P59) -> 1639.1952 | R59: =TRUE() -> TRUE
A60: ='03 Optimization Events'!A60 -> i-051 | B60: ='03 Optimization Events'!C60 -> bu-checkout | C60: ='03 Optimization Events'!D60 -> delete_orphaned_volume | D60: ='03 Optimization Events'!I60 -> 3338.5637 | E60: -0.7301696 | F60: =-(EXP(E60)-1)*D60 -> 1729.9527 | G60: -0.90406778 | H60: =EXP(-1.19884562528151)-1 -> -0.6984579 | I60: =EXP(-0.609289943636327)-1 -> -0.45626318 | J60: 0.024390244 | K60: =TRUE() -> TRUE | L60: =IF('10 Assumptions'!$B$24="Yes",TRUE(),K60) -> TRUE | M60: =-(EXP(G60)-1)*D60 -> 1986.7152 | N60: =IF(L60,M60,0) -> 1986.7152 | O60: -0.92363122 | P60: =-(EXP(O60)-1)*D60 -> 2012.905 | Q60: =ABS(F60-P60) -> 282.95231 | R60: =FALSE() -> FALSE
A61: ='03 Optimization Events'!A61 -> i-058 | B61: ='03 Optimization Events'!C61 -> bu-platform | C61: ='03 Optimization Events'!D61 -> cache_inference_results | D61: ='03 Optimization Events'!I61 -> 8167.5298 | E61: -0.39279997 | F61: =-(EXP(E61)-1)*D61 -> 2653.1094 | G61: -0.46053157 | H61: =EXP(-0.843954879068432)-1 -> -0.56999347 | I61: =EXP(-0.0771082699956896)-1 -> -0.074210387 | J61: 0.048780488 | K61: =TRUE() -> TRUE | L61: =IF('10 Assumptions'!$B$24="Yes",TRUE(),K61) -> TRUE | M61: =-(EXP(G61)-1)*D61 -> 3014.2419 | N61: =IF(L61,M61,0) -> 3014.2419 | O61: -0.71289638 | P61: =-(EXP(O61)-1)*D61 -> 4163.6248 | Q61: =ABS(F61-P61) -> 1510.5154 | R61: =FALSE() -> FALSE
A62: ='03 Optimization Events'!A62 -> i-057 | B62: ='03 Optimization Events'!C62 -> bu-checkout | C62: ='03 Optimization Events'!D62 -> schedule_shutdown | D62: ='03 Optimization Events'!I62 -> 68304.092 | E62: -0.41481004 | F62: =-(EXP(E62)-1)*D62 -> 23191.58 | G62: -0.64768738 | H62: =EXP(-0.941559305355121)-1 -> -0.6099808 | I62: =EXP(-0.35381545979069)-1 -> -0.2979955 | J62: 0.048780488 | K62: =TRUE() -> TRUE | L62: =IF('10 Assumptions'!$B$24="Yes",TRUE(),K62) -> TRUE | M62: =-(EXP(G62)-1)*D62 -> 32563.671 | N62: =IF(L62,M62,0) -> 32563.671 | O62: -0.70995625 | P62: =-(EXP(O62)-1)*D62 -> 34721.312 | Q62: =ABS(F62-P62) -> 11529.732 | R62: =FALSE() -> FALSE
A63: ='03 Optimization Events'!A63 -> i-081 | B63: ='03 Optimization Events'!C63 -> bu-assist | C63: ='03 Optimization Events'!D63 -> enable_autoscaling | D63: ='03 Optimization Events'!I63 -> 1199.351 | E63: -0.36980263 | F63: =-(EXP(E63)-1)*D63 -> 370.75458 | G63: -0.26894984 | H63: =EXP(-0.739259326127711)-1 -> -0.52253257 | I63: =EXP(0.201359650009677)-1 -> 0.22306457 | J63: 0.14634146 | K63: =TRUE() -> TRUE | L63: =IF('10 Assumptions'!$B$24="Yes",TRUE(),K63) -> TRUE | M63: =-(EXP(G63)-1)*D63 -> 282.82906 | N63: =IF(L63,M63,0) -> 282.82906 | O63: -0.44230552 | P63: =-(EXP(O63)-1)*D63 -> 428.70408 | Q63: =ABS(F63-P63) -> 57.949503 | R63: =FALSE() -> FALSE
A64: ='03 Optimization Events'!A64 -> i-004 | B64: ='03 Optimization Events'!C64 -> bu-search | C64: ='03 Optimization Events'!D64 -> rightsize_instance | D64: ='03 Optimization Events'!I64 -> 2078.1554 | E64: -0.90497413 | F64: =-(EXP(E64)-1)*D64 -> 1237.4328 | G64: -1.0775984 | H64: =EXP(-1.34063162637675)-1 -> -0.73831967 | I64: =EXP(-0.81456510380813)-1 -> -0.55716813 | J64: 0.024390244 | K64: =TRUE() -> TRUE | L64: =IF('10 Assumptions'!$B$24="Yes",TRUE(),K64) -> TRUE | M64: =-(EXP(G64)-1)*D64 -> 1370.7262 | N64: =IF(L64,M64,0) -> 1370.7262 | O64: -1.1942161 | P64: =-(EXP(O64)-1)*D64 -> 1448.5963 | Q64: =ABS(F64-P64) -> 211.16349 | R64: =FALSE() -> FALSE
A65: ='03 Optimization Events'!A65 -> i-092 | B65: ='03 Optimization Events'!C65 -> bu-search | C65: ='03 Optimization Events'!D65 -> delete_orphaned_volume | D65: ='03 Optimization Events'!I65 -> 1239.7233 | E65: 0.5499629 | F65: =-(EXP(E65)-1)*D65 -> -908.95112 | G65: 0.32062197 | H65: =EXP(-0.0380809481459518)-1 -> -0.037364986 | I65: =EXP(0.679324889376429)-1 -> 0.9725456 | J65: 0.12195122 | K65: =FALSE() -> FALSE | L65: =IF('10 Assumptions'!$B$24="Yes",TRUE(),K65) -> FALSE | M65: =-(EXP(G65)-1)*D65 -> -468.59626 | N65: =IF(L65,M65,0) -> 0 | O65: 0 | P65: =-(EXP(O65)-1)*D65 -> 0 | Q65: =ABS(F65-P65) -> 908.95112 | R65: =TRUE() -> TRUE
A66: ='03 Optimization Events'!A66 -> i-100 | B66: ='03 Optimization Events'!C66 -> bu-checkout | C66: ='03 Optimization Events'!D66 -> delete_orphaned_volume | D66: ='03 Optimization Events'!I66 -> 16317.347 | E66: 0.36471382 | F66: =-(EXP(E66)-1)*D66 -> -7181.2941 | G66: 0.16350054 | H66: =EXP(-0.100417837951523)-1 -> -0.095540578 | I66: =EXP(0.427418920913947)-1 -> 0.53329486 | J66: 0.17073171 | K66: =TRUE() -> TRUE | L66: =IF('10 Assumptions'!$B$24="Yes",TRUE(),K66) -> TRUE | M66: =-(EXP(G66)-1)*D66 -> -2898.385 | N66: =IF(L66,M66,0) -> -2898.385 | O66: 0 | P66: =-(EXP(O66)-1)*D66 -> 0 | Q66: =ABS(F66-P66) -> 7181.2941 | R66: =TRUE() -> TRUE
A67: ='03 Optimization Events'!A67 -> i-113 | B67: ='03 Optimization Events'!C67 -> bu-platform | C67: ='03 Optimization Events'!D67 -> cache_inference_results | D67: ='03 Optimization Events'!I67 -> 3686.2502 | E67: 0.10906542 | F67: =-(EXP(E67)-1)*D67 -> -424.78619 | G67: 0.070391585 | H67: =EXP(-0.292301254843609)-1 -> -0.2534564 | I67: =EXP(0.433084424235019)-1 -> 0.5420064 | J67: 0.7804878 | K67: =TRUE() -> TRUE | L67: =IF('10 Assumptions'!$B$24="Yes",TRUE(),K67) -> TRUE | M67: =-(EXP(G67)-1)*D67 -> -268.83175 | N67: =IF(L67,M67,0) -> -268.83175 | O67: 0 | P67: =-(EXP(O67)-1)*D67 -> 0 | Q67: =ABS(F67-P67) -> 424.78619 | R67: =TRUE() -> TRUE
A68: ='03 Optimization Events'!A68 -> i-017 | B68: ='03 Optimization Events'!C68 -> bu-checkout | C68: ='03 Optimization Events'!D68 -> cache_inference_results | D68: ='03 Optimization Events'!I68 -> 5788.1073 | E68: -1.0319196 | F68: =-(EXP(E68)-1)*D68 -> 3725.6755 | G68: -1.1331901 | H68: =EXP(-1.32853414654805)-1 -> -0.73513477 | I68: =EXP(-0.937846025362662)-1 -> -0.60852986 | J68: 0.024390244 | K68: =TRUE() -> TRUE | L68: =IF('10 Assumptions'!$B$24="Yes",TRUE(),K68) -> TRUE | M68: =-(EXP(G68)-1)*D68 -> 3924.3113 | N68: =IF(L68,M68,0) -> 3924.3113 | O68: -0.98714563 | P68: =-(EXP(O68)-1)*D68 -> 3631.2338 | Q68: =ABS(F68-P68) -> 94.441723 | R68: =FALSE() -> FALSE
A69: ='03 Optimization Events'!A69 -> i-112 | B69: ='03 Optimization Events'!C69 -> bu-checkout | C69: ='03 Optimization Events'!D69 -> consolidate_cluster | D69: ='03 Optimization Events'!I69 -> 15554.552 | E69: 0.30802954 | F69: =-(EXP(E69)-1)*D69 -> -5611.1673 | G69: 0.15680646 | H69: =EXP(-0.120468493305387)-1 -> -0.11349498 | I69: =EXP(0.434081409381318)-1 -> 0.54354452 | J69: 0.17073171 | K69: =TRUE() -> TRUE | L69: =IF('10 Assumptions'!$B$24="Yes",TRUE(),K69) -> TRUE | M69: =-(EXP(G69)-1)*D69 -> -2640.6837 | N69: =IF(L69,M69,0) -> -2640.6837 | O69: 0 | P69: =-(EXP(O69)-1)*D69 -> 0 | Q69: =ABS(F69-P69) -> 5611.1673 | R69: =TRUE() -> TRUE
A70: ='03 Optimization Events'!A70 -> i-048 | B70: ='03 Optimization Events'!C70 -> bu-search | C70: ='03 Optimization Events'!D70 -> delete_orphaned_volume | D70: ='03 Optimization Events'!I70 -> 8066.005 | E70: -0.86610176 | F70: =-(EXP(E70)-1)*D70 -> 4673.5408 | G70: -0.93300857 | H70: =EXP(-1.10151418107635)-1 -> -0.66763256 | I70: =EXP(-0.764502956710221)-1 -> -0.53443472 | J70: 0.024390244 | K70: =TRUE() -> TRUE | L70: =IF('10 Assumptions'!$B$24="Yes",TRUE(),K70) -> TRUE | M70: =-(EXP(G70)-1)*D70 -> 4893.0931 | N70: =IF(L70,M70,0) -> 4893.0931 | O70: -0.86699866 | P70: =-(EXP(O70)-1)*D70 -> 4676.5821 | Q70: =ABS(F70-P70) -> 3.0413159 | R70: =FALSE() -> FALSE
A71: ='03 Optimization Events'!A71 -> i-077 | B71: ='03 Optimization Events'!C71 -> bu-search | C71: ='03 Optimization Events'!D71 -> enable_autoscaling | D71: ='03 Optimization Events'!I71 -> 67126.395 | E71: -0.25618484 | F71: =-(EXP(E71)-1)*D71 -> 15170.64 | G71: -0.3317981 | H71: =EXP(-0.518215338395456)-1 -> -0.40441749 | I71: =EXP(-0.145380859626761)-1 -> -0.1353071 | J71: 0.024390244 | K71: =TRUE() -> TRUE | L71: =IF('10 Assumptions'!$B$24="Yes",TRUE(),K71) -> TRUE | M71: =-(EXP(G71)-1)*D71 -> 18954.333 | N71: =IF(L71,M71,0) -> 18954.333 | O71: -0.38961307 | P71: =-(EXP(O71)-1)*D71 -> 21660.419 | Q71: =ABS(F71-P71) -> 6489.7795 | R71: =FALSE() -> FALSE
A72: ='03 Optimization Events'!A72 -> i-047 | B72: ='03 Optimization Events'!C72 -> bu-platform | C72: ='03 Optimization Events'!D72 -> schedule_shutdown | D72: ='03 Optimization Events'!I72 -> 45890.897 | E72: -0.60088456 | F72: =-(EXP(E72)-1)*D72 -> 20727.707 | G72: -0.63762134 | H72: =EXP(-0.793711648664515)-1 -> -0.54783659 | I72: =EXP(-0.481531028219536)-1 -> -0.38216326 | J72: 0.024390244 | K72: =TRUE() -> TRUE | L72: =IF('10 Assumptions'!$B$24="Yes",TRUE(),K72) -> TRUE | M72: =-(EXP(G72)-1)*D72 -> 21635.347 | N72: =IF(L72,M72,0) -> 21635.347 | O72: -0.80854027 | P72: =-(EXP(O72)-1)*D72 -> 25446.139 | Q72: =ABS(F72-P72) -> 4718.4323 | R72: =FALSE() -> FALSE
A73: ='03 Optimization Events'!A73 -> i-033 | B73: ='03 Optimization Events'!C73 -> bu-datalake | C73: ='03 Optimization Events'!D73 -> cache_inference_results | D73: ='03 Optimization Events'!I73 -> 8261.4494 | E73: -1.0759883 | F73: =-(EXP(E73)-1)*D73 -> 5444.6205 | G73: -1.052231 | H73: =EXP(-1.30106897326226)-1 -> -0.72775938 | I73: =EXP(-0.803393126056657)-1 -> -0.55219308 | J73: 0.024390244 | K73: =TRUE() -> TRUE | L73: =IF('10 Assumptions'!$B$24="Yes",TRUE(),K73) -> TRUE | M73: =-(EXP(G73)-1)*D73 -> 5376.8992 | N73: =IF(L73,M73,0) -> 5376.8992 | O73: -1.0652518 | P73: =-(EXP(O73)-1)*D73 -> 5414.2147 | Q73: =ABS(F73-P73) -> 30.405805 | R73: =FALSE() -> FALSE
A74: ='03 Optimization Events'!A74 -> i-082 | B74: ='03 Optimization Events'!C74 -> bu-platform | C74: ='03 Optimization Events'!D74 -> rightsize_instance | D74: ='03 Optimization Events'!I74 -> 5802.3592 | E74: -0.43509006 | F74: =-(EXP(E74)-1)*D74 -> 2047.0353 | G74: -0.41811611 | H74: =EXP(-0.804381870573876)-1 -> -0.55263563 | I74: =EXP(-0.0318503492159352)-1 -> -0.031348469 | J74: 0.073170732 | K74: =TRUE() -> TRUE | L74: =IF('10 Assumptions'!$B$24="Yes",TRUE(),K74) -> TRUE | M74: =-(EXP(G74)-1)*D74 -> 1982.7486 | N74: =IF(L74,M74,0) -> 1982.7486 | O74: -0.35026555 | P74: =-(EXP(O74)-1)*D74 -> 1714.5914 | Q74: =ABS(F74-P74) -> 332.4439 | R74: =FALSE() -> FALSE
A75: ='03 Optimization Events'!A75 -> i-078 | B75: ='03 Optimization Events'!C75 -> bu-datasci | C75: ='03 Optimization Events'!D75 -> delete_orphaned_volume | D75: ='03 Optimization Events'!I75 -> 8290.8592 | E75: -0.38441736 | F75: =-(EXP(E75)-1)*D75 -> 2646.0509 | G75: -0.42246371 | H75: =EXP(-0.651804103835192)-1 -> -0.4788952 | I75: =EXP(-0.193123308792558)-1 -> -0.17561969 | J75: 0.048780488 | K75: =TRUE() -> TRUE | L75: =IF('10 Assumptions'!$B$24="Yes",TRUE(),K75) -> TRUE | M75: =-(EXP(G75)-1)*D75 -> 2856.781 | N75: =IF(L75,M75,0) -> 2856.781 | O75: -0.39634404 | P75: =-(EXP(O75)-1)*D75 -> 2712.9748 | Q75: =ABS(F75-P75) -> 66.923904 | R75: =FALSE() -> FALSE
A76: ='03 Optimization Events'!A76 -> i-106 | B76: ='03 Optimization Events'!C76 -> bu-checkout | C76: ='03 Optimization Events'!D76 -> cache_inference_results | D76: ='03 Optimization Events'!I76 -> 10031.028 | E76: 0.10106746 | F76: =-(EXP(E76)-1)*D76 -> -1066.8127 | G76: 0.1326714 | H76: =EXP(-0.0857729619668112)-1 -> -0.082197416 | I76: =EXP(0.351115755257476)-1 -> 0.42065176 | J76: 0.34146341 | K76: =TRUE() -> TRUE | L76: =IF('10 Assumptions'!$B$24="Yes",TRUE(),K76) -> TRUE | M76: =-(EXP(G76)-1)*D76 -> -1423.1492 | N76: =IF(L76,M76,0) -> -1423.1492 | O76: 0 | P76: =-(EXP(O76)-1)*D76 -> 0 | Q76: =ABS(F76-P76) -> 1066.8127 | R76: =TRUE() -> TRUE
A77: ='03 Optimization Events'!A77 -> i-096 | B77: ='03 Optimization Events'!C77 -> bu-assist | C77: ='03 Optimization Events'!D77 -> cache_inference_results | D77: ='03 Optimization Events'!I77 -> 7432.6589 | E77: -0.012220327 | F77: =-(EXP(E77)-1)*D77 -> 90.27679 | G77: -0.097623652 | H77: =EXP(-0.377498996202512)-1 -> -0.31442611 | I77: =EXP(0.182251692867583)-1 -> 0.19991617 | J77: 0.53658537 | K77: =FALSE() -> FALSE | L77: =IF('10 Assumptions'!$B$24="Yes",TRUE(),K77) -> FALSE | M77: =-(EXP(G77)-1)*D77 -> 691.31024 | N77: =IF(L77,M77,0) -> 0 | O77: 0 | P77: =-(EXP(O77)-1)*D77 -> 0 | Q77: =ABS(F77-P77) -> 90.27679 | R77: =TRUE() -> TRUE
A78: ='03 Optimization Events'!A78 -> i-098 | B78: ='03 Optimization Events'!C78 -> bu-checkout | C78: ='03 Optimization Events'!D78 -> cache_inference_results | D78: ='03 Optimization Events'!I78 -> 1818.1866 | E78: -0.098906151 | F78: =-(EXP(E78)-1)*D78 -> 171.22279 | G78: 0.030799639 | H78: =EXP(-0.146697645262625)-1 -> -0.13644496 | I78: =EXP(0.208296923685655)-1 -> 0.2315788 | J78: 0.70731707 | K78: =TRUE() -> TRUE | L78: =IF('10 Assumptions'!$B$24="Yes",TRUE(),K78) -> TRUE | M78: =-(EXP(G78)-1)*D78 -> -56.870797 | N78: =IF(L78,M78,0) -> -56.870797 | O78: 0 | P78: =-(EXP(O78)-1)*D78 -> 0 | Q78: =ABS(F78-P78) -> 171.22279 | R78: =TRUE() -> TRUE
A79: ='03 Optimization Events'!A79 -> i-009 | B79: ='03 Optimization Events'!C79 -> bu-search | C79: ='03 Optimization Events'!D79 -> rightsize_instance | D79: ='03 Optimization Events'!I79 -> 35564.82 | E79: -1.293141 | F79: =-(EXP(E79)-1)*D79 -> 25805.566 | G79: -1.1112377 | H79: =EXP(-1.32988453799133)-1 -> -0.7354922 | I79: =EXP(-0.8925908955184)-1 -> -0.59040684 | J79: 0.024390244 | K79: =TRUE() -> TRUE | L79: =IF('10 Assumptions'!$B$24="Yes",TRUE(),K79) -> TRUE | M79: =-(EXP(G79)-1)*D79 -> 23858.613 | N79: =IF(L79,M79,0) -> 23858.613 | O79: -1.2728949 | P79: =-(EXP(O79)-1)*D79 -> 25605.965 | Q79: =ABS(F79-P79) -> 199.60095 | R79: =FALSE() -> FALSE
A80: ='03 Optimization Events'!A80 -> i-064 | B80: ='03 Optimization Events'!C80 -> bu-checkout | C80: ='03 Optimization Events'!D80 -> consolidate_cluster | D80: ='03 Optimization Events'!I80 -> 7939.9168 | E80: -1.1665897 | F80: =-(EXP(E80)-1)*D80 -> 5467.2108 | G80: -0.95702493 | H80: =EXP(-1.1823736502146)-1 -> -0.69344977 | I80: =EXP(-0.731676215246439)-1 -> -0.51889812 | J80: 0.024390244 | K80: =TRUE() -> TRUE | L80: =IF('10 Assumptions'!$B$24="Yes",TRUE(),K80) -> TRUE | M80: =-(EXP(G80)-1)*D80 -> 4890.721 | N80: =IF(L80,M80,0) -> 4890.721 | O80: -0.89970662 | P80: =-(EXP(O80)-1)*D80 -> 4710.8403 | Q80: =ABS(F80-P80) -> 756.37052 | R80: =FALSE() -> FALSE
A81: ='03 Optimization Events'!A81 -> i-031 | B81: ='03 Optimization Events'!C81 -> bu-checkout | C81: ='03 Optimization Events'!D81 -> consolidate_cluster | D81: ='03 Optimization Events'!I81 -> 4699.2734 | E81: -1.1906364 | F81: =-(EXP(E81)-1)*D81 -> 3270.564 | G81: -0.95581509 | H81: =EXP(-1.13605396313482)-1 -> -0.67891647 | I81: =EXP(-0.77557622078598)-1 -> -0.53956161 | J81: 0.024390244 | K81: =TRUE() -> TRUE | L81: =IF('10 Assumptions'!$B$24="Yes",TRUE(),K81) -> TRUE | M81: =-(EXP(G81)-1)*D81 -> 2892.4093 | N81: =IF(L81,M81,0) -> 2892.4093 | O81: -0.98465446 | P81: =-(EXP(O81)-1)*D81 -> 2943.7739 | Q81: =ABS(F81-P81) -> 326.79015 | R81: =FALSE() -> FALSE
A82: ='03 Optimization Events'!A82 -> i-074 | B82: ='03 Optimization Events'!C82 -> bu-search | C82: ='03 Optimization Events'!D82 -> enable_autoscaling | D82: ='03 Optimization Events'!I82 -> 30223.004 | E82: -0.92253687 | F82: =-(EXP(E82)-1)*D82 -> 18209.078 | G82: -0.71102746 | H82: =EXP(-0.890791083564378)-1 -> -0.58966898 | I82: =EXP(-0.531263827476231)-1 -> -0.41213846 | J82: 0.024390244 | K82: =TRUE() -> TRUE | L82: =IF('10 Assumptions'!$B$24="Yes",TRUE(),K82) -> TRUE | M82: =-(EXP(G82)-1)*D82 -> 15379.298 | N82: =IF(L82,M82,0) -> 15379.298 | O82: -0.67391169 | P82: =-(EXP(O82)-1)*D82 -> 14818.011 | Q82: =ABS(F82-P82) -> 3391.0666 | R82: =FALSE() -> FALSE
A83: ='03 Optimization Events'!A83 -> i-010 | B83: ='03 Optimization Events'!C83 -> bu-platform | C83: ='03 Optimization Events'!D83 -> tune_batch_size | D83: ='03 Optimization Events'!I83 -> 147563.51 | E83: -1.3324829 | F83: =-(EXP(E83)-1)*D83 -> 108633.1 | G83: -1.256119 | H83: =EXP(-1.61432312354245)-1 -> -0.80097466 | I83: =EXP(-0.897914836388015)-1 -> -0.59258169 | J83: 0.024390244 | K83: =TRUE() -> TRUE | L83: =IF('10 Assumptions'!$B$24="Yes",TRUE(),K83) -> TRUE | M83: =-(EXP(G83)-1)*D83 -> 105543.76 | N83: =IF(L83,M83,0) -> 105543.76 | O83: -1.0744637 | P83: =-(EXP(O83)-1)*D83 -> 97173.397 | Q83: =ABS(F83-P83) -> 11459.7 | R83: =FALSE() -> FALSE
A84: ='03 Optimization Events'!A84 -> i-022 | B84: ='03 Optimization Events'!C84 -> bu-assist | C84: ='03 Optimization Events'!D84 -> cache_inference_results | D84: ='03 Optimization Events'!I84 -> 183203.32 | E84: -1.1002477 | F84: =-(EXP(E84)-1)*D84 -> 122235.33 | G84: -1.1661093 | H84: =EXP(-1.38060030730487)-1 -> -0.74857243 | I84: =EXP(-0.951618237241415)-1 -> -0.61388431 | J84: 0.024390244 | K84: =TRUE() -> TRUE | L84: =IF('10 Assumptions'!$B$24="Yes",TRUE(),K84) -> TRUE | M84: =-(EXP(G84)-1)*D84 -> 126121.4 | N84: =IF(L84,M84,0) -> 126121.4 | O84: -1.1419441 | P84: =-(EXP(O84)-1)*D84 -> 124725.21 | Q84: =ABS(F84-P84) -> 2489.8754 | R84: =FALSE() -> FALSE
A85: ='03 Optimization Events'!A85 -> i-104 | B85: ='03 Optimization Events'!C85 -> bu-checkout | C85: ='03 Optimization Events'!D85 -> consolidate_cluster | D85: ='03 Optimization Events'!I85 -> 35723.133 | E85: 0.052572529 | F85: =-(EXP(E85)-1)*D85 -> -1928.2991 | G85: 0.30278344 | H85: =EXP(0.0760273856678042)-1 -> 0.078992123 | I85: =EXP(0.529539490935792)-1 -> 0.69815012 | J85: 0.048780488 | K85: =FALSE() -> FALSE | L85: =IF('10 Assumptions'!$B$24="Yes",TRUE(),K85) -> FALSE | M85: =-(EXP(G85)-1)*D85 -> -12632.46 | N85: =IF(L85,M85,0) -> 0 | O85: 0 | P85: =-(EXP(O85)-1)*D85 -> 0 | Q85: =ABS(F85-P85) -> 1928.2991 | R85: =TRUE() -> TRUE
A86: ='03 Optimization Events'!A86 -> i-040 | B86: ='03 Optimization Events'!C86 -> bu-datasci | C86: ='03 Optimization Events'!D86 -> enable_autoscaling | D86: ='03 Optimization Events'!I86 -> 134432.9 | E86: -0.71088497 | F86: =-(EXP(E86)-1)*D86 -> 68398.21 | G86: -0.81390216 | H86: =EXP(-1.00331351532943)-1 -> -0.63333752 | I86: =EXP(-0.624490799452882)-1 -> -0.46446595 | J86: 0.024390244 | K86: =TRUE() -> TRUE | L86: =IF('10 Assumptions'!$B$24="Yes",TRUE(),K86) -> TRUE | M86: =-(EXP(G86)-1)*D86 -> 74862.249 | N86: =IF(L86,M86,0) -> 74862.249 | O86: -0.83029272 | P86: =-(EXP(O86)-1)*D86 -> 75830.687 | Q86: =ABS(F86-P86) -> 7432.4773 | R86: =FALSE() -> FALSE
A87: ='03 Optimization Events'!A87 -> i-050 | B87: ='03 Optimization Events'!C87 -> bu-datalake | C87: ='03 Optimization Events'!D87 -> cache_inference_results | D87: ='03 Optimization Events'!I87 -> 112472.53 | E87: -0.83908827 | F87: =-(EXP(E87)-1)*D87 -> 63872.664 | G87: -0.90145901 | H87: =EXP(-1.10941820529612)-1 -> -0.67024925 | I87: =EXP(-0.693499816589162)-1 -> -0.50017629 | J87: 0.024390244 | K87: =TRUE() -> TRUE | L87: =IF('10 Assumptions'!$B$24="Yes",TRUE(),K87) -> TRUE | M87: =-(EXP(G87)-1)*D87 -> 66811.28 | N87: =IF(L87,M87,0) -> 66811.28 | O87: -0.9974075 | P87: =-(EXP(O87)-1)*D87 -> 70988.79 | Q87: =ABS(F87-P87) -> 7116.1257 | R87: =FALSE() -> FALSE
A88: ='03 Optimization Events'!A88 -> i-052 | B88: ='03 Optimization Events'!C88 -> bu-search | C88: ='03 Optimization Events'!D88 -> cache_inference_results | D88: ='03 Optimization Events'!I88 -> 13985.004 | E88: -1.0401127 | F88: =-(EXP(E88)-1)*D88 -> 9042.4961 | G88: -0.81147588 | H88: =EXP(-1.01181916551076)-1 -> -0.63644299 | I88: =EXP(-0.611132603385575)-1 -> -0.45726418 | J88: 0.024390244 | K88: =TRUE() -> TRUE | L88: =IF('10 Assumptions'!$B$24="Yes",TRUE(),K88) -> TRUE | M88: =-(EXP(G88)-1)*D88 -> 7772.8374 | N88: =IF(L88,M88,0) -> 7772.8374 | O88: -0.84812624 | P88: =-(EXP(O88)-1)*D88 -> 7996.3938 | Q88: =ABS(F88-P88) -> 1046.1023 | R88: =FALSE() -> FALSE
A89: ='03 Optimization Events'!A89 -> i-039 | B89: ='03 Optimization Events'!C89 -> bu-platform | C89: ='03 Optimization Events'!D89 -> schedule_shutdown | D89: ='03 Optimization Events'!I89 -> 52124.865 | E89: -0.80770167 | F89: =-(EXP(E89)-1)*D89 -> 28883.343 | G89: -0.89639948 | H89: =EXP(-1.17852407944204)-1 -> -0.69226741 | I89: =EXP(-0.614274884326846)-1 -> -0.45896694 | J89: 0.024390244 | K89: =TRUE() -> TRUE | L89: =IF('10 Assumptions'!$B$24="Yes",TRUE(),K89) -> TRUE | M89: =-(EXP(G89)-1)*D89 -> 30856.035 | N89: =IF(L89,M89,0) -> 30856.035 | O89: -0.88611313 | P89: =-(EXP(O89)-1)*D89 -> 30636.127 | Q89: =ABS(F89-P89) -> 1752.7846 | R89: =FALSE() -> FALSE
A90: ='03 Optimization Events'!A90 -> i-091 | B90: ='03 Optimization Events'!C90 -> bu-platform | C90: ='03 Optimization Events'!D90 -> migrate_storage_class | D90: ='03 Optimization Events'!I90 -> 480.32857 | E90: 0.27772601 | F90: =-(EXP(E90)-1)*D90 -> -153.76492 | G90: 0.2199176 | H90: =EXP(-0.296361284418711)-1 -> -0.25648124 | I90: =EXP(0.736196487003586)-1 -> 1.0879787 | J90: 0.3902439 | K90: =TRUE() -> TRUE | L90: =IF('10 Assumptions'!$B$24="Yes",TRUE(),K90) -> TRUE | M90: =-(EXP(G90)-1)*D90 -> -118.14837 | N90: =IF(L90,M90,0) -> -118.14837 | O90: 0 | P90: =-(EXP(O90)-1)*D90 -> 0 | Q90: =ABS(F90-P90) -> 153.76492 | R90: =TRUE() -> TRUE
A91: ='03 Optimization Events'!A91 -> i-063 | B91: ='03 Optimization Events'!C91 -> bu-datasci | C91: ='03 Optimization Events'!D91 -> tune_batch_size | D91: ='03 Optimization Events'!I91 -> 1530.3876 | E91: -0.6407295 | F91: =-(EXP(E91)-1)*D91 -> 724.01429 | G91: -0.73480263 | H91: =EXP(-0.987582061808064)-1 -> -0.62752377 | I91: =EXP(-0.482023197653216)-1 -> -0.38246726 | J91: 0.024390244 | K91: =TRUE() -> TRUE | L91: =IF('10 Assumptions'!$B$24="Yes",TRUE(),K91) -> TRUE | M91: =-(EXP(G91)-1)*D91 -> 796.41355 | N91: =IF(L91,M91,0) -> 796.41355 | O91: -0.60875852 | P91: =-(EXP(O91)-1)*D91 -> 697.8172 | Q91: =ABS(F91-P91) -> 26.197086 | R91: =FALSE() -> FALSE
A92: ='03 Optimization Events'!A92 -> i-072 | B92: ='03 Optimization Events'!C92 -> bu-platform | C92: ='03 Optimization Events'!D92 -> cache_inference_results | D92: ='03 Optimization Events'!I92 -> 18055.127 | E92: -0.87453462 | F92: =-(EXP(E92)-1)*D92 -> 10525.127 | G92: -0.96599211 | H92: =EXP(-1.2499528518974)-1 -> -0.71348169 | I92: =EXP(-0.682031372731127)-1 -> -0.49441109 | J92: 0.024390244 | K92: =TRUE() -> TRUE | L92: =IF('10 Assumptions'!$B$24="Yes",TRUE(),K92) -> TRUE | M92: =-(EXP(G92)-1)*D92 -> 11183.248 | N92: =IF(L92,M92,0) -> 11183.248 | O92: -0.74130991 | P92: =-(EXP(O92)-1)*D92 -> 9452.0512 | Q92: =ABS(F92-P92) -> 1073.0755 | R92: =FALSE() -> FALSE
A93: ='03 Optimization Events'!A93 -> i-020 | B93: ='03 Optimization Events'!C93 -> bu-checkout | C93: ='03 Optimization Events'!D93 -> delete_orphaned_volume | D93: ='03 Optimization Events'!I93 -> 90455.381 | E93: -1.1659631 | F93: =-(EXP(E93)-1)*D93 -> 62267.459 | G93: -1.0400429 | H93: =EXP(-1.25198284058982)-1 -> -0.71406273 | I93: =EXP(-0.82810288176844)-1 -> -0.56312269 | J93: 0.024390244 | K93: =TRUE() -> TRUE | L93: =IF('10 Assumptions'!$B$24="Yes",TRUE(),K93) -> TRUE | M93: =-(EXP(G93)-1)*D93 -> 58484.874 | N93: =IF(L93,M93,0) -> 58484.874 | O93: -1.0934161 | P93: =-(EXP(O93)-1)*D93 -> 60146.504 | Q93: =ABS(F93-P93) -> 2120.9544 | R93: =FALSE() -> FALSE
A94: ='03 Optimization Events'!A94 -> i-032 | B94: ='03 Optimization Events'!C94 -> bu-datalake | C94: ='03 Optimization Events'!D94 -> cache_inference_results | D94: ='03 Optimization Events'!I94 -> 15192.254 | E94: -1.0158432 | F94: =-(EXP(E94)-1)*D94 -> 9691.1851 | G94: -1.1375444 | H94: =EXP(-1.45229967091037)-1 -> -0.76596853 | I94: =EXP(-0.822789199451188)-1 -> -0.56079509 | J94: 0.024390244 | K94: =TRUE() -> TRUE | L94: =IF('10 Assumptions'!$B$24="Yes",TRUE(),K94) -> TRUE | M94: =-(EXP(G94)-1)*D94 -> 10321.537 | N94: =IF(L94,M94,0) -> 10321.537 | O94: -1.1066587 | P94: =-(EXP(O94)-1)*D94 -> 10168.754 | Q94: =ABS(F94-P94) -> 477.56859 | R94: =FALSE() -> FALSE
A95: ='03 Optimization Events'!A95 -> i-103 | B95: ='03 Optimization Events'!C95 -> bu-assist | C95: ='03 Optimization Events'!D95 -> consolidate_cluster | D95: ='03 Optimization Events'!I95 -> 39578.295 | E95: 0.60922792 | F95: =-(EXP(E95)-1)*D95 -> -33206.624 | G95: 0.44147793 | H95: =EXP(0.0729545177683959)-1 -> 0.075681611 | I95: =EXP(0.810001342013339)-1 -> 1.247911 | J95: 0.073170732 | K95: =FALSE() -> FALSE | L95: =IF('10 Assumptions'!$B$24="Yes",TRUE(),K95) -> FALSE | M95: =-(EXP(G95)-1)*D95 -> -21966.1 | N95: =IF(L95,M95,0) -> 0 | O95: 0 | P95: =-(EXP(O95)-1)*D95 -> 0 | Q95: =ABS(F95-P95) -> 33206.624 | R95: =TRUE() -> TRUE
A96: ='03 Optimization Events'!A96 -> i-025 | B96: ='03 Optimization Events'!C96 -> bu-checkout | C96: ='03 Optimization Events'!D96 -> schedule_shutdown | D96: ='03 Optimization Events'!I96 -> 69145.041 | E96: -1.0531663 | F96: =-(EXP(E96)-1)*D96 -> 45025.072 | G96: -0.94252692 | H96: =EXP(-1.1915476615635)-1 -> -0.6962492 | I96: =EXP(-0.693506187622614)-1 -> -0.50017947 | J96: 0.024390244 | K96: =TRUE() -> TRUE | L96: =IF('10 Assumptions'!$B$24="Yes",TRUE(),K96) -> TRUE | M96: =-(EXP(G96)-1)*D96 -> 42203.229 | N96: =IF(L96,M96,0) -> 42203.229 | O96: -0.94529957 | P96: =-(EXP(O96)-1)*D96 -> 42277.826 | Q96: =ABS(F96-P96) -> 2747.2463 | R96: =FALSE() -> FALSE
A97: ='03 Optimization Events'!A97 -> i-006 | B97: ='03 Optimization Events'!C97 -> bu-assist | C97: ='03 Optimization Events'!D97 -> migrate_storage_class | D97: ='03 Optimization Events'!I97 -> 360421.5 | E97: -1.3600898 | F97: =-(EXP(E97)-1)*D97 -> 267923.74 | G97: -1.4473982 | H97: =EXP(-1.65832533616731)-1 -> -0.80954233 | I97: =EXP(-1.23647113511251)-1 -> -0.70959278 | J97: 0.024390244 | K97: =TRUE() -> TRUE | L97: =IF('10 Assumptions'!$B$24="Yes",TRUE(),K97) -> TRUE | M97: =-(EXP(G97)-1)*D97 -> 275657.07 | N97: =IF(L97,M97,0) -> 275657.07 | O97: -1.2300449 | P97: =-(EXP(O97)-1)*D97 -> 255077.7 | Q97: =ABS(F97-P97) -> 12846.048 | R97: =FALSE() -> FALSE
A98: ='03 Optimization Events'!A98 -> i-007 | B98: ='03 Optimization Events'!C98 -> bu-datasci | C98: ='03 Optimization Events'!D98 -> cache_inference_results | D98: ='03 Optimization Events'!I98 -> 22136.486 | E98: -1.0638004 | F98: =-(EXP(E98)-1)*D98 -> 14496.263 | G98: -1.1842165 | H98: =EXP(-1.45666627160088)-1 -> -0.76698822 | I98: =EXP(-0.911766757672679)-1 -> -0.59818631 | J98: 0.024390244 | K98: =TRUE() -> TRUE | L98: =IF('10 Assumptions'!$B$24="Yes",TRUE(),K98) -> TRUE | M98: =-(EXP(G98)-1)*D98 -> 15363.035 | N98: =IF(L98,M98,0) -> 15363.035 | O98: -1.2056826 | P98: =-(EXP(O98)-1)*D98 -> 15506.885 | Q98: =ABS(F98-P98) -> 1010.6225 | R98: =FALSE() -> FALSE
A99: ='03 Optimization Events'!A99 -> i-024 | B99: ='03 Optimization Events'!C99 -> bu-datalake | C99: ='03 Optimization Events'!D99 -> delete_orphaned_volume | D99: ='03 Optimization Events'!I99 -> 62329.67 | E99: -0.64047949 | F99: =-(EXP(E99)-1)*D99 -> 29479.462 | G99: -0.79611998 | H99: =EXP(-1.06671440865689)-1 -> -0.65586264 | I99: =EXP(-0.52552555606482)-1 -> -0.40875545 | J99: 0.024390244 | K99: =TRUE() -> TRUE | L99: =IF('10 Assumptions'!$B$24="Yes",TRUE(),K99) -> TRUE | M99: =-(EXP(G99)-1)*D99 -> 34214.267 | N99: =IF(L99,M99,0) -> 34214.267 | O99: -0.94340856 | P99: =-(EXP(O99)-1)*D99 -> 38064.815 | Q99: =ABS(F99-P99) -> 8585.3527 | R99: =FALSE() -> FALSE
A100: ='03 Optimization Events'!A100 -> i-107 | B100: ='03 Optimization Events'!C100 -> bu-platform | C100: ='03 Optimization Events'!D100 -> enable_autoscaling | D100: ='03 Optimization Events'!I100 -> 2242.9771 | E100: 0.12123101 | F100: =-(EXP(E100)-1)*D100 -> -289.0876 | G100: 0.06569497 | H100: =EXP(-0.182676106469926)-1 -> -0.16696207 | I100: =EXP(0.314066045705526)-1 -> 0.36898015 | J100: 0.53658537 | K100: =TRUE() -> TRUE | L100: =IF('10 Assumptions'!$B$24="Yes",TRUE(),K100) -> TRUE | M100: =-(EXP(G100)-1)*D100 -> -152.30022 | N100: =IF(L100,M100,0) -> -152.30022 | O100: 0 | P100: =-(EXP(O100)-1)*D100 -> 0 | Q100: =ABS(F100-P100) -> 289.0876 | R100: =TRUE() -> TRUE
...

Sheet 05 Budget vs Actual
A1: Budget vs actual
A2: Budget = average of the first six complete months, grown monthly at the budget growth assumption. Actuals link to Raw Cost Data. Cost variance: under budget is favourable.
A3: SIMULATED DATA. The estate is synthetic (FOCUS 1.2, 400 resources, 540 days). Figures illustrate the method; ground truth exists only because the data is simulated.
A4: Monthly growth factor | B4: =(1+'10 Assumptions'!$B$20)^(1/12) -> 1.0117149 | C4: (1 + annual budget growth)^(1/12)
A5: Baseline (avg. months 1–6) | B5: =AVERAGE('02 Raw Cost Data'!I6:I11) -> 157209.37 | E5: =AVERAGE('02 Raw Cost Data'!J6:J11) -> 86225.561 | H5: =AVERAGE('02 Raw Cost Data'!K6:K11) -> 63959.106 | K5: =AVERAGE('02 Raw Cost Data'!L6:L11) -> 150202.68 | N5: =AVERAGE('02 Raw Cost Data'!M6:M11) -> 71068.818 | Q5: =AVERAGE('02 Raw Cost Data'!N6:N11) -> 86269.186 | T5: =AVERAGE('02 Raw Cost Data'!O6:O11) -> 74231.57
A6: Month | B6: bu-assist budget | C6: bu-assist actual | D6: bu-assist var | E6: bu-checkout budget | F6: bu-checkout actual | G6: bu-checkout var | H6: bu-datalake budget | I6: bu-datalake actual | J6: bu-datalake var | K6: bu-datasci budget | L6: bu-datasci actual | M6: bu-datasci var | N6: bu-platform budget | O6: bu-platform actual | P6: bu-platform var | Q6: bu-search budget | R6: bu-search actual | S6: bu-search var | T6: unallocated budget | U6: unallocated actual | V6: unallocated var | W6: Total budget | X6: Total actual | Y6: Total variance | Z6: Variance % | AA6: Status
A7: 45839 | B7: =$B$5*$B$4^1 -> 159051.06 | C7: ='02 Raw Cost Data'!I12 -> 157484.7 | D7: =C7-B7 -> -1566.3654 | E7: =$E$5*$B$4^1 -> 87235.687 | F7: ='02 Raw Cost Data'!J12 -> 93742.453 | G7: =F7-E7 -> 6506.7661 | H7: =$H$5*$B$4^1 -> 64708.381 | I7: ='02 Raw Cost Data'!K12 -> 71220.469 | J7: =I7-H7 -> 6512.0875 | K7: =$K$5*$B$4^1 -> 151962.29 | L7: ='02 Raw Cost Data'!L12 -> 154568.58 | M7: =L7-K7 -> 2606.2836 | N7: =$N$5*$B$4^1 -> 71901.384 | O7: ='02 Raw Cost Data'!M12 -> 70392.849 | P7: =O7-N7 -> -1508.5341 | Q7: =$Q$5*$B$4^1 -> 87279.823 | R7: ='02 Raw Cost Data'!N12 -> 97421.955 | S7: =R7-Q7 -> 10142.132 | T7: =$T$5*$B$4^1 -> 75101.187 | U7: ='02 Raw Cost Data'!O12 -> 78358.728 | V7: =U7-T7 -> 3257.5407 | W7: =B7+E7+H7+K7+N7+Q7+T7 -> 697239.81 | X7: =C7+F7+I7+L7+O7+R7+U7 -> 723189.72 | Y7: =X7-W7 -> 25949.91 | Z7: =IF(W7=0,0,Y7/W7) -> 0.037218056 | AA7: =IF(Z7>0.05,"Unfavourable",IF(Z7<-0.05,"Favourable","On plan")) -> On plan
A8: 45870 | B8: =$B$5*$B$4^2 -> 160914.33 | C8: ='02 Raw Cost Data'!I13 -> 164579.11 | D8: =C8-B8 -> 3664.775 | E8: =$E$5*$B$4^2 -> 88257.645 | F8: ='02 Raw Cost Data'!J13 -> 97362.162 | G8: =F8-E8 -> 9104.5163 | H8: =$H$5*$B$4^2 -> 65466.435 | I8: ='02 Raw Cost Data'!K13 -> 63816.123 | J8: =I8-H8 -> -1650.3117 | K8: =$K$5*$B$4^2 -> 153742.52 | L8: ='02 Raw Cost Data'!L13 -> 143516.31 | M8: =L8-K8 -> -10226.202 | N8: =$N$5*$B$4^2 -> 72743.702 | O8: ='02 Raw Cost Data'!M13 -> 73737.598 | P8: =O8-N8 -> 993.89605 | Q8: =$Q$5*$B$4^2 -> 88302.298 | R8: ='02 Raw Cost Data'!N13 -> 100098.44 | S8: =R8-Q8 -> 11796.137 | T8: =$T$5*$B$4^2 -> 75980.991 | U8: ='02 Raw Cost Data'!O13 -> 77229.281 | V8: =U8-T8 -> 1248.2897 | W8: =B8+E8+H8+K8+N8+Q8+T8 -> 705407.92 | X8: =C8+F8+I8+L8+O8+R8+U8 -> 720339.02 | Y8: =X8-W8 -> 14931.1 | Z8: =IF(W8=0,0,Y8/W8) -> 0.021166618 | AA8: =IF(Z8>0.05,"Unfavourable",IF(Z8<-0.05,"Favourable","On plan")) -> On plan
A9: 45901 | B9: =$B$5*$B$4^3 -> 162799.43 | C9: ='02 Raw Cost Data'!I14 -> 158979.41 | D9: =C9-B9 -> -3820.0155 | E9: =$E$5*$B$4^3 -> 89291.576 | F9: ='02 Raw Cost Data'!J14 -> 92261.506 | G9: =F9-E9 -> 2969.9297 | H9: =$H$5*$B$4^3 -> 66233.369 | I9: ='02 Raw Cost Data'!K14 -> 61211.517 | J9: =I9-H9 -> -5021.8513 | K9: =$K$5*$B$4^3 -> 155543.6 | L9: ='02 Raw Cost Data'!L14 -> 159667.6 | M9: =L9-K9 -> 4123.9979 | N9: =$N$5*$B$4^3 -> 73595.889 | O9: ='02 Raw Cost Data'!M14 -> 77160.957 | P9: =O9-N9 -> 3565.0684 | Q9: =$Q$5*$B$4^3 -> 89336.753 | R9: ='02 Raw Cost Data'!N14 -> 95928.862 | S9: =R9-Q9 -> 6592.1099 | T9: =$T$5*$B$4^3 -> 76871.102 | U9: ='02 Raw Cost Data'!O14 -> 81095.158 | V9: =U9-T9 -> 4224.056 | W9: =B9+E9+H9+K9+N9+Q9+T9 -> 713671.72 | X9: =C9+F9+I9+L9+O9+R9+U9 -> 726305.01 | Y9: =X9-W9 -> 12633.295 | Z9: =IF(W9=0,0,Y9/W9) -> 0.01770183 | AA9: =IF(Z9>0.05,"Unfavourable",IF(Z9<-0.05,"Favourable","On plan")) -> On plan
A10: 45931 | B10: =$B$5*$B$4^4 -> 164706.61 | C10: ='02 Raw Cost Data'!I15 -> 173558.54 | D10: =C10-B10 -> 8851.9301 | E10: =$E$5*$B$4^4 -> 90337.62 | F10: ='02 Raw Cost Data'!J15 -> 111068.97 | G10: =F10-E10 -> 20731.35 | H10: =$H$5*$B$4^4 -> 67009.287 | I10: ='02 Raw Cost Data'!K15 -> 61411.786 | J10: =I10-H10 -> -5597.5012 | K10: =$K$5*$B$4^4 -> 157365.78 | L10: ='02 Raw Cost Data'!L15 -> 164202.51 | M10: =L10-K10 -> 6836.7334 | N10: =$N$5*$B$4^4 -> 74458.058 | O10: ='02 Raw Cost Data'!M15 -> 87267.349 | P10: =O10-N10 -> 12809.291 | Q10: =$Q$5*$B$4^4 -> 90383.325 | R10: ='02 Raw Cost Data'!N15 -> 109009.59 | S10: =R10-Q10 -> 18626.262 | T10: =$T$5*$B$4^4 -> 77771.641 | U10: ='02 Raw Cost Data'!O15 -> 85190.819 | V10: =U10-T10 -> 7419.1784 | W10: =B10+E10+H10+K10+N10+Q10+T10 -> 722032.32 | X10: =C10+F10+I10+L10+O10+R10+U10 -> 791709.56 | Y10: =X10-W10 -> 69677.243 | Z10: =IF(W10=0,0,Y10/W10) -> 0.096501557 | AA10: =IF(Z10>0.05,"Unfavourable",IF(Z10<-0.05,"Favourable","On plan")) -> Unfavourable
A11: 45962 | B11: =$B$5*$B$4^5 -> 166636.14 | C11: ='02 Raw Cost Data'!I16 -> 170043.12 | D11: =C11-B11 -> 3406.9864 | E11: =$E$5*$B$4^5 -> 91395.918 | F11: ='02 Raw Cost Data'!J16 -> 132965.8 | G11: =F11-E11 -> 41569.88 | H11: =$H$5*$B$4^5 -> 67794.295 | I11: ='02 Raw Cost Data'!K16 -> 58841.39 | J11: =I11-H11 -> -8952.9053 | K11: =$K$5*$B$4^5 -> 159209.31 | L11: ='02 Raw Cost Data'!L16 -> 144469.26 | M11: =L11-K11 -> -14740.041 | N11: =$N$5*$B$4^5 -> 75330.328 | O11: ='02 Raw Cost Data'!M16 -> 85378.466 | P11: =O11-N11 -> 10048.138 | Q11: =$Q$5*$B$4^5 -> 91442.158 | R11: ='02 Raw Cost Data'!N16 -> 119213.62 | S11: =R11-Q11 -> 27771.465 | T11: =$T$5*$B$4^5 -> 78682.729 | U11: ='02 Raw Cost Data'!O16 -> 90806.45 | V11: =U11-T11 -> 12123.722 | W11: =B11+E11+H11+K11+N11+Q11+T11 -> 730490.87 | X11: =C11+F11+I11+L11+O11+R11+U11 -> 801718.11 | Y11: =X11-W11 -> 71227.245 | Z11: =IF(W11=0,0,Y11/W11) -> 0.097506002 | AA11: =IF(Z11>0.05,"Unfavourable",IF(Z11<-0.05,"Favourable","On plan")) -> Unfavourable
A12: 45992 | B12: =$B$5*$B$4^6 -> 168588.26 | C12: ='02 Raw Cost Data'!I17 -> 196719.21 | D12: =C12-B12 -> 28130.95 | E12: =$E$5*$B$4^6 -> 92466.613 | F12: ='02 Raw Cost Data'!J17 -> 126834.23 | G12: =F12-E12 -> 34367.621 | H12: =$H$5*$B$4^6 -> 68588.5 | I12: ='02 Raw Cost Data'!K17 -> 67374.564 | J12: =I12-H12 -> -1213.9352 | K12: =$K$5*$B$4^6 -> 161074.43 | L12: ='02 Raw Cost Data'!L17 -> 179764.62 | M12: =L12-K12 -> 18690.196 | N12: =$N$5*$B$4^6 -> 76212.817 | O12: ='02 Raw Cost Data'!M17 -> 77821.171 | P12: =O12-N12 -> 1608.3538 | Q12: =$Q$5*$B$4^6 -> 92513.396 | R12: ='02 Raw Cost Data'!N17 -> 113922.09 | S12: =R12-Q12 -> 21408.69 | T12: =$T$5*$B$4^6 -> 79604.491 | U12: ='02 Raw Cost Data'!O17 -> 93942.017 | V12: =U12-T12 -> 14337.526 | W12: =B12+E12+H12+K12+N12+Q12+T12 -> 739048.51 | X12: =C12+F12+I12+L12+O12+R12+U12 -> 856377.91 | Y12: =X12-W12 -> 117329.4 | Z12: =IF(W12=0,0,Y12/W12) -> 0.15875738 | AA12: =IF(Z12>0.05,"Unfavourable",IF(Z12<-0.05,"Favourable","On plan")) -> Unfavourable
A13: 46023 | B13: =$B$5*$B$4^7 -> 170563.26 | C13: ='02 Raw Cost Data'!I18 -> 198025.43 | D13: =C13-B13 -> 27462.173 | E13: =$E$5*$B$4^7 -> 93549.852 | F13: ='02 Raw Cost Data'!J18 -> 102962.32 | G13: =F13-E13 -> 9412.4702 | H13: =$H$5*$B$4^7 -> 69392.008 | I13: ='02 Raw Cost Data'!K18 -> 68852.693 | J13: =I13-H13 -> -539.31535 | K13: =$K$5*$B$4^7 -> 162961.4 | L13: ='02 Raw Cost Data'!L18 -> 181287.51 | M13: =L13-K13 -> 18326.103 | N13: =$N$5*$B$4^7 -> 77105.644 | O13: ='02 Raw Cost Data'!M18 -> 78034.495 | P13: =O13-N13 -> 928.85173 | Q13: =$Q$5*$B$4^7 -> 93597.182 | R13: ='02 Raw Cost Data'!N18 -> 92404.937 | S13: =R13-Q13 -> -1192.2449 | T13: =$T$5*$B$4^7 -> 80537.051 | U13: ='02 Raw Cost Data'!O18 -> 83037.662 | V13: =U13-T13 -> 2500.6114 | W13: =B13+E13+H13+K13+N13+Q13+T13 -> 747706.4 | X13: =C13+F13+I13+L13+O13+R13+U13 -> 804605.05 | Y13: =X13-W13 -> 56898.649 | Z13: =IF(W13=0,0,Y13/W13) -> 0.076097581 | AA13: =IF(Z13>0.05,"Unfavourable",IF(Z13<-0.05,"Favourable","On plan")) -> Unfavourable
A14: 46054 | B14: =$B$5*$B$4^8 -> 172561.4 | C14: ='02 Raw Cost Data'!I19 -> 172349.58 | D14: =C14-B14 -> -211.81291 | E14: =$E$5*$B$4^8 -> 94645.781 | F14: ='02 Raw Cost Data'!J19 -> 93784.657 | G14: =F14-E14 -> -861.12407 | H14: =$H$5*$B$4^8 -> 70204.93 | I14: ='02 Raw Cost Data'!K19 -> 64577.367 | J14: =I14-H14 -> -5627.5627 | K14: =$K$5*$B$4^8 -> 164870.48 | L14: ='02 Raw Cost Data'!L19 -> 145215.4 | M14: =L14-K14 -> -19655.079 | N14: =$N$5*$B$4^8 -> 78008.93 | O14: ='02 Raw Cost Data'!M19 -> 67682.038 | P14: =O14-N14 -> -10326.892 | Q14: =$Q$5*$B$4^8 -> 94693.666 | R14: ='02 Raw Cost Data'!N19 -> 87466.732 | S14: =R14-Q14 -> -7226.9337 | T14: =$T$5*$B$4^8 -> 81480.535 | U14: ='02 Raw Cost Data'!O19 -> 77358.65 | V14: =U14-T14 -> -4121.8859 | W14: =B14+E14+H14+K14+N14+Q14+T14 -> 756465.72 | X14: =C14+F14+I14+L14+O14+R14+U14 -> 708434.43 | Y14: =X14-W14 -> -48031.291 | Z14: =IF(W14=0,0,Y14/W14) -> -0.063494339 | AA14: =IF(Z14>0.05,"Unfavourable",IF(Z14<-0.05,"Favourable","On plan")) -> Favourable
A15: 46082 | B15: =$B$5*$B$4^9 -> 174582.94 | C15: ='02 Raw Cost Data'!I20 -> 207714.89 | D15: =C15-B15 -> 33131.953 | E15: =$E$5*$B$4^9 -> 95754.548 | F15: ='02 Raw Cost Data'!J20 -> 107075.45 | G15: =F15-E15 -> 11320.897 | H15: =$H$5*$B$4^9 -> 71027.375 | I15: ='02 Raw Cost Data'!K20 -> 74857.575 | J15: =I15-H15 -> 3830.2 | K15: =$K$5*$B$4^9 -> 166801.93 | L15: ='02 Raw Cost Data'!L20 -> 219042.95 | M15: =L15-K15 -> 52241.019 | N15: =$N$5*$B$4^9 -> 78922.798 | O15: ='02 Raw Cost Data'!M20 -> 74464.015 | P15: =O15-N15 -> -4458.7836 | Q15: =$Q$5*$B$4^9 -> 95802.994 | R15: ='02 Raw Cost Data'!N20 -> 100600.74 | S15: =R15-Q15 -> 4797.7467 | T15: =$T$5*$B$4^9 -> 82435.073 | U15: ='02 Raw Cost Data'!O20 -> 86338.602 | V15: =U15-T15 -> 3903.5288 | W15: =B15+E15+H15+K15+N15+Q15+T15 -> 765327.65 | X15: =C15+F15+I15+L15+O15+R15+U15 -> 870094.21 | Y15: =X15-W15 -> 104766.56 | Z15: =IF(W15=0,0,Y15/W15) -> 0.13689112 | AA15: =IF(Z15>0.05,"Unfavourable",IF(Z15<-0.05,"Favourable","On plan")) -> Unfavourable
A16: 46113 | B16: =$B$5*$B$4^10 -> 176628.16 | C16: ='02 Raw Cost Data'!I21 -> 215101.33 | D16: =C16-B16 -> 38473.171 | E16: =$E$5*$B$4^10 -> 96876.305 | F16: ='02 Raw Cost Data'!J21 -> 99504.595 | G16: =F16-E16 -> 2628.2907 | H16: =$H$5*$B$4^10 -> 71859.455 | I16: ='02 Raw Cost Data'!K21 -> 78120.424 | J16: =I16-H16 -> 6260.9693 | K16: =$K$5*$B$4^10 -> 168756 | L16: ='02 Raw Cost Data'!L21 -> 239549.44 | M16: =L16-K16 -> 70793.443 | N16: =$N$5*$B$4^10 -> 79847.372 | O16: ='02 Raw Cost Data'!M21 -> 72718.11 | P16: =O16-N16 -> -7129.2626 | Q16: =$Q$5*$B$4^10 -> 96925.318 | R16: ='02 Raw Cost Data'!N21 -> 94561.92 | S16: =R16-Q16 -> -2363.3978 | T16: =$T$5*$B$4^10 -> 83400.793 | U16: ='02 Raw Cost Data'!O21 -> 81252.916 | V16: =U16-T16 -> -2147.8776 | W16: =B16+E16+H16+K16+N16+Q16+T16 -> 774293.4 | X16: =C16+F16+I16+L16+O16+R16+U16 -> 880808.74 | Y16: =X16-W16 -> 106515.34 | Z16: =IF(W16=0,0,Y16/W16) -> 0.13756457 | AA16: =IF(Z16>0.05,"Unfavourable",IF(Z16<-0.05,"Favourable","On plan")) -> Unfavourable
A17: 46143 | B17: =$B$5*$B$4^11 -> 178697.35 | C17: ='02 Raw Cost Data'!I22 -> 199289.57 | D17: =C17-B17 -> 20592.227 | E17: =$E$5*$B$4^11 -> 98011.202 | F17: ='02 Raw Cost Data'!J22 -> 107902.82 | G17: =F17-E17 -> 9891.6134 | H17: =$H$5*$B$4^11 -> 72701.282 | I17: ='02 Raw Cost Data'!K22 -> 79901.899 | J17: =I17-H17 -> 7200.6167 | K17: =$K$5*$B$4^11 -> 170732.96 | L17: ='02 Raw Cost Data'!L22 -> 182830.56 | M17: =L17-K17 -> 12097.602 | N17: =$N$5*$B$4^11 -> 80782.777 | O17: ='02 Raw Cost Data'!M22 -> 77319.347 | P17: =O17-N17 -> -3463.4308 | Q17: =$Q$5*$B$4^11 -> 98060.79 | R17: ='02 Raw Cost Data'!N22 -> 102550.65 | S17: =R17-Q17 -> 4489.8596 | T17: =$T$5*$B$4^11 -> 84377.827 | U17: ='02 Raw Cost Data'!O22 -> 87225.165 | V17: =U17-T17 -> 2847.3382 | W17: =B17+E17+H17+K17+N17+Q17+T17 -> 783364.19 | X17: =C17+F17+I17+L17+O17+R17+U17 -> 837020.01 | Y17: =X17-W17 -> 53655.826 | Z17: =IF(W17=0,0,Y17/W17) -> 0.068494101 | AA17: =IF(Z17>0.05,"Unfavourable",IF(Z17<-0.05,"Favourable","On plan")) -> Unfavourable
A18: Total | B18: =SUM(B7:B17) -> 1855728.9 | C18: =SUM(C7:C17) -> 2013844.9 | D18: =SUM(D7:D17) -> 158115.97 | E18: =SUM(E7:E17) -> 1017822.7 | F18: =SUM(F7:F17) -> 1165465 | G18: =SUM(G7:G17) -> 147642.21 | H18: =SUM(H7:H17) -> 754985.32 | I18: =SUM(I7:I17) -> 750185.81 | ... Y18: =SUM(Y7:Y17) -> 585553.28 | Z18: =IF(W18=0,0,Y18/W18) -> 0.071979076
A20: Every business unit's bill rose over the period. Budget vs actual cannot tell you whether that is growth or waste -- the unit-economics layer in the repository does. This sheet shows the variance; the engine explains it.

Sheet 06 Forecast
A1: Forecast
A2: Twelve months forward. Trend = linear regression of each unit's monthly actuals on time (FORECAST). Run-rate = last three months' average grown at the active scenario's cloud growth. Two methods shown so the gap between them is visible.
A3: SIMULATED DATA. The estate is synthetic (FOCUS 1.2, 400 resources, 540 days). Figures illustrate the method; ground truth exists only because the data is simulated.
A6: Monthly growth factor (active scenario) | B6: =(1+'10 Assumptions'!$B$38)^(1/12) -> 1.0117149
A7: Last 3 months avg. total | B7: =AVERAGE('02 Raw Cost Data'!P20:P22) -> 862640.99
A8: Month | B8: bu-assist (trend) | C8: bu-checkout (trend) | D8: bu-datalake (trend) | E8: bu-datasci (trend) | F8: bu-platform (trend) | G8: bu-search (trend) | H8: unallocated (trend) | I8: Total (trend) | J8: Total (run-rate × growth) | K8: Gap
A9: 46174 | B9: =MAX(0,FORECAST(18,'02 Raw Cost Data'!$I$6:$I$22,'02 Raw Cost Data'!$H$6:$H$22)) -> 207745.85 | C9: =MAX(0,FORECAST(18,'02 Raw Cost Data'!$J$6:$J$22,'02 Raw Cost Data'!$H$6:$H$22)) -> 116352.86 | D9: =MAX(0,FORECAST(18,'02 Raw Cost Data'!$K$6:$K$22,'02 Raw Cost Data'!$H$6:$H$22)) -> 74573.172 | E9: =MAX(0,FORECAST(18,'02 Raw Cost Data'!$L$6:$L$22,'02 Raw Cost Data'!$H$6:$H$22)) -> 200417.06 | F9: =MAX(0,FORECAST(18,'02 Raw Cost Data'!$M$6:$M$22,'02 Raw Cost Data'!$H$6:$H$22)) -> 78415.899 | G9: =MAX(0,FORECAST(18,'02 Raw Cost Data'!$N$6:$N$22,'02 Raw Cost Data'!$H$6:$H$22)) -> 106842.68 | H9: =MAX(0,FORECAST(18,'02 Raw Cost Data'!$O$6:$O$22,'02 Raw Cost Data'!$H$6:$H$22)) -> 89642.279 | I9: =SUM(B9:H9) -> 873989.79 | J9: =$B$7*$B$6^1 -> 872746.76 | K9: =J9-I9 -> -1243.0392
A10: 46204 | B10: =MAX(0,FORECAST(19,'02 Raw Cost Data'!$I$6:$I$22,'02 Raw Cost Data'!$H$6:$H$22)) -> 211501.26 | C10: =MAX(0,FORECAST(19,'02 Raw Cost Data'!$J$6:$J$22,'02 Raw Cost Data'!$H$6:$H$22)) -> 118282.14 | D10: =MAX(0,FORECAST(19,'02 Raw Cost Data'!$K$6:$K$22,'02 Raw Cost Data'!$H$6:$H$22)) -> 75447.705 | E10: =MAX(0,FORECAST(19,'02 Raw Cost Data'!$L$6:$L$22,'02 Raw Cost Data'!$H$6:$H$22)) -> 204284.77 | F10: =MAX(0,FORECAST(19,'02 Raw Cost Data'!$M$6:$M$22,'02 Raw Cost Data'!$H$6:$H$22)) -> 78838.651 | G10: =MAX(0,FORECAST(19,'02 Raw Cost Data'!$N$6:$N$22,'02 Raw Cost Data'!$H$6:$H$22)) -> 108055.3 | H10: =MAX(0,FORECAST(19,'02 Raw Cost Data'!$O$6:$O$22,'02 Raw Cost Data'!$H$6:$H$22)) -> 90666.422 | I10: =SUM(B10:H10) -> 887076.25 | J10: =$B$7*$B$6^2 -> 882970.91 | K10: =J10-I10 -> -4105.3344
A11: 46235 | B11: =MAX(0,FORECAST(20,'02 Raw Cost Data'!$I$6:$I$22,'02 Raw Cost Data'!$H$6:$H$22)) -> 215256.67 | C11: =MAX(0,FORECAST(20,'02 Raw Cost Data'!$J$6:$J$22,'02 Raw Cost Data'!$H$6:$H$22)) -> 120211.42 | D11: =MAX(0,FORECAST(20,'02 Raw Cost Data'!$K$6:$K$22,'02 Raw Cost Data'!$H$6:$H$22)) -> 76322.238 | E11: =MAX(0,FORECAST(20,'02 Raw Cost Data'!$L$6:$L$22,'02 Raw Cost Data'!$H$6:$H$22)) -> 208152.48 | F11: =MAX(0,FORECAST(20,'02 Raw Cost Data'!$M$6:$M$22,'02 Raw Cost Data'!$H$6:$H$22)) -> 79261.403 | G11: =MAX(0,FORECAST(20,'02 Raw Cost Data'!$N$6:$N$22,'02 Raw Cost Data'!$H$6:$H$22)) -> 109267.92 | H11: =MAX(0,FORECAST(20,'02 Raw Cost Data'!$O$6:$O$22,'02 Raw Cost Data'!$H$6:$H$22)) -> 91690.564 | I11: =SUM(B11:H11) -> 900162.7 | J11: =$B$7*$B$6^3 -> 893314.84 | K11: =J11-I11 -> -6847.8544
A12: 46266 | B12: =MAX(0,FORECAST(21,'02 Raw Cost Data'!$I$6:$I$22,'02 Raw Cost Data'!$H$6:$H$22)) -> 219012.09 | C12: =MAX(0,FORECAST(21,'02 Raw Cost Data'!$J$6:$J$22,'02 Raw Cost Data'!$H$6:$H$22)) -> 122140.71 | D12: =MAX(0,FORECAST(21,'02 Raw Cost Data'!$K$6:$K$22,'02 Raw Cost Data'!$H$6:$H$22)) -> 77196.77 | E12: =MAX(0,FORECAST(21,'02 Raw Cost Data'!$L$6:$L$22,'02 Raw Cost Data'!$H$6:$H$22)) -> 212020.19 | F12: =MAX(0,FORECAST(21,'02 Raw Cost Data'!$M$6:$M$22,'02 Raw Cost Data'!$H$6:$H$22)) -> 79684.154 | G12: =MAX(0,FORECAST(21,'02 Raw Cost Data'!$N$6:$N$22,'02 Raw Cost Data'!$H$6:$H$22)) -> 110480.54 | H12: =MAX(0,FORECAST(21,'02 Raw Cost Data'!$O$6:$O$22,'02 Raw Cost Data'!$H$6:$H$22)) -> 92714.707 | I12: =SUM(B12:H12) -> 913249.15 | J12: =$B$7*$B$6^4 -> 903779.95 | K12: =J12-I12 -> -9469.1962
A13: 46296 | B13: =MAX(0,FORECAST(22,'02 Raw Cost Data'!$I$6:$I$22,'02 Raw Cost Data'!$H$6:$H$22)) -> 222767.5 | C13: =MAX(0,FORECAST(22,'02 Raw Cost Data'!$J$6:$J$22,'02 Raw Cost Data'!$H$6:$H$22)) -> 124069.99 | D13: =MAX(0,FORECAST(22,'02 Raw Cost Data'!$K$6:$K$22,'02 Raw Cost Data'!$H$6:$H$22)) -> 78071.303 | E13: =MAX(0,FORECAST(22,'02 Raw Cost Data'!$L$6:$L$22,'02 Raw Cost Data'!$H$6:$H$22)) -> 215887.89 | F13: =MAX(0,FORECAST(22,'02 Raw Cost Data'!$M$6:$M$22,'02 Raw Cost Data'!$H$6:$H$22)) -> 80106.906 | G13: =MAX(0,FORECAST(22,'02 Raw Cost Data'!$N$6:$N$22,'02 Raw Cost Data'!$H$6:$H$22)) -> 111693.16 | H13: =MAX(0,FORECAST(22,'02 Raw Cost Data'!$O$6:$O$22,'02 Raw Cost Data'!$H$6:$H$22)) -> 93738.85 | I13: =SUM(B13:H13) -> 926335.6 | J13: =$B$7*$B$6^5 -> 914367.66 | K13: =J13-I13 -> -11967.94
A14: 46327 | B14: =MAX(0,FORECAST(23,'02 Raw Cost Data'!$I$6:$I$22,'02 Raw Cost Data'!$H$6:$H$22)) -> 226522.91 | C14: =MAX(0,FORECAST(23,'02 Raw Cost Data'!$J$6:$J$22,'02 Raw Cost Data'!$H$6:$H$22)) -> 125999.27 | D14: =MAX(0,FORECAST(23,'02 Raw Cost Data'!$K$6:$K$22,'02 Raw Cost Data'!$H$6:$H$22)) -> 78945.835 | E14: =MAX(0,FORECAST(23,'02 Raw Cost Data'!$L$6:$L$22,'02 Raw Cost Data'!$H$6:$H$22)) -> 219755.6 | F14: =MAX(0,FORECAST(23,'02 Raw Cost Data'!$M$6:$M$22,'02 Raw Cost Data'!$H$6:$H$22)) -> 80529.657 | G14: =MAX(0,FORECAST(23,'02 Raw Cost Data'!$N$6:$N$22,'02 Raw Cost Data'!$H$6:$H$22)) -> 112905.78 | H14: =MAX(0,FORECAST(23,'02 Raw Cost Data'!$O$6:$O$22,'02 Raw Cost Data'!$H$6:$H$22)) -> 94762.993 | I14: =SUM(B14:H14) -> 939422.05 | J14: =$B$7*$B$6^6 -> 925079.4 | K14: =J14-I14 -> -14342.65
A15: 46357 | B15: =MAX(0,FORECAST(24,'02 Raw Cost Data'!$I$6:$I$22,'02 Raw Cost Data'!$H$6:$H$22)) -> 230278.33 | C15: =MAX(0,FORECAST(24,'02 Raw Cost Data'!$J$6:$J$22,'02 Raw Cost Data'!$H$6:$H$22)) -> 127928.55 | D15: =MAX(0,FORECAST(24,'02 Raw Cost Data'!$K$6:$K$22,'02 Raw Cost Data'!$H$6:$H$22)) -> 79820.368 | E15: =MAX(0,FORECAST(24,'02 Raw Cost Data'!$L$6:$L$22,'02 Raw Cost Data'!$H$6:$H$22)) -> 223623.31 | F15: =MAX(0,FORECAST(24,'02 Raw Cost Data'!$M$6:$M$22,'02 Raw Cost Data'!$H$6:$H$22)) -> 80952.409 | G15: =MAX(0,FORECAST(24,'02 Raw Cost Data'!$N$6:$N$22,'02 Raw Cost Data'!$H$6:$H$22)) -> 114118.4 | H15: =MAX(0,FORECAST(24,'02 Raw Cost Data'!$O$6:$O$22,'02 Raw Cost Data'!$H$6:$H$22)) -> 95787.136 | I15: =SUM(B15:H15) -> 952508.5 | J15: =$B$7*$B$6^7 -> 935916.63 | K15: =J15-I15 -> -16591.872
A16: 46388 | B16: =MAX(0,FORECAST(25,'02 Raw Cost Data'!$I$6:$I$22,'02 Raw Cost Data'!$H$6:$H$22)) -> 234033.74 | C16: =MAX(0,FORECAST(25,'02 Raw Cost Data'!$J$6:$J$22,'02 Raw Cost Data'!$H$6:$H$22)) -> 129857.84 | D16: =MAX(0,FORECAST(25,'02 Raw Cost Data'!$K$6:$K$22,'02 Raw Cost Data'!$H$6:$H$22)) -> 80694.901 | E16: =MAX(0,FORECAST(25,'02 Raw Cost Data'!$L$6:$L$22,'02 Raw Cost Data'!$H$6:$H$22)) -> 227491.02 | F16: =MAX(0,FORECAST(25,'02 Raw Cost Data'!$M$6:$M$22,'02 Raw Cost Data'!$H$6:$H$22)) -> 81375.16 | G16: =MAX(0,FORECAST(25,'02 Raw Cost Data'!$N$6:$N$22,'02 Raw Cost Data'!$H$6:$H$22)) -> 115331.02 | H16: =MAX(0,FORECAST(25,'02 Raw Cost Data'!$O$6:$O$22,'02 Raw Cost Data'!$H$6:$H$22)) -> 96811.279 | I16: =SUM(B16:H16) -> 965594.95 | J16: =$B$7*$B$6^8 -> 946880.81 | K16: =J16-I16 -> -18714.138
A17: 46419 | B17: =MAX(0,FORECAST(26,'02 Raw Cost Data'!$I$6:$I$22,'02 Raw Cost Data'!$H$6:$H$22)) -> 237789.15 | C17: =MAX(0,FORECAST(26,'02 Raw Cost Data'!$J$6:$J$22,'02 Raw Cost Data'!$H$6:$H$22)) -> 131787.12 | D17: =MAX(0,FORECAST(26,'02 Raw Cost Data'!$K$6:$K$22,'02 Raw Cost Data'!$H$6:$H$22)) -> 81569.433 | E17: =MAX(0,FORECAST(26,'02 Raw Cost Data'!$L$6:$L$22,'02 Raw Cost Data'!$H$6:$H$22)) -> 231358.72 | F17: =MAX(0,FORECAST(26,'02 Raw Cost Data'!$M$6:$M$22,'02 Raw Cost Data'!$H$6:$H$22)) -> 81797.912 | G17: =MAX(0,FORECAST(26,'02 Raw Cost Data'!$N$6:$N$22,'02 Raw Cost Data'!$H$6:$H$22)) -> 116543.64 | H17: =MAX(0,FORECAST(26,'02 Raw Cost Data'!$O$6:$O$22,'02 Raw Cost Data'!$H$6:$H$22)) -> 97835.422 | I17: =SUM(B17:H17) -> 978681.4 | J17: =$B$7*$B$6^9 -> 957973.44 | K17: =J17-I17 -> -20707.959
A18: 46447 | B18: =MAX(0,FORECAST(27,'02 Raw Cost Data'!$I$6:$I$22,'02 Raw Cost Data'!$H$6:$H$22)) -> 241544.57 | C18: =MAX(0,FORECAST(27,'02 Raw Cost Data'!$J$6:$J$22,'02 Raw Cost Data'!$H$6:$H$22)) -> 133716.4 | D18: =MAX(0,FORECAST(27,'02 Raw Cost Data'!$K$6:$K$22,'02 Raw Cost Data'!$H$6:$H$22)) -> 82443.966 | E18: =MAX(0,FORECAST(27,'02 Raw Cost Data'!$L$6:$L$22,'02 Raw Cost Data'!$H$6:$H$22)) -> 235226.43 | F18: =MAX(0,FORECAST(27,'02 Raw Cost Data'!$M$6:$M$22,'02 Raw Cost Data'!$H$6:$H$22)) -> 82220.663 | G18: =MAX(0,FORECAST(27,'02 Raw Cost Data'!$N$6:$N$22,'02 Raw Cost Data'!$H$6:$H$22)) -> 117756.26 | H18: =MAX(0,FORECAST(27,'02 Raw Cost Data'!$O$6:$O$22,'02 Raw Cost Data'!$H$6:$H$22)) -> 98859.565 | I18: =SUM(B18:H18) -> 991767.85 | J18: =$B$7*$B$6^10 -> 969196.02 | K18: =J18-I18 -> -22571.83
A19: 46478 | B19: =MAX(0,FORECAST(28,'02 Raw Cost Data'!$I$6:$I$22,'02 Raw Cost Data'!$H$6:$H$22)) -> 245299.98 | C19: =MAX(0,FORECAST(28,'02 Raw Cost Data'!$J$6:$J$22,'02 Raw Cost Data'!$H$6:$H$22)) -> 135645.68 | D19: =MAX(0,FORECAST(28,'02 Raw Cost Data'!$K$6:$K$22,'02 Raw Cost Data'!$H$6:$H$22)) -> 83318.499 | E19: =MAX(0,FORECAST(28,'02 Raw Cost Data'!$L$6:$L$22,'02 Raw Cost Data'!$H$6:$H$22)) -> 239094.14 | F19: =MAX(0,FORECAST(28,'02 Raw Cost Data'!$M$6:$M$22,'02 Raw Cost Data'!$H$6:$H$22)) -> 82643.415 | G19: =MAX(0,FORECAST(28,'02 Raw Cost Data'!$N$6:$N$22,'02 Raw Cost Data'!$H$6:$H$22)) -> 118968.88 | H19: =MAX(0,FORECAST(28,'02 Raw Cost Data'!$O$6:$O$22,'02 Raw Cost Data'!$H$6:$H$22)) -> 99883.708 | I19: =SUM(B19:H19) -> 1004854.3 | J19: =$B$7*$B$6^11 -> 980550.07 | K19: =J19-I19 -> -24304.23
A20: 46508 | B20: =MAX(0,FORECAST(29,'02 Raw Cost Data'!$I$6:$I$22,'02 Raw Cost Data'!$H$6:$H$22)) -> 249055.39 | C20: =MAX(0,FORECAST(29,'02 Raw Cost Data'!$J$6:$J$22,'02 Raw Cost Data'!$H$6:$H$22)) -> 137574.97 | D20: =MAX(0,FORECAST(29,'02 Raw Cost Data'!$K$6:$K$22,'02 Raw Cost Data'!$H$6:$H$22)) -> 84193.031 | E20: =MAX(0,FORECAST(29,'02 Raw Cost Data'!$L$6:$L$22,'02 Raw Cost Data'!$H$6:$H$22)) -> 242961.85 | F20: =MAX(0,FORECAST(29,'02 Raw Cost Data'!$M$6:$M$22,'02 Raw Cost Data'!$H$6:$H$22)) -> 83066.167 | G20: =MAX(0,FORECAST(29,'02 Raw Cost Data'!$N$6:$N$22,'02 Raw Cost Data'!$H$6:$H$22)) -> 120181.5 | H20: =MAX(0,FORECAST(29,'02 Raw Cost Data'!$O$6:$O$22,'02 Raw Cost Data'!$H$6:$H$22)) -> 100907.85 | I20: =SUM(B20:H20) -> 1017940.8 | J20: =$B$7*$B$6^12 -> 992037.14 | K20: =J20-I20 -> -25903.619
A21: 12-month total | B21: =SUM(B9:B20) -> 2740807.4 | C21: =SUM(C9:C20) -> 1523567 | D21: =SUM(D9:D20) -> 952597.22 | E21: =SUM(E9:E20) -> 2660273.5 | F21: =SUM(F9:F20) -> 968892.4 | G21: =SUM(G9:G20) -> 1362145.1 | H21: =SUM(H9:H20) -> 1143300.8 | I21: =SUM(I9:I20) -> 11351583 | ... K21: =SUM(K9:K20) -> -176769.66
A23: A linear trend extrapolates the whole history; the run-rate method trusts only the last quarter. When they disagree by more than ~10%, the recent quarter contains something the trend has not caught up with.

Sheet 07 ROI Analysis
A1: ROI analysis
A2: Programme economics under the active scenario. Savings are the credited annual figure from Savings Attribution, scaled by effect realisation and decayed by persistence. Costs are the programme inputs scaled by the cost multiplier.
A3: SIMULATED DATA. The estate is synthetic (FOCUS 1.2, 400 resources, 540 days). Figures illustrate the method; ground truth exists only because the data is simulated.
A5: Inputs (links)
A6: Credited annual savings (measurement) | B6: ='04 Savings Attribution'!$D$133 -> 1872634
A7: Effect realisation (scenario) | B7: ='10 Assumptions'!$B$36 -> 1
A8: Savings persistence (scenario) | B8: ='10 Assumptions'!$B$39 -> 0.85
A9: Programme cost multiplier (scenario) | B9: ='10 Assumptions'!$B$37 -> 1
A10: Discount rate | B10: ='10 Assumptions'!$B$6 -> 0.12
A11: Annual programme run cost | B11: =('10 Assumptions'!$B$11*'10 Assumptions'!$B$12+'10 Assumptions'!$B$13)*'10 Assumptions'!$B$37 -> 330000
A12: One-time setup (year 0) | B12: ='10 Assumptions'!$B$14*'10 Assumptions'!$B$37 -> 50000
A13: Intervention engineering, one-time (year 0) | B13: ='04 Savings Attribution'!$D$127*'10 Assumptions'!$B$15*'10 Assumptions'!$B$16*'10 Assumptions'!$B$37 -> 280800
A14: Year-1 ramp | B14: ='10 Assumptions'!$B$17 -> 0.5
A16: Cash flows
B17: Year 0 | C17: Year 1 | D17: Year 2 | E17: Year 3 | F17: Year 4 | G17: Year 5 | H17: Note
A18: Realised savings | B18: =0 -> 0 | C18: =$B$6*$B$7*$B$14 -> 936317.02 | D18: =$B$6*$B$7*$B$8^1 -> 1591738.9 | E18: =$B$6*$B$7*$B$8^2 -> 1352978.1 | F18: =$B$6*$B$7*$B$8^3 -> 1150031.4 | G18: =$B$6*$B$7*$B$8^4 -> 977526.67 | H18: credited × realisation × ramp (yr 1) or persistence^(t−1) (yr 2+)
A19: Programme cost | B19: =-($B$12+$B$13) -> -330800 | C19: =-$B$11 -> -330000 | D19: =-$B$11 -> -330000 | E19: =-$B$11 -> -330000 | F19: =-$B$11 -> -330000 | G19: =-$B$11 -> -330000 | H19: setup + intervention engineering in year 0; run cost yrs 1–5; × cost multiplier
A20: Net cash flow | B20: =B18+B19 -> -330800 | C20: =C18+C19 -> 606317.02 | D20: =D18+D19 -> 1261738.9 | E20: =E18+E19 -> 1022978.1 | F20: =F18+F19 -> 820031.38 | G20: =G18+G19 -> 647526.67
A21: Cumulative net cash flow | B21: =B20 -> -330800 | C21: =B21+C20 -> 275517.02 | D21: =C21+D20 -> 1537256 | E21: =D21+E20 -> 2560234.1 | F21: =E21+F20 -> 3380265.4 | G21: =F21+G20 -> 4027792.1
A22: Discount factor | B22: =1/(1+$B$10)^0 -> 1 | C22: =1/(1+$B$10)^1 -> 0.89285714 | D22: =1/(1+$B$10)^2 -> 0.79719388 | E22: =1/(1+$B$10)^3 -> 0.71178025 | F22: =1/(1+$B$10)^4 -> 0.63551808 | G22: =1/(1+$B$10)^5 -> 0.56742686
A23: Present value of net | B23: =B20*B22 -> -330800 | C23: =C20*C22 -> 541354.48 | D23: =D20*D22 -> 1005850.6 | E23: =E20*E22 -> 728135.6 | F23: =F20*F22 -> 521144.77 | G23: =G20*G22 -> 367424.02
A25: Results
A26: Net present value (5 years) | B26: =SUM(B23:G23) -> 2833109.4
A27: Present value of savings | B27: =SUMPRODUCT(C18:G18,C22:G22) -> 4353485.6
A28: Present value of programme cost | B28: =(-B19-SUMPRODUCT(C19:G19,C22:G22)) -> 1520376.1
A29: Benefit-to-cost ratio | B29: =IF((-B19-SUMPRODUCT(C19:G19,C22:G22))=0,0,SUMPRODUCT(C18:G18,C22:G22)/(-B19-SUMPRODUCT(C19:G19,C22:G22))) -> 2.8634267
A30: Return on investment (PV basis) | B30: =IF((-B19-SUMPRODUCT(C19:G19,C22:G22))=0,0,(SUMPRODUCT(C18:G18,C22:G22)-(-B19-SUMPRODUCT(C19:G19,C22:G22)))/(-B19-SUMPRODUCT(C19:G19,C22:G22))) -> 1.8634267
A31: Internal rate of return | B31: =IFERROR(IRR(B20:G20),"n/a") -> 2.3364268
A32: Payback (months) | B32: =IF(B21>=0,0,IF(C21>=0,12*(1-1)+12*(-B21)/C20,IF(D21>=0,12*(2-1)+12*(-C21)/D20,IF(E21>=0,12*(3-1)+12*(-D21)/E20,IF(F21>=0,12*(4-1)+12*(-E21)/F20,IF(G21>=0,12*(5-1)+12*(-F21)/G20,"beyond 5 yrs")))))) -> 6.54707
A33: Year-1 ROI (net year 1 ÷ year-0 outlay + run) | B33: =IF(($B$12+$B$13+$B$11)=0,0,D20/($B$12+$B$13+$B$11)) -> 1.9094112
A35: What the before/after number would have said
A36: Before/after reported annual savings | B36: ='04 Savings Attribution'!$D$131 -> 1693741
A37: Credited savings (identified, gated) | B37: =$B$6 -> 1872634
A38: Difference the method makes to the headline | B38: =$B$6-$B$36 -> 178893.04
A39: SIMULATED: gross misattribution inside the before/after total | B39: ='04 Savings Attribution'!$D$135 -> 450967.84
A41: The aggregate can look close while every individual attribution is wrong: errors in both directions net out. Gross misattribution is the sum of the absolute errors, and it is what a budget owner actually experiences.

Sheet 08 Scenario Analysis
A1: Scenario analysis
A2: Base, Bull and Bear computed side by side from the driver table on Assumptions. Independent of the active-scenario selector, so all three are always visible.
A3: SIMULATED DATA. The estate is synthetic (FOCUS 1.2, 400 resources, 540 days). Figures illustrate the method; ground truth exists only because the data is simulated.
B5: Base | C5: Bull | D5: Bear | E5: How it is computed
A6: Drivers
A7: Effect realisation | B7: ='10 Assumptions'!B30 -> 1 | C7: ='10 Assumptions'!C30 -> 1.1 | D7: ='10 Assumptions'!D30 -> 0.75
A8: Programme cost multiplier | B8: ='10 Assumptions'!B31 -> 1 | C8: ='10 Assumptions'!C31 -> 0.9 | D8: ='10 Assumptions'!D31 -> 1.3
A9: Cloud growth (forecast) | B9: ='10 Assumptions'!B32 -> 0.15 | C9: ='10 Assumptions'!C32 -> 0.1 | D9: ='10 Assumptions'!D32 -> 0.25
A10: Savings persistence | B10: ='10 Assumptions'!B33 -> 0.85 | C10: ='10 Assumptions'!C33 -> 0.9 | D10: ='10 Assumptions'!D33 -> 0.7
A12: Constants
A13: Credited annual savings | B13: ='04 Savings Attribution'!$D$133 -> 1872634 | C13: ='04 Savings Attribution'!$D$133 -> 1872634 | D13: ='04 Savings Attribution'!$D$133 -> 1872634
A14: Discount rate | B14: ='10 Assumptions'!$B$6 -> 0.12 | C14: ='10 Assumptions'!$B$6 -> 0.12 | D14: ='10 Assumptions'!$B$6 -> 0.12
A15: Annual run cost (before multiplier) | B15: ='10 Assumptions'!$B$11*'10 Assumptions'!$B$12+'10 Assumptions'!$B$13 -> 330000 | C15: ='10 Assumptions'!$B$11*'10 Assumptions'!$B$12+'10 Assumptions'!$B$13 -> 330000 | D15: ='10 Assumptions'!$B$11*'10 Assumptions'!$B$12+'10 Assumptions'!$B$13 -> 330000
A16: Setup (before multiplier) | B16: ='10 Assumptions'!$B$14 -> 50000 | C16: ='10 Assumptions'!$B$14 -> 50000 | D16: ='10 Assumptions'!$B$14 -> 50000
A17: Intervention engineering (before multiplier) | B17: ='04 Savings Attribution'!$D$127*'10 Assumptions'!$B$15*'10 Assumptions'!$B$16 -> 280800 | C17: ='04 Savings Attribution'!$D$127*'10 Assumptions'!$B$15*'10 Assumptions'!$B$16 -> 280800 | D17: ='04 Savings Attribution'!$D$127*'10 Assumptions'!$B$15*'10 Assumptions'!$B$16 -> 280800
A18: Year-1 ramp | B18: ='10 Assumptions'!$B$17 -> 0.5 | C18: ='10 Assumptions'!$B$17 -> 0.5 | D18: ='10 Assumptions'!$B$17 -> 0.5
A20: Results
A21: Year-1 realised savings | B21: =B13*B7*B18 -> 936317.02 | C21: =C13*C7*C18 -> 1029948.7 | D21: =D13*D7*D18 -> 702237.77 | E21: credited × realisation × ramp
A22: PV of savings, 5 years | B22: =(B13*B7*(B18/(1+B14)+SUMPRODUCT(B10^({2,3,4,5}-1)/(1+B14)^{2,3,4,5}))) -> 4353485.6 | C22: =(C13*C7*(C18/(1+C14)+SUMPRODUCT(C10^({2,3,4,5}-1)/(1+C14)^{2,3,4,5}))) -> 5306350.4 | D22: =(D13*D7*(D18/(1+D14)+SUMPRODUCT(D10^({2,3,4,5}-1)/(1+D14)^{2,3,4,5}))) -> 2398083.7 | E22: credited·real·[ramp/(1+r) + Σ₂₋₅ persist^(t−1)/(1+r)^t]
A23: PV of programme cost | B23: =((B16+B17)*B8+B15*B8*SUMPRODUCT(1/(1+B14)^{1,2,3,4,5})) -> 1520376.1 | C23: =((C16+C17)*C8+C15*C8*SUMPRODUCT(1/(1+C14)^{1,2,3,4,5})) -> 1368338.5 | D23: =((D16+D17)*D8+D15*D8*SUMPRODUCT(1/(1+D14)^{1,2,3,4,5})) -> 1976489 | E23: (setup + engineering)·mult + Σ run·mult / (1+r)^t
A24: NPV | B24: =(B13*B7*(B18/(1+B14)+SUMPRODUCT(B10^({2,3,4,5}-1)/(1+B14)^{2,3,4,5})))-((B16+B17)*B8+B15*B8*SUMPRODUCT(1/(1+B14)^{1,2,3,4,5})) -> 2833109.4 | C24: =(C13*C7*(C18/(1+C14)+SUMPRODUCT(C10^({2,3,4,5}-1)/(1+C14)^{2,3,4,5})))-((C16+C17)*C8+C15*C8*SUMPRODUCT(1/(1+C14)^{1,2,3,4,5})) -> 3938011.9 | D24: =(D13*D7*(D18/(1+D14)+SUMPRODUCT(D10^({2,3,4,5}-1)/(1+D14)^{2,3,4,5})))-((D16+D17)*D8+D15*D8*SUMPRODUCT(1/(1+D14)^{1,2,3,4,5})) -> 421594.69 | E24: PV savings − PV cost
A25: ROI (PV basis) | B25: =IF(((B16+B17)*B8+B15*B8*SUMPRODUCT(1/(1+B14)^{1,2,3,4,5}))=0,0,((B13*B7*(B18/(1+B14)+SUMPRODUCT(B10^({2,3,4,5}-1)/(1+B14)^{2,3,4,5})))-((B16+B17)*B8+B15*B8*SUMPRODUCT(1/(1+B14)^{1,2,3,4,5})))/((B16+B17)*B8+B15*B8*SUMPRODUCT(1/(1+B14)^{1,2,3,4,5}))) -> 1.8634267 | C25: =IF(((C16+C17)*C8+C15*C8*SUMPRODUCT(1/(1+C14)^{1,2,3,4,5}))=0,0,((C13*C7*(C18/(1+C14)+SUMPRODUCT(C10^({2,3,4,5}-1)/(1+C14)^{2,3,4,5})))-((C16+C17)*C8+C15*C8*SUMPRODUCT(1/(1+C14)^{1,2,3,4,5})))/((C16+C17)*C8+C15*C8*SUMPRODUCT(1/(1+C14)^{1,2,3,4,5}))) -> 2.8779515 | D25: =IF(((D16+D17)*D8+D15*D8*SUMPRODUCT(1/(1+D14)^{1,2,3,4,5}))=0,0,((D13*D7*(D18/(1+D14)+SUMPRODUCT(D10^({2,3,4,5}-1)/(1+D14)^{2,3,4,5})))-((D16+D17)*D8+D15*D8*SUMPRODUCT(1/(1+D14)^{1,2,3,4,5})))/((D16+D17)*D8+D15*D8*SUMPRODUCT(1/(1+D14)^{1,2,3,4,5}))) -> 0.21330485 | E25: (PV savings − PV cost) / PV cost
A26: Benefit-to-cost ratio | B26: =IF(((B16+B17)*B8+B15*B8*SUMPRODUCT(1/(1+B14)^{1,2,3,4,5}))=0,0,(B13*B7*(B18/(1+B14)+SUMPRODUCT(B10^({2,3,4,5}-1)/(1+B14)^{2,3,4,5})))/((B16+B17)*B8+B15*B8*SUMPRODUCT(1/(1+B14)^{1,2,3,4,5}))) -> 2.8634267 | C26: =IF(((C16+C17)*C8+C15*C8*SUMPRODUCT(1/(1+C14)^{1,2,3,4,5}))=0,0,(C13*C7*(C18/(1+C14)+SUMPRODUCT(C10^({2,3,4,5}-1)/(1+C14)^{2,3,4,5})))/((C16+C17)*C8+C15*C8*SUMPRODUCT(1/(1+C14)^{1,2,3,4,5}))) -> 3.8779515 | D26: =IF(((D16+D17)*D8+D15*D8*SUMPRODUCT(1/(1+D14)^{1,2,3,4,5}))=0,0,(D13*D7*(D18/(1+D14)+SUMPRODUCT(D10^({2,3,4,5}-1)/(1+D14)^{2,3,4,5})))/((D16+D17)*D8+D15*D8*SUMPRODUCT(1/(1+D14)^{1,2,3,4,5}))) -> 1.2133048 | E26: PV savings / PV cost
A27: Simple payback (months) | B27: =IF((B13*B7*B18-B15*B8)<=0,"beyond yr 1",12*(B16+B17)*B8/(B13*B7*B18-B15*B8)) -> 6.54707 | C27: =IF((C13*C7*C18-C15*C8)<=0,"beyond yr 1",12*(C16+C17)*C8/(C13*C7*C18-C15*C8)) -> 4.8743383 | D27: =IF((D13*D7*D18-D15*D8)<=0,"beyond yr 1",12*(D16+D17)*D8/(D13*D7*D18-D15*D8)) -> 18.886408 | E27: 12 × year-0 outlay / (year-1 savings − run cost), if within year 1
A29: Bear is not a stress test of the measurement -- the estimator's error is on the Savings Attribution sheet. Bear is a stress test of execution: what if a quarter of measured savings never reach production, hiring runs 30% over, and savings decay faster.

Sheet 09 Sensitivity Analysis
A1: Sensitivity analysis
A2: Five-year NPV as two inputs move together, everything else at the active scenario. Each cell is the full NPV formula, so the grid recalculates.
A3: SIMULATED DATA. The estate is synthetic (FOCUS 1.2, 400 resources, 540 days). Figures illustrate the method; ground truth exists only because the data is simulated.
A5: NPV: effect realisation (rows) × programme cost multiplier (columns)
A6: realisation ↓ / cost × → | B6: 0.8 | C6: 1 | D6: 1.2 | E6: 1.5 | F6: 2
A7: 0.5 | B7: =('04 Savings Attribution'!$D$133*$A7*('10 Assumptions'!$B$17/(1+'10 Assumptions'!$B$6)+SUMPRODUCT('10 Assumptions'!$B$39^({2,3,4,5}-1)/(1+'10 Assumptions'!$B$6)^{2,3,4,5})))-(('10 Assumptions'!$B$14+'04 Savings Attribution'!$D$127*'10 Assumptions'!$B$15*'10 Assumptions'!$B$16)*B$6+('10 Assumptions'!$B$11*'10 Assumptions'!$B$12+'10 Assumptions'!$B$13)*B$6*SUMPRODUCT(1/(1+'10 Assumptions'!$B$6)^{1,2,3,4,5})) -> 960441.87 | C7: =('04 Savings Attribution'!$D$133*$A7*('10 Assumptions'!$B$17/(1+'10 Assumptions'!$B$6)+SUMPRODUCT('10 Assumptions'!$B$39^({2,3,4,5}-1)/(1+'10 Assumptions'!$B$6)^{2,3,4,5})))-(('10 Assumptions'!$B$14+'04 Savings Attribution'!$D$127*'10 Assumptions'!$B$15*'10 Assumptions'!$B$16)*C$6+('10 Assumptions'!$B$11*'10 Assumptions'!$B$12+'10 Assumptions'!$B$13)*C$6*SUMPRODUCT(1/(1+'10 Assumptions'!$B$6)^{1,2,3,4,5})) -> 656366.64 | D7: =('04 Savings Attribution'!$D$133*$A7*('10 Assumptions'!$B$17/(1+'10 Assumptions'!$B$6)+SUMPRODUCT('10 Assumptions'!$B$39^({2,3,4,5}-1)/(1+'10 Assumptions'!$B$6)^{2,3,4,5})))-(('10 Assumptions'!$B$14+'04 Savings Attribution'!$D$127*'10 Assumptions'!$B$15*'10 Assumptions'!$B$16)*D$6+('10 Assumptions'!$B$11*'10 Assumptions'!$B$12+'10 Assumptions'!$B$13)*D$6*SUMPRODUCT(1/(1+'10 Assumptions'!$B$6)^{1,2,3,4,5})) -> 352291.41 | E7: =('04 Savings Attribution'!$D$133*$A7*('10 Assumptions'!$B$17/(1+'10 Assumptions'!$B$6)+SUMPRODUCT('10 Assumptions'!$B$39^({2,3,4,5}-1)/(1+'10 Assumptions'!$B$6)^{2,3,4,5})))-(('10 Assumptions'!$B$14+'04 Savings Attribution'!$D$127*'10 Assumptions'!$B$15*'10 Assumptions'!$B$16)*E$6+('10 Assumptions'!$B$11*'10 Assumptions'!$B$12+'10 Assumptions'!$B$13)*E$6*SUMPRODUCT(1/(1+'10 Assumptions'!$B$6)^{1,2,3,4,5})) -> -103821.43 | F7: =('04 Savings Attribution'!$D$133*$A7*('10 Assumptions'!$B$17/(1+'10 Assumptions'!$B$6)+SUMPRODUCT('10 Assumptions'!$B$39^({2,3,4,5}-1)/(1+'10 Assumptions'!$B$6)^{2,3,4,5})))-(('10 Assumptions'!$B$14+'04 Savings Attribution'!$D$127*'10 Assumptions'!$B$15*'10 Assumptions'!$B$16)*F$6+('10 Assumptions'!$B$11*'10 Assumptions'!$B$12+'10 Assumptions'!$B$13)*F$6*SUMPRODUCT(1/(1+'10 Assumptions'!$B$6)^{1,2,3,4,5})) -> -864009.51
A8: 0.625 | B8: =('04 Savings Attribution'!$D$133*$A8*('10 Assumptions'!$B$17/(1+'10 Assumptions'!$B$6)+SUMPRODUCT('10 Assumptions'!$B$39^({2,3,4,5}-1)/(1+'10 Assumptions'!$B$6)^{2,3,4,5})))-(('10 Assumptions'!$B$14+'04 Savings Attribution'!$D$127*'10 Assumptions'!$B$15*'10 Assumptions'!$B$16)*B$6+('10 Assumptions'!$B$11*'10 Assumptions'!$B$12+'10 Assumptions'!$B$13)*B$6*SUMPRODUCT(1/(1+'10 Assumptions'!$B$6)^{1,2,3,4,5})) -> 1504627.6 | C8: =('04 Savings Attribution'!$D$133*$A8*('10 Assumptions'!$B$17/(1+'10 Assumptions'!$B$6)+SUMPRODUCT('10 Assumptions'!$B$39^({2,3,4,5}-1)/(1+'10 Assumptions'!$B$6)^{2,3,4,5})))-(('10 Assumptions'!$B$14+'04 Savings Attribution'!$D$127*'10 Assumptions'!$B$15*'10 Assumptions'!$B$16)*C$6+('10 Assumptions'!$B$11*'10 Assumptions'!$B$12+'10 Assumptions'!$B$13)*C$6*SUMPRODUCT(1/(1+'10 Assumptions'!$B$6)^{1,2,3,4,5})) -> 1200552.3 | D8: =('04 Savings Attribution'!$D$133*$A8*('10 Assumptions'!$B$17/(1+'10 Assumptions'!$B$6)+SUMPRODUCT('10 Assumptions'!$B$39^({2,3,4,5}-1)/(1+'10 Assumptions'!$B$6)^{2,3,4,5})))-(('10 Assumptions'!$B$14+'04 Savings Attribution'!$D$127*'10 Assumptions'!$B$15*'10 Assumptions'!$B$16)*D$6+('10 Assumptions'!$B$11*'10 Assumptions'!$B$12+'10 Assumptions'!$B$13)*D$6*SUMPRODUCT(1/(1+'10 Assumptions'!$B$6)^{1,2,3,4,5})) -> 896477.11 | E8: =('04 Savings Attribution'!$D$133*$A8*('10 Assumptions'!$B$17/(1+'10 Assumptions'!$B$6)+SUMPRODUCT('10 Assumptions'!$B$39^({2,3,4,5}-1)/(1+'10 Assumptions'!$B$6)^{2,3,4,5})))-(('10 Assumptions'!$B$14+'04 Savings Attribution'!$D$127*'10 Assumptions'!$B$15*'10 Assumptions'!$B$16)*E$6+('10 Assumptions'!$B$11*'10 Assumptions'!$B$12+'10 Assumptions'!$B$13)*E$6*SUMPRODUCT(1/(1+'10 Assumptions'!$B$6)^{1,2,3,4,5})) -> 440364.27 | F8: =('04 Savings Attribution'!$D$133*$A8*('10 Assumptions'!$B$17/(1+'10 Assumptions'!$B$6)+SUMPRODUCT('10 Assumptions'!$B$39^({2,3,4,5}-1)/(1+'10 Assumptions'!$B$6)^{2,3,4,5})))-(('10 Assumptions'!$B$14+'04 Savings Attribution'!$D$127*'10 Assumptions'!$B$15*'10 Assumptions'!$B$16)*F$6+('10 Assumptions'!$B$11*'10 Assumptions'!$B$12+'10 Assumptions'!$B$13)*F$6*SUMPRODUCT(1/(1+'10 Assumptions'!$B$6)^{1,2,3,4,5})) -> -319823.81
A9: 0.75 | B9: =('04 Savings Attribution'!$D$133*$A9*('10 Assumptions'!$B$17/(1+'10 Assumptions'!$B$6)+SUMPRODUCT('10 Assumptions'!$B$39^({2,3,4,5}-1)/(1+'10 Assumptions'!$B$6)^{2,3,4,5})))-(('10 Assumptions'!$B$14+'04 Savings Attribution'!$D$127*'10 Assumptions'!$B$15*'10 Assumptions'!$B$16)*B$6+('10 Assumptions'!$B$11*'10 Assumptions'!$B$12+'10 Assumptions'!$B$13)*B$6*SUMPRODUCT(1/(1+'10 Assumptions'!$B$6)^{1,2,3,4,5})) -> 2048813.3 | C9: =('04 Savings Attribution'!$D$133*$A9*('10 Assumptions'!$B$17/(1+'10 Assumptions'!$B$6)+SUMPRODUCT('10 Assumptions'!$B$39^({2,3,4,5}-1)/(1+'10 Assumptions'!$B$6)^{2,3,4,5})))-(('10 Assumptions'!$B$14+'04 Savings Attribution'!$D$127*'10 Assumptions'!$B$15*'10 Assumptions'!$B$16)*C$6+('10 Assumptions'!$B$11*'10 Assumptions'!$B$12+'10 Assumptions'!$B$13)*C$6*SUMPRODUCT(1/(1+'10 Assumptions'!$B$6)^{1,2,3,4,5})) -> 1744738 | D9: =('04 Savings Attribution'!$D$133*$A9*('10 Assumptions'!$B$17/(1+'10 Assumptions'!$B$6)+SUMPRODUCT('10 Assumptions'!$B$39^({2,3,4,5}-1)/(1+'10 Assumptions'!$B$6)^{2,3,4,5})))-(('10 Assumptions'!$B$14+'04 Savings Attribution'!$D$127*'10 Assumptions'!$B$15*'10 Assumptions'!$B$16)*D$6+('10 Assumptions'!$B$11*'10 Assumptions'!$B$12+'10 Assumptions'!$B$13)*D$6*SUMPRODUCT(1/(1+'10 Assumptions'!$B$6)^{1,2,3,4,5})) -> 1440662.8 | E9: =('04 Savings Attribution'!$D$133*$A9*('10 Assumptions'!$B$17/(1+'10 Assumptions'!$B$6)+SUMPRODUCT('10 Assumptions'!$B$39^({2,3,4,5}-1)/(1+'10 Assumptions'!$B$6)^{2,3,4,5})))-(('10 Assumptions'!$B$14+'04 Savings Attribution'!$D$127*'10 Assumptions'!$B$15*'10 Assumptions'!$B$16)*E$6+('10 Assumptions'!$B$11*'10 Assumptions'!$B$12+'10 Assumptions'!$B$13)*E$6*SUMPRODUCT(1/(1+'10 Assumptions'!$B$6)^{1,2,3,4,5})) -> 984549.96 | F9: =('04 Savings Attribution'!$D$133*$A9*('10 Assumptions'!$B$17/(1+'10 Assumptions'!$B$6)+SUMPRODUCT('10 Assumptions'!$B$39^({2,3,4,5}-1)/(1+'10 Assumptions'!$B$6)^{2,3,4,5})))-(('10 Assumptions'!$B$14+'04 Savings Attribution'!$D$127*'10 Assumptions'!$B$15*'10 Assumptions'!$B$16)*F$6+('10 Assumptions'!$B$11*'10 Assumptions'!$B$12+'10 Assumptions'!$B$13)*F$6*SUMPRODUCT(1/(1+'10 Assumptions'!$B$6)^{1,2,3,4,5})) -> 224361.89
A10: 0.875 | B10: =('04 Savings Attribution'!$D$133*$A10*('10 Assumptions'!$B$17/(1+'10 Assumptions'!$B$6)+SUMPRODUCT('10 Assumptions'!$B$39^({2,3,4,5}-1)/(1+'10 Assumptions'!$B$6)^{2,3,4,5})))-(('10 Assumptions'!$B$14+'04 Savings Attribution'!$D$127*'10 Assumptions'!$B$15*'10 Assumptions'!$B$16)*B$6+('10 Assumptions'!$B$11*'10 Assumptions'!$B$12+'10 Assumptions'!$B$13)*B$6*SUMPRODUCT(1/(1+'10 Assumptions'!$B$6)^{1,2,3,4,5})) -> 2592999 | C10: =('04 Savings Attribution'!$D$133*$A10*('10 Assumptions'!$B$17/(1+'10 Assumptions'!$B$6)+SUMPRODUCT('10 Assumptions'!$B$39^({2,3,4,5}-1)/(1+'10 Assumptions'!$B$6)^{2,3,4,5})))-(('10 Assumptions'!$B$14+'04 Savings Attribution'!$D$127*'10 Assumptions'!$B$15*'10 Assumptions'!$B$16)*C$6+('10 Assumptions'!$B$11*'10 Assumptions'!$B$12+'10 Assumptions'!$B$13)*C$6*SUMPRODUCT(1/(1+'10 Assumptions'!$B$6)^{1,2,3,4,5})) -> 2288923.7 | D10: =('04 Savings Attribution'!$D$133*$A10*('10 Assumptions'!$B$17/(1+'10 Assumptions'!$B$6)+SUMPRODUCT('10 Assumptions'!$B$39^({2,3,4,5}-1)/(1+'10 Assumptions'!$B$6)^{2,3,4,5})))-(('10 Assumptions'!$B$14+'04 Savings Attribution'!$D$127*'10 Assumptions'!$B$15*'10 Assumptions'!$B$16)*D$6+('10 Assumptions'!$B$11*'10 Assumptions'!$B$12+'10 Assumptions'!$B$13)*D$6*SUMPRODUCT(1/(1+'10 Assumptions'!$B$6)^{1,2,3,4,5})) -> 1984848.5 | E10: =('04 Savings Attribution'!$D$133*$A10*('10 Assumptions'!$B$17/(1+'10 Assumptions'!$B$6)+SUMPRODUCT('10 Assumptions'!$B$39^({2,3,4,5}-1)/(1+'10 Assumptions'!$B$6)^{2,3,4,5})))-(('10 Assumptions'!$B$14+'04 Savings Attribution'!$D$127*'10 Assumptions'!$B$15*'10 Assumptions'!$B$16)*E$6+('10 Assumptions'!$B$11*'10 Assumptions'!$B$12+'10 Assumptions'!$B$13)*E$6*SUMPRODUCT(1/(1+'10 Assumptions'!$B$6)^{1,2,3,4,5})) -> 1528735.7 | F10: =('04 Savings Attribution'!$D$133*$A10*('10 Assumptions'!$B$17/(1+'10 Assumptions'!$B$6)+SUMPRODUCT('10 Assumptions'!$B$39^({2,3,4,5}-1)/(1+'10 Assumptions'!$B$6)^{2,3,4,5})))-(('10 Assumptions'!$B$14+'04 Savings Attribution'!$D$127*'10 Assumptions'!$B$15*'10 Assumptions'!$B$16)*F$6+('10 Assumptions'!$B$11*'10 Assumptions'!$B$12+'10 Assumptions'!$B$13)*F$6*SUMPRODUCT(1/(1+'10 Assumptions'!$B$6)^{1,2,3,4,5})) -> 768547.59
A11: 1 | B11: =('04 Savings Attribution'!$D$133*$A11*('10 Assumptions'!$B$17/(1+'10 Assumptions'!$B$6)+SUMPRODUCT('10 Assumptions'!$B$39^({2,3,4,5}-1)/(1+'10 Assumptions'!$B$6)^{2,3,4,5})))-(('10 Assumptions'!$B$14+'04 Savings Attribution'!$D$127*'10 Assumptions'!$B$15*'10 Assumptions'!$B$16)*B$6+('10 Assumptions'!$B$11*'10 Assumptions'!$B$12+'10 Assumptions'!$B$13)*B$6*SUMPRODUCT(1/(1+'10 Assumptions'!$B$6)^{1,2,3,4,5})) -> 3137184.7 | C11: =('04 Savings Attribution'!$D$133*$A11*('10 Assumptions'!$B$17/(1+'10 Assumptions'!$B$6)+SUMPRODUCT('10 Assumptions'!$B$39^({2,3,4,5}-1)/(1+'10 Assumptions'!$B$6)^{2,3,4,5})))-(('10 Assumptions'!$B$14+'04 Savings Attribution'!$D$127*'10 Assumptions'!$B$15*'10 Assumptions'!$B$16)*C$6+('10 Assumptions'!$B$11*'10 Assumptions'!$B$12+'10 Assumptions'!$B$13)*C$6*SUMPRODUCT(1/(1+'10 Assumptions'!$B$6)^{1,2,3,4,5})) -> 2833109.4 | D11: =('04 Savings Attribution'!$D$133*$A11*('10 Assumptions'!$B$17/(1+'10 Assumptions'!$B$6)+SUMPRODUCT('10 Assumptions'!$B$39^({2,3,4,5}-1)/(1+'10 Assumptions'!$B$6)^{2,3,4,5})))-(('10 Assumptions'!$B$14+'04 Savings Attribution'!$D$127*'10 Assumptions'!$B$15*'10 Assumptions'!$B$16)*D$6+('10 Assumptions'!$B$11*'10 Assumptions'!$B$12+'10 Assumptions'!$B$13)*D$6*SUMPRODUCT(1/(1+'10 Assumptions'!$B$6)^{1,2,3,4,5})) -> 2529034.2 | E11: =('04 Savings Attribution'!$D$133*$A11*('10 Assumptions'!$B$17/(1+'10 Assumptions'!$B$6)+SUMPRODUCT('10 Assumptions'!$B$39^({2,3,4,5}-1)/(1+'10 Assumptions'!$B$6)^{2,3,4,5})))-(('10 Assumptions'!$B$14+'04 Savings Attribution'!$D$127*'10 Assumptions'!$B$15*'10 Assumptions'!$B$16)*E$6+('10 Assumptions'!$B$11*'10 Assumptions'!$B$12+'10 Assumptions'!$B$13)*E$6*SUMPRODUCT(1/(1+'10 Assumptions'!$B$6)^{1,2,3,4,5})) -> 2072921.4 | F11: =('04 Savings Attribution'!$D$133*$A11*('10 Assumptions'!$B$17/(1+'10 Assumptions'!$B$6)+SUMPRODUCT('10 Assumptions'!$B$39^({2,3,4,5}-1)/(1+'10 Assumptions'!$B$6)^{2,3,4,5})))-(('10 Assumptions'!$B$14+'04 Savings Attribution'!$D$127*'10 Assumptions'!$B$15*'10 Assumptions'!$B$16)*F$6+('10 Assumptions'!$B$11*'10 Assumptions'!$B$12+'10 Assumptions'!$B$13)*F$6*SUMPRODUCT(1/(1+'10 Assumptions'!$B$6)^{1,2,3,4,5})) -> 1312733.3
A12: 1.125 | B12: =('04 Savings Attribution'!$D$133*$A12*('10 Assumptions'!$B$17/(1+'10 Assumptions'!$B$6)+SUMPRODUCT('10 Assumptions'!$B$39^({2,3,4,5}-1)/(1+'10 Assumptions'!$B$6)^{2,3,4,5})))-(('10 Assumptions'!$B$14+'04 Savings Attribution'!$D$127*'10 Assumptions'!$B$15*'10 Assumptions'!$B$16)*B$6+('10 Assumptions'!$B$11*'10 Assumptions'!$B$12+'10 Assumptions'!$B$13)*B$6*SUMPRODUCT(1/(1+'10 Assumptions'!$B$6)^{1,2,3,4,5})) -> 3681370.4 | C12: =('04 Savings Attribution'!$D$133*$A12*('10 Assumptions'!$B$17/(1+'10 Assumptions'!$B$6)+SUMPRODUCT('10 Assumptions'!$B$39^({2,3,4,5}-1)/(1+'10 Assumptions'!$B$6)^{2,3,4,5})))-(('10 Assumptions'!$B$14+'04 Savings Attribution'!$D$127*'10 Assumptions'!$B$15*'10 Assumptions'!$B$16)*C$6+('10 Assumptions'!$B$11*'10 Assumptions'!$B$12+'10 Assumptions'!$B$13)*C$6*SUMPRODUCT(1/(1+'10 Assumptions'!$B$6)^{1,2,3,4,5})) -> 3377295.1 | D12: =('04 Savings Attribution'!$D$133*$A12*('10 Assumptions'!$B$17/(1+'10 Assumptions'!$B$6)+SUMPRODUCT('10 Assumptions'!$B$39^({2,3,4,5}-1)/(1+'10 Assumptions'!$B$6)^{2,3,4,5})))-(('10 Assumptions'!$B$14+'04 Savings Attribution'!$D$127*'10 Assumptions'!$B$15*'10 Assumptions'!$B$16)*D$6+('10 Assumptions'!$B$11*'10 Assumptions'!$B$12+'10 Assumptions'!$B$13)*D$6*SUMPRODUCT(1/(1+'10 Assumptions'!$B$6)^{1,2,3,4,5})) -> 3073219.9 | E12: =('04 Savings Attribution'!$D$133*$A12*('10 Assumptions'!$B$17/(1+'10 Assumptions'!$B$6)+SUMPRODUCT('10 Assumptions'!$B$39^({2,3,4,5}-1)/(1+'10 Assumptions'!$B$6)^{2,3,4,5})))-(('10 Assumptions'!$B$14+'04 Savings Attribution'!$D$127*'10 Assumptions'!$B$15*'10 Assumptions'!$B$16)*E$6+('10 Assumptions'!$B$11*'10 Assumptions'!$B$12+'10 Assumptions'!$B$13)*E$6*SUMPRODUCT(1/(1+'10 Assumptions'!$B$6)^{1,2,3,4,5})) -> 2617107.1 | F12: =('04 Savings Attribution'!$D$133*$A12*('10 Assumptions'!$B$17/(1+'10 Assumptions'!$B$6)+SUMPRODUCT('10 Assumptions'!$B$39^({2,3,4,5}-1)/(1+'10 Assumptions'!$B$6)^{2,3,4,5})))-(('10 Assumptions'!$B$14+'04 Savings Attribution'!$D$127*'10 Assumptions'!$B$15*'10 Assumptions'!$B$16)*F$6+('10 Assumptions'!$B$11*'10 Assumptions'!$B$12+'10 Assumptions'!$B$13)*F$6*SUMPRODUCT(1/(1+'10 Assumptions'!$B$6)^{1,2,3,4,5})) -> 1856919
A13: 1.25 | B13: =('04 Savings Attribution'!$D$133*$A13*('10 Assumptions'!$B$17/(1+'10 Assumptions'!$B$6)+SUMPRODUCT('10 Assumptions'!$B$39^({2,3,4,5}-1)/(1+'10 Assumptions'!$B$6)^{2,3,4,5})))-(('10 Assumptions'!$B$14+'04 Savings Attribution'!$D$127*'10 Assumptions'!$B$15*'10 Assumptions'!$B$16)*B$6+('10 Assumptions'!$B$11*'10 Assumptions'!$B$12+'10 Assumptions'!$B$13)*B$6*SUMPRODUCT(1/(1+'10 Assumptions'!$B$6)^{1,2,3,4,5})) -> 4225556.1 | C13: =('04 Savings Attribution'!$D$133*$A13*('10 Assumptions'!$B$17/(1+'10 Assumptions'!$B$6)+SUMPRODUCT('10 Assumptions'!$B$39^({2,3,4,5}-1)/(1+'10 Assumptions'!$B$6)^{2,3,4,5})))-(('10 Assumptions'!$B$14+'04 Savings Attribution'!$D$127*'10 Assumptions'!$B$15*'10 Assumptions'!$B$16)*C$6+('10 Assumptions'!$B$11*'10 Assumptions'!$B$12+'10 Assumptions'!$B$13)*C$6*SUMPRODUCT(1/(1+'10 Assumptions'!$B$6)^{1,2,3,4,5})) -> 3921480.8 | D13: =('04 Savings Attribution'!$D$133*$A13*('10 Assumptions'!$B$17/(1+'10 Assumptions'!$B$6)+SUMPRODUCT('10 Assumptions'!$B$39^({2,3,4,5}-1)/(1+'10 Assumptions'!$B$6)^{2,3,4,5})))-(('10 Assumptions'!$B$14+'04 Savings Attribution'!$D$127*'10 Assumptions'!$B$15*'10 Assumptions'!$B$16)*D$6+('10 Assumptions'!$B$11*'10 Assumptions'!$B$12+'10 Assumptions'!$B$13)*D$6*SUMPRODUCT(1/(1+'10 Assumptions'!$B$6)^{1,2,3,4,5})) -> 3617405.6 | E13: =('04 Savings Attribution'!$D$133*$A13*('10 Assumptions'!$B$17/(1+'10 Assumptions'!$B$6)+SUMPRODUCT('10 Assumptions'!$B$39^({2,3,4,5}-1)/(1+'10 Assumptions'!$B$6)^{2,3,4,5})))-(('10 Assumptions'!$B$14+'04 Savings Attribution'!$D$127*'10 Assumptions'!$B$15*'10 Assumptions'!$B$16)*E$6+('10 Assumptions'!$B$11*'10 Assumptions'!$B$12+'10 Assumptions'!$B$13)*E$6*SUMPRODUCT(1/(1+'10 Assumptions'!$B$6)^{1,2,3,4,5})) -> 3161292.8 | F13: =('04 Savings Attribution'!$D$133*$A13*('10 Assumptions'!$B$17/(1+'10 Assumptions'!$B$6)+SUMPRODUCT('10 Assumptions'!$B$39^({2,3,4,5}-1)/(1+'10 Assumptions'!$B$6)^{2,3,4,5})))-(('10 Assumptions'!$B$14+'04 Savings Attribution'!$D$127*'10 Assumptions'!$B$15*'10 Assumptions'!$B$16)*F$6+('10 Assumptions'!$B$11*'10 Assumptions'!$B$12+'10 Assumptions'!$B$13)*F$6*SUMPRODUCT(1/(1+'10 Assumptions'!$B$6)^{1,2,3,4,5})) -> 2401104.7
A15: NPV: discount rate (rows) × savings persistence (columns)
A16: rate ↓ / persistence → | B16: 0.6 | C16: 0.7 | D16: 0.8 | E16: 0.85 | F16: 0.9 | G16: 1
A17: 0.08 | B17: =('04 Savings Attribution'!$D$133*'10 Assumptions'!$B$36*('10 Assumptions'!$B$17/(1+$A17)+SUMPRODUCT(B$16^({2,3,4,5}-1)/(1+$A17)^{2,3,4,5})))-(('10 Assumptions'!$B$14+'04 Savings Attribution'!$D$127*'10 Assumptions'!$B$15*'10 Assumptions'!$B$16)*'10 Assumptions'!$B$37+('10 Assumptions'!$B$11*'10 Assumptions'!$B$12+'10 Assumptions'!$B$13)*'10 Assumptions'!$B$37*SUMPRODUCT(1/(1+$A17)^{1,2,3,4,5})) -> 1179500.1 | C17: =('04 Savings Attribution'!$D$133*'10 Assumptions'!$B$36*('10 Assumptions'!$B$17/(1+$A17)+SUMPRODUCT(C$16^({2,3,4,5}-1)/(1+$A17)^{2,3,4,5})))-(('10 Assumptions'!$B$14+'04 Savings Attribution'!$D$127*'10 Assumptions'!$B$15*'10 Assumptions'!$B$16)*'10 Assumptions'!$B$37+('10 Assumptions'!$B$11*'10 Assumptions'!$B$12+'10 Assumptions'!$B$13)*'10 Assumptions'!$B$37*SUMPRODUCT(1/(1+$A17)^{1,2,3,4,5})) -> 1848939.3 | D17: =('04 Savings Attribution'!$D$133*'10 Assumptions'!$B$36*('10 Assumptions'!$B$17/(1+$A17)+SUMPRODUCT(D$16^({2,3,4,5}-1)/(1+$A17)^{2,3,4,5})))-(('10 Assumptions'!$B$14+'04 Savings Attribution'!$D$127*'10 Assumptions'!$B$15*'10 Assumptions'!$B$16)*'10 Assumptions'!$B$37+('10 Assumptions'!$B$11*'10 Assumptions'!$B$12+'10 Assumptions'!$B$13)*'10 Assumptions'!$B$37*SUMPRODUCT(1/(1+$A17)^{1,2,3,4,5})) -> 2681114.6 | E17: =('04 Savings Attribution'!$D$133*'10 Assumptions'!$B$36*('10 Assumptions'!$B$17/(1+$A17)+SUMPRODUCT(E$16^({2,3,4,5}-1)/(1+$A17)^{2,3,4,5})))-(('10 Assumptions'!$B$14+'04 Savings Attribution'!$D$127*'10 Assumptions'!$B$15*'10 Assumptions'!$B$16)*'10 Assumptions'!$B$37+('10 Assumptions'!$B$11*'10 Assumptions'!$B$12+'10 Assumptions'!$B$13)*'10 Assumptions'!$B$37*SUMPRODUCT(1/(1+$A17)^{1,2,3,4,5})) -> 3167858.7 | F17: =('04 Savings Attribution'!$D$133*'10 Assumptions'!$B$36*('10 Assumptions'!$B$17/(1+$A17)+SUMPRODUCT(F$16^({2,3,4,5}-1)/(1+$A17)^{2,3,4,5})))-(('10 Assumptions'!$B$14+'04 Savings Attribution'!$D$127*'10 Assumptions'!$B$15*'10 Assumptions'!$B$16)*'10 Assumptions'!$B$37+('10 Assumptions'!$B$11*'10 Assumptions'!$B$12+'10 Assumptions'!$B$13)*'10 Assumptions'!$B$37*SUMPRODUCT(1/(1+$A17)^{1,2,3,4,5})) -> 3707225.6 | G17: =('04 Savings Attribution'!$D$133*'10 Assumptions'!$B$36*('10 Assumptions'!$B$17/(1+$A17)+SUMPRODUCT(G$16^({2,3,4,5}-1)/(1+$A17)^{2,3,4,5})))-(('10 Assumptions'!$B$14+'04 Savings Attribution'!$D$127*'10 Assumptions'!$B$15*'10 Assumptions'!$B$16)*'10 Assumptions'!$B$37+('10 Assumptions'!$B$11*'10 Assumptions'!$B$12+'10 Assumptions'!$B$13)*'10 Assumptions'!$B$37*SUMPRODUCT(1/(1+$A17)^{1,2,3,4,5})) -> 4961530.2
A18: 0.1 | B18: =('04 Savings Attribution'!$D$133*'10 Assumptions'!$B$36*('10 Assumptions'!$B$17/(1+$A18)+SUMPRODUCT(B$16^({2,3,4,5}-1)/(1+$A18)^{2,3,4,5})))-(('10 Assumptions'!$B$14+'04 Savings Attribution'!$D$127*'10 Assumptions'!$B$15*'10 Assumptions'!$B$16)*'10 Assumptions'!$B$37+('10 Assumptions'!$B$11*'10 Assumptions'!$B$12+'10 Assumptions'!$B$13)*'10 Assumptions'!$B$37*SUMPRODUCT(1/(1+$A18)^{1,2,3,4,5})) -> 1131479 | C18: =('04 Savings Attribution'!$D$133*'10 Assumptions'!$B$36*('10 Assumptions'!$B$17/(1+$A18)+SUMPRODUCT(C$16^({2,3,4,5}-1)/(1+$A18)^{2,3,4,5})))-(('10 Assumptions'!$B$14+'04 Savings Attribution'!$D$127*'10 Assumptions'!$B$15*'10 Assumptions'!$B$16)*'10 Assumptions'!$B$37+('10 Assumptions'!$B$11*'10 Assumptions'!$B$12+'10 Assumptions'!$B$13)*'10 Assumptions'!$B$37*SUMPRODUCT(1/(1+$A18)^{1,2,3,4,5})) -> 1760066.2 | D18: =('04 Savings Attribution'!$D$133*'10 Assumptions'!$B$36*('10 Assumptions'!$B$17/(1+$A18)+SUMPRODUCT(D$16^({2,3,4,5}-1)/(1+$A18)^{2,3,4,5})))-(('10 Assumptions'!$B$14+'04 Savings Attribution'!$D$127*'10 Assumptions'!$B$15*'10 Assumptions'!$B$16)*'10 Assumptions'!$B$37+('10 Assumptions'!$B$11*'10 Assumptions'!$B$12+'10 Assumptions'!$B$13)*'10 Assumptions'!$B$37*SUMPRODUCT(1/(1+$A18)^{1,2,3,4,5})) -> 2539114.3 | E18: =('04 Savings Attribution'!$D$133*'10 Assumptions'!$B$36*('10 Assumptions'!$B$17/(1+$A18)+SUMPRODUCT(E$16^({2,3,4,5}-1)/(1+$A18)^{2,3,4,5})))-(('10 Assumptions'!$B$14+'04 Savings Attribution'!$D$127*'10 Assumptions'!$B$15*'10 Assumptions'!$B$16)*'10 Assumptions'!$B$37+('10 Assumptions'!$B$11*'10 Assumptions'!$B$12+'10 Assumptions'!$B$13)*'10 Assumptions'!$B$37*SUMPRODUCT(1/(1+$A18)^{1,2,3,4,5})) -> 2993890.9 | F18: =('04 Savings Attribution'!$D$133*'10 Assumptions'!$B$36*('10 Assumptions'!$B$17/(1+$A18)+SUMPRODUCT(F$16^({2,3,4,5}-1)/(1+$A18)^{2,3,4,5})))-(('10 Assumptions'!$B$14+'04 Savings Attribution'!$D$127*'10 Assumptions'!$B$15*'10 Assumptions'!$B$16)*'10 Assumptions'!$B$37+('10 Assumptions'!$B$11*'10 Assumptions'!$B$12+'10 Assumptions'!$B$13)*'10 Assumptions'!$B$37*SUMPRODUCT(1/(1+$A18)^{1,2,3,4,5})) -> 3497227.2 | G18: =('04 Savings Attribution'!$D$133*'10 Assumptions'!$B$36*('10 Assumptions'!$B$17/(1+$A18)+SUMPRODUCT(G$16^({2,3,4,5}-1)/(1+$A18)^{2,3,4,5})))-(('10 Assumptions'!$B$14+'04 Savings Attribution'!$D$127*'10 Assumptions'!$B$15*'10 Assumptions'!$B$16)*'10 Assumptions'!$B$37+('10 Assumptions'!$B$11*'10 Assumptions'!$B$12+'10 Assumptions'!$B$13)*'10 Assumptions'!$B$37*SUMPRODUCT(1/(1+$A18)^{1,2,3,4,5})) -> 4665799.4
A19: 0.12 | B19: =('04 Savings Attribution'!$D$133*'10 Assumptions'!$B$36*('10 Assumptions'!$B$17/(1+$A19)+SUMPRODUCT(B$16^({2,3,4,5}-1)/(1+$A19)^{2,3,4,5})))-(('10 Assumptions'!$B$14+'04 Savings Attribution'!$D$127*'10 Assumptions'!$B$15*'10 Assumptions'!$B$16)*'10 Assumptions'!$B$37+('10 Assumptions'!$B$11*'10 Assumptions'!$B$12+'10 Assumptions'!$B$13)*'10 Assumptions'!$B$37*SUMPRODUCT(1/(1+$A19)^{1,2,3,4,5})) -> 1085948.8 | C19: =('04 Savings Attribution'!$D$133*'10 Assumptions'!$B$36*('10 Assumptions'!$B$17/(1+$A19)+SUMPRODUCT(C$16^({2,3,4,5}-1)/(1+$A19)^{2,3,4,5})))-(('10 Assumptions'!$B$14+'04 Savings Attribution'!$D$127*'10 Assumptions'!$B$15*'10 Assumptions'!$B$16)*'10 Assumptions'!$B$37+('10 Assumptions'!$B$11*'10 Assumptions'!$B$12+'10 Assumptions'!$B$13)*'10 Assumptions'!$B$37*SUMPRODUCT(1/(1+$A19)^{1,2,3,4,5})) -> 1677068.8 | D19: =('04 Savings Attribution'!$D$133*'10 Assumptions'!$B$36*('10 Assumptions'!$B$17/(1+$A19)+SUMPRODUCT(D$16^({2,3,4,5}-1)/(1+$A19)^{2,3,4,5})))-(('10 Assumptions'!$B$14+'04 Savings Attribution'!$D$127*'10 Assumptions'!$B$15*'10 Assumptions'!$B$16)*'10 Assumptions'!$B$37+('10 Assumptions'!$B$11*'10 Assumptions'!$B$12+'10 Assumptions'!$B$13)*'10 Assumptions'!$B$37*SUMPRODUCT(1/(1+$A19)^{1,2,3,4,5})) -> 2407523.1 | E19: =('04 Savings Attribution'!$D$133*'10 Assumptions'!$B$36*('10 Assumptions'!$B$17/(1+$A19)+SUMPRODUCT(E$16^({2,3,4,5}-1)/(1+$A19)^{2,3,4,5})))-(('10 Assumptions'!$B$14+'04 Savings Attribution'!$D$127*'10 Assumptions'!$B$15*'10 Assumptions'!$B$16)*'10 Assumptions'!$B$37+('10 Assumptions'!$B$11*'10 Assumptions'!$B$12+'10 Assumptions'!$B$13)*'10 Assumptions'!$B$37*SUMPRODUCT(1/(1+$A19)^{1,2,3,4,5})) -> 2833109.4 | F19: =('04 Savings Attribution'!$D$133*'10 Assumptions'!$B$36*('10 Assumptions'!$B$17/(1+$A19)+SUMPRODUCT(F$16^({2,3,4,5}-1)/(1+$A19)^{2,3,4,5})))-(('10 Assumptions'!$B$14+'04 Savings Attribution'!$D$127*'10 Assumptions'!$B$15*'10 Assumptions'!$B$16)*'10 Assumptions'!$B$37+('10 Assumptions'!$B$11*'10 Assumptions'!$B$12+'10 Assumptions'!$B$13)*'10 Assumptions'!$B$37*SUMPRODUCT(1/(1+$A19)^{1,2,3,4,5})) -> 3303578.8 | G19: =('04 Savings Attribution'!$D$133*'10 Assumptions'!$B$36*('10 Assumptions'!$B$17/(1+$A19)+SUMPRODUCT(G$16^({2,3,4,5}-1)/(1+$A19)^{2,3,4,5})))-(('10 Assumptions'!$B$14+'04 Savings Attribution'!$D$127*'10 Assumptions'!$B$15*'10 Assumptions'!$B$16)*'10 Assumptions'!$B$37+('10 Assumptions'!$B$11*'10 Assumptions'!$B$12+'10 Assumptions'!$B$13)*'10 Assumptions'!$B$37*SUMPRODUCT(1/(1+$A19)^{1,2,3,4,5})) -> 4394053.1
A20: 0.15 | B20: =('04 Savings Attribution'!$D$133*'10 Assumptions'!$B$36*('10 Assumptions'!$B$17/(1+$A20)+SUMPRODUCT(B$16^({2,3,4,5}-1)/(1+$A20)^{2,3,4,5})))-(('10 Assumptions'!$B$14+'04 Savings Attribution'!$D$127*'10 Assumptions'!$B$15*'10 Assumptions'!$B$16)*'10 Assumptions'!$B$37+('10 Assumptions'!$B$11*'10 Assumptions'!$B$12+'10 Assumptions'!$B$13)*'10 Assumptions'!$B$37*SUMPRODUCT(1/(1+$A20)^{1,2,3,4,5})) -> 1021958.5 | C20: =('04 Savings Attribution'!$D$133*'10 Assumptions'!$B$36*('10 Assumptions'!$B$17/(1+$A20)+SUMPRODUCT(C$16^({2,3,4,5}-1)/(1+$A20)^{2,3,4,5})))-(('10 Assumptions'!$B$14+'04 Savings Attribution'!$D$127*'10 Assumptions'!$B$15*'10 Assumptions'!$B$16)*'10 Assumptions'!$B$37+('10 Assumptions'!$B$11*'10 Assumptions'!$B$12+'10 Assumptions'!$B$13)*'10 Assumptions'!$B$37*SUMPRODUCT(1/(1+$A20)^{1,2,3,4,5})) -> 1562479.7 | D20: =('04 Savings Attribution'!$D$133*'10 Assumptions'!$B$36*('10 Assumptions'!$B$17/(1+$A20)+SUMPRODUCT(D$16^({2,3,4,5}-1)/(1+$A20)^{2,3,4,5})))-(('10 Assumptions'!$B$14+'04 Savings Attribution'!$D$127*'10 Assumptions'!$B$15*'10 Assumptions'!$B$16)*'10 Assumptions'!$B$37+('10 Assumptions'!$B$11*'10 Assumptions'!$B$12+'10 Assumptions'!$B$13)*'10 Assumptions'!$B$37*SUMPRODUCT(1/(1+$A20)^{1,2,3,4,5})) -> 2227526.1 | E20: =('04 Savings Attribution'!$D$133*'10 Assumptions'!$B$36*('10 Assumptions'!$B$17/(1+$A20)+SUMPRODUCT(E$16^({2,3,4,5}-1)/(1+$A20)^{2,3,4,5})))-(('10 Assumptions'!$B$14+'04 Savings Attribution'!$D$127*'10 Assumptions'!$B$15*'10 Assumptions'!$B$16)*'10 Assumptions'!$B$37+('10 Assumptions'!$B$11*'10 Assumptions'!$B$12+'10 Assumptions'!$B$13)*'10 Assumptions'!$B$37*SUMPRODUCT(1/(1+$A20)^{1,2,3,4,5})) -> 2613903.6 | F20: =('04 Savings Attribution'!$D$133*'10 Assumptions'!$B$36*('10 Assumptions'!$B$17/(1+$A20)+SUMPRODUCT(F$16^({2,3,4,5}-1)/(1+$A20)^{2,3,4,5})))-(('10 Assumptions'!$B$14+'04 Savings Attribution'!$D$127*'10 Assumptions'!$B$15*'10 Assumptions'!$B$16)*'10 Assumptions'!$B$37+('10 Assumptions'!$B$11*'10 Assumptions'!$B$12+'10 Assumptions'!$B$13)*'10 Assumptions'!$B$37*SUMPRODUCT(1/(1+$A20)^{1,2,3,4,5})) -> 3040280.5 | G20: =('04 Savings Attribution'!$D$133*'10 Assumptions'!$B$36*('10 Assumptions'!$B$17/(1+$A20)+SUMPRODUCT(G$16^({2,3,4,5}-1)/(1+$A20)^{2,3,4,5})))-(('10 Assumptions'!$B$14+'04 Savings Attribution'!$D$127*'10 Assumptions'!$B$15*'10 Assumptions'!$B$16)*'10 Assumptions'!$B$37+('10 Assumptions'!$B$11*'10 Assumptions'!$B$12+'10 Assumptions'!$B$13)*'10 Assumptions'!$B$37*SUMPRODUCT(1/(1+$A20)^{1,2,3,4,5})) -> 4026159.9
A21: 0.2 | B21: =('04 Savings Attribution'!$D$133*'10 Assumptions'!$B$36*('10 Assumptions'!$B$17/(1+$A21)+SUMPRODUCT(B$16^({2,3,4,5}-1)/(1+$A21)^{2,3,4,5})))-(('10 Assumptions'!$B$14+'04 Savings Attribution'!$D$127*'10 Assumptions'!$B$15*'10 Assumptions'!$B$16)*'10 Assumptions'!$B$37+('10 Assumptions'!$B$11*'10 Assumptions'!$B$12+'10 Assumptions'!$B$13)*'10 Assumptions'!$B$37*SUMPRODUCT(1/(1+$A21)^{1,2,3,4,5})) -> 925557.52 | C21: =('04 Savings Attribution'!$D$133*'10 Assumptions'!$B$36*('10 Assumptions'!$B$17/(1+$A21)+SUMPRODUCT(C$16^({2,3,4,5}-1)/(1+$A21)^{2,3,4,5})))-(('10 Assumptions'!$B$14+'04 Savings Attribution'!$D$127*'10 Assumptions'!$B$15*'10 Assumptions'!$B$16)*'10 Assumptions'!$B$37+('10 Assumptions'!$B$11*'10 Assumptions'!$B$12+'10 Assumptions'!$B$13)*'10 Assumptions'!$B$37*SUMPRODUCT(1/(1+$A21)^{1,2,3,4,5})) -> 1394333.1 | D21: =('04 Savings Attribution'!$D$133*'10 Assumptions'!$B$36*('10 Assumptions'!$B$17/(1+$A21)+SUMPRODUCT(D$16^({2,3,4,5}-1)/(1+$A21)^{2,3,4,5})))-(('10 Assumptions'!$B$14+'04 Savings Attribution'!$D$127*'10 Assumptions'!$B$15*'10 Assumptions'!$B$16)*'10 Assumptions'!$B$37+('10 Assumptions'!$B$11*'10 Assumptions'!$B$12+'10 Assumptions'!$B$13)*'10 Assumptions'!$B$37*SUMPRODUCT(1/(1+$A21)^{1,2,3,4,5})) -> 1967113.9 | E21: =('04 Savings Attribution'!$D$133*'10 Assumptions'!$B$36*('10 Assumptions'!$B$17/(1+$A21)+SUMPRODUCT(E$16^({2,3,4,5}-1)/(1+$A21)^{2,3,4,5})))-(('10 Assumptions'!$B$14+'04 Savings Attribution'!$D$127*'10 Assumptions'!$B$15*'10 Assumptions'!$B$16)*'10 Assumptions'!$B$37+('10 Assumptions'!$B$11*'10 Assumptions'!$B$12+'10 Assumptions'!$B$13)*'10 Assumptions'!$B$37*SUMPRODUCT(1/(1+$A21)^{1,2,3,4,5})) -> 2298362.1 | F21: =('04 Savings Attribution'!$D$133*'10 Assumptions'!$B$36*('10 Assumptions'!$B$17/(1+$A21)+SUMPRODUCT(F$16^({2,3,4,5}-1)/(1+$A21)^{2,3,4,5})))-(('10 Assumptions'!$B$14+'04 Savings Attribution'!$D$127*'10 Assumptions'!$B$15*'10 Assumptions'!$B$16)*'10 Assumptions'!$B$37+('10 Assumptions'!$B$11*'10 Assumptions'!$B$12+'10 Assumptions'!$B$13)*'10 Assumptions'!$B$37*SUMPRODUCT(1/(1+$A21)^{1,2,3,4,5})) -> 2662864.5 | G21: =('04 Savings Attribution'!$D$133*'10 Assumptions'!$B$36*('10 Assumptions'!$B$17/(1+$A21)+SUMPRODUCT(G$16^({2,3,4,5}-1)/(1+$A21)^{2,3,4,5})))-(('10 Assumptions'!$B$14+'04 Savings Attribution'!$D$127*'10 Assumptions'!$B$15*'10 Assumptions'!$B$16)*'10 Assumptions'!$B$37+('10 Assumptions'!$B$11*'10 Assumptions'!$B$12+'10 Assumptions'!$B$13)*'10 Assumptions'!$B$37*SUMPRODUCT(1/(1+$A21)^{1,2,3,4,5})) -> 3502355.9
A23: Check: grid 1 at (100%, 1.00x) − ROI NPV, Base scenario | B23: =C11-'07 ROI Analysis'!$B$26 -> 0

Sheet 10 Assumptions
A1: Assumptions
A2: Blue cells are inputs. Everything else in the workbook is a formula that reads them. Change one here and every sheet moves.
A5: Financial
A6: Discount rate (cost of capital) | B6: 0.12 | E6: Applied to programme cash flows. Sensitivity sheet varies it 8%–20%.
A7: Analysis horizon (years) | B7: 5 | E7: Fixed at 5 in the ROI layout.
A8: Savings persistence, year over year | B8: 0.85 | E8: Share of an attributed saving still realised the following year. Optimisations erode: resources get re-provisioned, autoscaling floors drift up.
A10: Programme cost
A11: FinOps engineers (FTE) | B11: 1.5 | E11: Who runs the measurement and remediation.
A12: Loaded annual cost per FTE | B12: 180000 | E12: Salary, benefits, overhead. Change to your organisation's rate.
A13: Tooling and platform, per year | B13: 60000 | E13: Billing export, warehouse, watsonx.ai inference, workstation.
A14: One-time setup (year 0) | B14: 50000 | E14: FOCUS export wiring, warehouse build, tagging remediation sprint.
A15: Engineering hours per intervention | B15: 16 | E15: Executing a rightsizing, a storage migration or a cluster consolidation is engineering time. Counted once per event, in year 0.
A16: Loaded engineering rate per hour | B16: 150 | E16: Blended senior/mid rate including overhead.
A17: Year-1 ramp (share of run-rate realised in year 1) | B17: 0.5 | E17: Interventions land through the year; a linear ramp realises half the annual run-rate in year 1 and the full run-rate from year 2.
A19: Planning
A20: Budget growth assumption (annual) | B20: 0.15 | E20: Budget = run-rate of the first six months, grown monthly at this rate. Illustrates the method; a real plan replaces this row.
A21: Months defining the run-rate budget | B21: 6 | E21: First N complete months average to the baseline. Fixed at 6 in the layout.
A23: Attribution policy
A24: Credit estimates that fail the parallel-trends check? | B24: No | E24: No = only estimates whose pre-trend check passed are credited (recommended). Yes = credit every identified estimate.
A26: Scenario
A27: Active scenario | B27: Base | E27: Drives ROI Analysis, Forecast and the KPI Dashboard. Scenario Analysis shows all three side by side regardless.
A29: Scenario driver | B29: Base | C29: Bull | D29: Bear | E29: What it means
A30: Effect realisation | B30: 1 | C30: 1.1 | D30: 0.75 | E30: Multiplier on attributed savings. Bear: a quarter of measured savings do not survive contact with production.
A31: Programme cost multiplier | B31: 1 | C31: 0.9 | D31: 1.3 | E31: Bear: hiring takes longer and tooling costs more than planned.
A32: Cloud growth (forecast) | B32: 0.15 | C32: 0.1 | D32: 0.25 | E32: Annual growth applied in the run-rate forecast.
A33: Savings persistence | B33: 0.85 | C33: 0.9 | D33: 0.7 | E33: Overrides the financial assumption above when a scenario is active.
A35: Active scenario values (formulas)
A36: Effect realisation | B36: =INDEX($B$30:$D$30,MATCH(B27,$B$29:$D$29,0)) -> 1
A37: Programme cost multiplier | B37: =INDEX($B$31:$D$31,MATCH(B27,$B$29:$D$29,0)) -> 1
A38: Cloud growth (forecast) | B38: =INDEX($B$32:$D$32,MATCH(B27,$B$29:$D$29,0)) -> 0.15
A39: Savings persistence | B39: =INDEX($B$33:$D$33,MATCH(B27,$B$29:$D$29,0)) -> 0.85
A41: SIMULATED DATA. The estate is synthetic (FOCUS 1.2, 400 resources, 540 days). Figures illustrate the method; ground truth exists only because the data is simulated.

Sheet 11 KPI Dashboard
A1: KPI dashboard
A2: Everything here is a formula into the other sheets. Change an assumption and the dashboard changes.
A3: SIMULATED DATA. The estate is synthetic (FOCUS 1.2, 400 resources, 540 days). Figures illustrate the method; ground truth exists only because the data is simulated.
A5: Annualised cloud run-rate | C5: Events measured | E5: Passing parallel trends | G5: Credited annual savings
A6: =AVERAGE('02 Raw Cost Data'!P11:P22)*12 -> 9422547.7 | C6: ='04 Savings Attribution'!$D$127 -> 117 | E6: ='04 Savings Attribution'!$D$128 -> 103 | G6: ='04 Savings Attribution'!$D$133 -> 1872634
A7: last 12 complete months, annualised | C7: interventions with a usable control group | E7: estimates credible enough to credit | G7: identified, gated by parallel trends
A9: Before/after would report | C9: Programme NPV (5 yr) | E9: ROI (PV basis) | G9: Payback
A10: ='04 Savings Attribution'!$D$131 -> 1693741 | C10: ='07 ROI Analysis'!$B$26 -> 2833109.4 | E10: ='07 ROI Analysis'!$B$30 -> 1.8634267 | G10: ='07 ROI Analysis'!$B$32 -> 6.54707
A11: the industry's number | C11: active scenario | E11: active scenario | G11: months
A13: Budget variance, period | C13: SIMULATED: gross misattribution | E13: Active scenario | G13: Attribution policy
A14: ='05 Budget vs Actual'!$Z$18 -> 0.071979076 | C14: ='04 Savings Attribution'!$D$135 -> 450967.84 | E14: ='10 Assumptions'!$B$27 -> Base | G14: =IF('10 Assumptions'!$B$24="Yes","all estimates","parallel-trends gate") -> parallel-trends gate
A15: actual vs run-rate budget | C15: |before/after − true|, summed
A18: Chart data (formulas)
A19: Measure | B19: Annual $
A20: Before/after | B20: ='04 Savings Attribution'!$D$131 -> 1693741
A21: Identified, all | B21: ='04 Savings Attribution'!$D$132 -> 1809486.9
A22: Credited (gated) | B22: ='04 Savings Attribution'!$D$133 -> 1872634
A23: SIMULATED true | B23: ='04 Savings Attribution'!$D$134 -> 2020441.1
A26: Month | B26: Budget | C26: Actual
A27: ='05 Budget vs Actual'!A7 -> 45839 | B27: ='05 Budget vs Actual'!W7 -> 697239.81 | C27: ='05 Budget vs Actual'!X7 -> 723189.72
A28: ='05 Budget vs Actual'!A8 -> 45870 | B28: ='05 Budget vs Actual'!W8 -> 705407.92 | C28: ='05 Budget vs Actual'!X8 -> 720339.02
A29: ='05 Budget vs Actual'!A9 -> 45901 | B29: ='05 Budget vs Actual'!W9 -> 713671.72 | C29: ='05 Budget vs Actual'!X9 -> 726305.01
A30: ='05 Budget vs Actual'!A10 -> 45931 | B30: ='05 Budget vs Actual'!W10 -> 722032.32 | C30: ='05 Budget vs Actual'!X10 -> 791709.56
A31: ='05 Budget vs Actual'!A11 -> 45962 | B31: ='05 Budget vs Actual'!W11 -> 730490.87 | C31: ='05 Budget vs Actual'!X11 -> 801718.11
A32: ='05 Budget vs Actual'!A12 -> 45992 | B32: ='05 Budget vs Actual'!W12 -> 739048.51 | C32: ='05 Budget vs Actual'!X12 -> 856377.91
A33: ='05 Budget vs Actual'!A13 -> 46023 | B33: ='05 Budget vs Actual'!W13 -> 747706.4 | C33: ='05 Budget vs Actual'!X13 -> 804605.05
A34: ='05 Budget vs Actual'!A14 -> 46054 | B34: ='05 Budget vs Actual'!W14 -> 756465.72 | C34: ='05 Budget vs Actual'!X14 -> 708434.43
A35: ='05 Budget vs Actual'!A15 -> 46082 | B35: ='05 Budget vs Actual'!W15 -> 765327.65 | C35: ='05 Budget vs Actual'!X15 -> 870094.21
A36: ='05 Budget vs Actual'!A16 -> 46113 | B36: ='05 Budget vs Actual'!W16 -> 774293.4 | C36: ='05 Budget vs Actual'!X16 -> 880808.74
A37: ='05 Budget vs Actual'!A17 -> 46143 | B37: ='05 Budget vs Actual'!W17 -> 783364.19 | C37: ='05 Budget vs Actual'!X17 -> 837020.01
A40: Business unit | B40: Budget | C40: Actual
A41: bu-assist | B41: ='05 Budget vs Actual'!B18 -> 1855728.9 | C41: ='05 Budget vs Actual'!C18 -> 2013844.9
A42: bu-checkout | B42: ='05 Budget vs Actual'!E18 -> 1017822.7 | C42: ='05 Budget vs Actual'!F18 -> 1165465
A43: bu-datalake | B43: ='05 Budget vs Actual'!H18 -> 754985.32 | C43: ='05 Budget vs Actual'!I18 -> 750185.81
A44: bu-datasci | B44: ='05 Budget vs Actual'!K18 -> 1773020.7 | C44: ='05 Budget vs Actual'!L18 -> 1914114.7
A45: bu-platform | B45: ='05 Budget vs Actual'!N18 -> 838909.7 | C45: ='05 Budget vs Actual'!O18 -> 841976.39
A46: bu-search | B46: ='05 Budget vs Actual'!Q18 -> 1018337.7 | C46: ='05 Budget vs Actual'!R18 -> 1113179.5
A47: unallocated | B47: ='05 Budget vs Actual'!T18 -> 876243.42 | C47: ='05 Budget vs Actual'!U18 -> 921835.45
