Workbook

Sheet Executive Summary
A1: CostProof - Business Case
A2: Measuring cloud savings correctly. All figures regenerate from `python -m costproof.cli study`; nothing here is hardcoded.
B4: THE PROBLEM
B5: Cloud waste reached 29% of spend in 2026, its first rise in five years, while 63% of organisations run a dedicated FinOps team. Either those teams do not work, or nobody can measure whether they work.
B9: THE FINDING
C11: ='Measurement Accuracy'!E5 -> 0.8 | E11: of actions that did nothing are reported as savings by the industry standard method
C14: ='Measurement Accuracy'!E7 -> 0.13333333 | E14: under CostProof - same point estimate, honest uncertainty
C17: =-'Measurement Accuracy'!$D$20 -> 326700.12 | E17: annual misstatement of the savings programme under the naive method
B20: THE RETURN
B21: Five-year NPV | C21: ='Value Model'!B25 -> 557508.1
B22: Benefit-to-cost ratio | C22: ='Value Model'!B26 -> 6.2698943
B24: WHAT IS AND IS NOT COUNTED
B25: Counted: engineering time saved by not scaling techniques that do not work. Not counted: the corrected misstatement itself. Fixing a reporting error makes the budget right; it does not create cash. Booking it as a benefit would repeat exactly the error this system exists to prevent.
B30: Source: outputs/tables/scorecard.csv and dollar_impact.csv, produced by 117 interventions scored against known ground truth.

Sheet Assumptions
A1: Assumptions
A2: Blue cells are inputs you set. Yellow fill marks the levers that move the answer most. Everything else in the workbook is a formula referencing these cells.
A4: ESTATE
A5: Annual cloud spend | B5: 9200000 | D5: From the modelled estate: 216,036 FOCUS billing rows over 18 months.
A6: Optimisation actions per year | B6: 79 | D6: 117 actions observed over 540 days, annualised.
A7: Share of actions with no real effect | B7: 0.2564 | D7: 30 of 117 actions in the study had a true effect of exactly zero.
A9: MEASUREMENT PERFORMANCE (measured, not assumed)
A10: False-positive rate - naive before/after | B10: 0.8 | D10: Share of zero-effect actions the industry method declares a significant saving.
A11: False-positive rate - CostProof | B11: 0.1333 | D11: Same measurement, difference-in-differences with randomization inference.
A13: COST OF ACTING ON A FALSE POSITIVE
A14: Engineering hours to scale a practice | B14: 24 | D14: A technique believed to work gets applied to more resources, written into a runbook and taught. Set to your team's actual rollout effort.
A15: Fully loaded engineering cost per hour | B15: 145 | D15: Salary, benefits, overhead. Adjust to your organisation.
A16: Times a believed-good practice is reapplied | B16: 3 | D16: How many further resources receive a technique once it is thought to work.
A18: PROGRAMME COST
A19: Implementation - one time | B19: 40000 | D19: Integrate the billing feed, map the change log, validate against a known period.
A20: Analyst hours per month to operate | B20: 12 | D20: Reviewing the queue, approving remediations, investigating failed validity checks.
A21: Fully loaded analyst cost per hour | B21: 110 | D21: Salary, benefits, overhead.
A22: Compute and storage per year | B22: 3600 | D22: DuckDB runs on a single machine; this is object storage plus the model calls.
A24: FINANCE
A25: Discount rate | B25: 0.12 | D25: Weighted average cost of capital. Set to your firm's rate.
A26: Evaluation horizon (years) | B26: 5 | D26: Standard for an internal tooling investment.
A27: Annual growth in optimisation activity | B27: 0.15 | D27: FinOps programmes scale; more actions each year means more to measure.
A29: Source for all measurement figures: outputs/tables/scorecard.csv and dollar_impact.csv, regenerated by `python -m costproof.cli study`.

Sheet Measurement Accuracy
A1: Measurement Accuracy
A2: Four estimators scored against known ground truth over 117 interventions, 30 of which had a true effect of exactly zero.
A4: Method | B4: Bias | C4: RMSE | D4: 95% coverage | E4: False positives | F4: Power | G4: Verdict
A5: Naive before/after | B5: 0.0983 | C5: 0.23785269 | D5: 0.27350427 | E5: 0.8 | F5: 1 | G5: Industry standard. Reports a significant saving on four in five actions that did nothing.
A6: DiD, cluster-robust errors | B6: 0.0655 | C6: 0.19881152 | D6: 0.23076923 | E6: 0.8333 | F6: 1 | G6: Same point estimate as the row below. Standard errors are invalid with one treated unit.
A7: DiD, randomization inference | B7: 0.0655 | C7: 0.19881152 | D7: 0.91452991 | E7: 0.13333333 | F7: 0.90804598 | G7: CostProof. Identical arithmetic to the row above; only the uncertainty differs.
A8: Synthetic control | B8: 0.0834 | C8: 0.2436 | D8: 0.83760684 | E8: 0 | F8: 0.4828 | G8: No false positives at all, but detects under half of real effects.
A11: THE VALIDITY FILTER
A12: Parallel-trends test | B12: n | C12: RMSE | D12: 95% coverage
A13: Passes | B13: 103 | C13: 0.1513 | D13: 0.951
A14: Fails | B14: 14 | C14: 0.4022 | D14: 0.643
A16: Estimates that pass the validity check have less than half the error and essentially nominal interval coverage. The system knows which of its own answers to trust, and that was measured rather than asserted.
A18: REPORTED SAVINGS vs TRUTH (annualised)
A19: Method | B19: True saving | C19: Claimed | D19: Misstatement
A20: Naive before/after | B20: 2020441.1 | C20: 1693741 | D20: -326700.12
A21: CostProof | B21: 2020441.1 | C21: 1809486.9 | D21: -210954.22

Sheet Value Model
A1: Value Model
A2: Five-year cash flows. Reported-savings accuracy is shown but deliberately excluded from NPV -- see the note at the bottom.
B4: Year 1 | C4: Year 2 | D4: Year 3 | E4: Year 4 | F4: Year 5
A5: ACTIVITY
A6: Optimisation actions measured | B6: =ROUND(Assumptions!$B$6*(1+Assumptions!$B$27)^0,0) -> 79 | C6: =ROUND(Assumptions!$B$6*(1+Assumptions!$B$27)^1,0) -> 91 | D6: =ROUND(Assumptions!$B$6*(1+Assumptions!$B$27)^2,0) -> 104 | E6: =ROUND(Assumptions!$B$6*(1+Assumptions!$B$27)^3,0) -> 120 | F6: =ROUND(Assumptions!$B$6*(1+Assumptions!$B$27)^4,0) -> 138
A7: Actions with no real effect | B7: =B6*Assumptions!$B$7 -> 20.2556 | C7: =C6*Assumptions!$B$7 -> 23.3324 | D7: =D6*Assumptions!$B$7 -> 26.6656 | E7: =E6*Assumptions!$B$7 -> 30.768 | F7: =F6*Assumptions!$B$7 -> 35.3832
A9: BENEFIT - AVOIDED WASTED EFFORT (cash)
A10: Falsely credited under naive method | B10: =B7*Assumptions!$B$10 -> 16.20448 | C10: =C7*Assumptions!$B$10 -> 18.66592 | D10: =D7*Assumptions!$B$10 -> 21.33248 | E10: =E7*Assumptions!$B$10 -> 24.6144 | F10: =F7*Assumptions!$B$10 -> 28.30656
A11: Falsely credited under CostProof | B11: =B7*Assumptions!$B$11 -> 2.7000715 | C11: =C7*Assumptions!$B$11 -> 3.1102089 | D11: =D7*Assumptions!$B$11 -> 3.5545245 | E11: =E7*Assumptions!$B$11 -> 4.1013744 | F11: =F7*Assumptions!$B$11 -> 4.7165806
A12: False credits avoided | B12: =B10-B11 -> 13.504409 | C12: =C10-C11 -> 15.555711 | D12: =D10-D11 -> 17.777956 | E12: =E10-E11 -> 20.513026 | F12: =F10-F11 -> 23.589979
A13: Cost of scaling one ineffective practice | B13: =Assumptions!$B$14*Assumptions!$B$15*Assumptions!$B$16 -> 10440 | C13: =Assumptions!$B$14*Assumptions!$B$15*Assumptions!$B$16 -> 10440 | D13: =Assumptions!$B$14*Assumptions!$B$15*Assumptions!$B$16 -> 10440 | E13: =Assumptions!$B$14*Assumptions!$B$15*Assumptions!$B$16 -> 10440 | F13: =Assumptions!$B$14*Assumptions!$B$15*Assumptions!$B$16 -> 10440
A14: Avoided wasted effort | B14: =B12*B13 -> 140986.02 | C14: =C12*C13 -> 162401.62 | D14: =D12*D13 -> 185601.86 | E14: =E12*E13 -> 214155.99 | F14: =F12*F13 -> 246279.39
A16: PROGRAMME COST
A17: Implementation | B17: =IF(1=1,-Assumptions!$B$19,0) -> -40000 | C17: =IF(2=1,-Assumptions!$B$19,0) -> 0 | D17: =IF(3=1,-Assumptions!$B$19,0) -> 0 | E17: =IF(4=1,-Assumptions!$B$19,0) -> 0 | F17: =IF(5=1,-Assumptions!$B$19,0) -> 0
A18: Analyst time | B18: =-Assumptions!$B$20*12*Assumptions!$B$21 -> -15840 | C18: =-Assumptions!$B$20*12*Assumptions!$B$21 -> -15840 | D18: =-Assumptions!$B$20*12*Assumptions!$B$21 -> -15840 | E18: =-Assumptions!$B$20*12*Assumptions!$B$21 -> -15840 | F18: =-Assumptions!$B$20*12*Assumptions!$B$21 -> -15840
A19: Compute and storage | B19: =-Assumptions!$B$22 -> -3600 | C19: =-Assumptions!$B$22 -> -3600 | D19: =-Assumptions!$B$22 -> -3600 | E19: =-Assumptions!$B$22 -> -3600 | F19: =-Assumptions!$B$22 -> -3600
A20: Total cost | B20: =SUM(B17:B19) -> -59440 | C20: =SUM(C17:C19) -> -19440 | D20: =SUM(D17:D19) -> -19440 | E20: =SUM(E17:E19) -> -19440 | F20: =SUM(F17:F19) -> -19440
A21: NET CASH FLOW | B21: =B14+B20 -> 81546.025 | C21: =C14+C20 -> 142961.62 | D21: =D14+D20 -> 166161.86 | E21: =E14+E20 -> 194715.99 | F21: =F14+F20 -> 226839.39
A24: RETURNS
A25: Net present value | B25: =NPV(Assumptions!$B$25,B21:F21) -> 557508.1
A26: Benefit-to-cost ratio (5yr, discounted) | B26: =NPV(Assumptions!$B$25,B14:F14)/-NPV(Assumptions!$B$25,B20:F20) -> 6.2698943
A27: Year 1 net cash flow | B27: =B21 -> 81546.025
A28: IRR is not reported: it requires a sign change in the cash flows, and this programme is cash-positive in year one. An undefined IRR is a strong result here, not a missing one.
A30: SHOWN BUT NOT COUNTED AS CASH
A31: Reduction in reported-savings misstatement | B31: ='Measurement Accuracy'!$D$21-'Measurement Accuracy'!$D$20 -> 115745.9
A32: Correcting a misstatement does not create cash -- it makes the budget right. Booking accounting accuracy as a cash benefit would repeat exactly the error this system exists to prevent, so it is excluded from the NPV above.

Sheet Sensitivity
A1: Sensitivity
A2: Five-year NPV. Rows vary the loaded engineering rate; columns vary the share of optimisation actions that have no real effect.
A4: Loaded rate \ null share | B4: 10.0% | C4: 15.0% | D4: 20.0% | E4: 25.6% | F4: 30.0% | G4: 35.0%
A5: 95 | B5: =((ROUND(Assumptions!$B$6*(1+Assumptions!$B$27)^0,0)*0.1*(Assumptions!$B$10-Assumptions!$B$11)*Assumptions!$B$14*95*Assumptions!$B$16)-((Assumptions!$B$20*12*Assumptions!$B$21+Assumptions!$B$22)+Assumptions!$B$19))/(1+Assumptions!$B$25)^1+((ROUND(Assumptions!$B$6*(1+Assumptions!$B$27)^1,0)*0.1*(Assumptions!$B$10-Assumptions!$B$11)*Assumptions!$B$14*95*Assumptions!$B$16)-((Assumptions!$B$20*12*Assumptions!$B$21+Assumptions!$B$22)))/(1+Assumptions!$B$25)^2+((ROUND(Assumptions!$B$6*(1+Assumptions!$B$27)^2,0)*0.1*(Assumptions!$B$10-Assumptions!$B$11)*Assumptions!$B$14*95*Assumptions!$B$16)-((Assumptions!$B$20*12*Assumptions!$B$21+Assumptions!$B$22)))/(1+Assumptions!$B$25)^3+((ROUND(Assumptions!$B$6*(1+Assumptions!$B$27)^3,0)*0.1*(Assumptions!$B$10-Assumptions!$B$11)*Assumptions!$B$14*95*Assumptions!$B$16)-((Assumptions!$B$20*12*Assumptions!$B$21+Assumptions!$B$22)))/(1+Assumptions!$B$25)^4+((ROUND(Assumptions!$B$6*(1+Assumptions!$B$27)^4,0)*0.1*(Assumptions!$B$10-Assumptions!$B$11)*Assumptions!$B$14*95*Assumptions!$B$16)-((Assumptions!$B$20*12*Assumptions!$B$21+Assumptions!$B$22)))/(1+Assumptions!$B$25)^5 -> 63700.035 | C5: =((ROUND(Assumptions!$B$6*(1+Assumptions!$B$27)^0,0)*0.15*(Assumptions!$B$10-Assumptions!$B$11)*Assumptions!$B$14*95*Assumptions!$B$16)-((Assumptions!$B$20*12*Assumptions!$B$21+Assumptions!$B$22)+Assumptions!$B$19))/(1+Assumptions!$B$25)^1+((ROUND(Assumptions!$B$6*(1+Assumptions!$B$27)^1,0)*0.15*(Assumptions!$B$10-Assumptions!$B$11)*Assumptions!$B$14*95*Assumptions!$B$16)-((Assumptions!$B$20*12*Assumptions!$B$21+Assumptions!$B$22)))/(1+Assumptions!$B$25)^2+((ROUND(Assumptions!$B$6*(1+Assumptions!$B$27)^2,0)*0.15*(Assumptions!$B$10-Assumptions!$B$11)*Assumptions!$B$14*95*Assumptions!$B$16)-((Assumptions!$B$20*12*Assumptions!$B$21+Assumptions!$B$22)))/(1+Assumptions!$B$25)^3+((ROUND(Assumptions!$B$6*(1+Assumptions!$B$27)^3,0)*0.15*(Assumptions!$B$10-Assumptions!$B$11)*Assumptions!$B$14*95*Assumptions!$B$16)-((Assumptions!$B$20*12*Assumptions!$B$21+Assumptions!$B$22)))/(1+Assumptions!$B$25)^4+((ROUND(Assumptions!$B$6*(1+Assumptions!$B$27)^4,0)*0.15*(Assumptions!$B$10-Assumptions!$B$11)*Assumptions!$B$14*95*Assumptions!$B$16)-((Assumptions!$B$20*12*Assumptions!$B$21+Assumptions!$B$22)))/(1+Assumptions!$B$25)^5 -> 148445.62 | D5: =((ROUND(Assumptions!$B$6*(1+Assumptions!$B$27)^0,0)*0.2*(Assumptions!$B$10-Assumptions!$B$11)*Assumptions!$B$14*95*Assumptions!$B$16)-((Assumptions!$B$20*12*Assumptions!$B$21+Assumptions!$B$22)+Assumptions!$B$19))/(1+Assumptions!$B$25)^1+((ROUND(Assumptions!$B$6*(1+Assumptions!$B$27)^1,0)*0.2*(Assumptions!$B$10-Assumptions!$B$11)*Assumptions!$B$14*95*Assumptions!$B$16)-((Assumptions!$B$20*12*Assumptions!$B$21+Assumptions!$B$22)))/(1+Assumptions!$B$25)^2+((ROUND(Assumptions!$B$6*(1+Assumptions!$B$27)^2,0)*0.2*(Assumptions!$B$10-Assumptions!$B$11)*Assumptions!$B$14*95*Assumptions!$B$16)-((Assumptions!$B$20*12*Assumptions!$B$21+Assumptions!$B$22)))/(1+Assumptions!$B$25)^3+((ROUND(Assumptions!$B$6*(1+Assumptions!$B$27)^3,0)*0.2*(Assumptions!$B$10-Assumptions!$B$11)*Assumptions!$B$14*95*Assumptions!$B$16)-((Assumptions!$B$20*12*Assumptions!$B$21+Assumptions!$B$22)))/(1+Assumptions!$B$25)^4+((ROUND(Assumptions!$B$6*(1+Assumptions!$B$27)^4,0)*0.2*(Assumptions!$B$10-Assumptions!$B$11)*Assumptions!$B$14*95*Assumptions!$B$16)-((Assumptions!$B$20*12*Assumptions!$B$21+Assumptions!$B$22)))/(1+Assumptions!$B$25)^5 -> 233191.2 | E5: =((ROUND(Assumptions!$B$6*(1+Assumptions!$B$27)^0,0)*0.256*(Assumptions!$B$10-Assumptions!$B$11)*Assumptions!$B$14*95*Assumptions!$B$16)-((Assumptions!$B$20*12*Assumptions!$B$21+Assumptions!$B$22)+Assumptions!$B$19))/(1+Assumptions!$B$25)^1+((ROUND(Assumptions!$B$6*(1+Assumptions!$B$27)^1,0)*0.256*(Assumptions!$B$10-Assumptions!$B$11)*Assumptions!$B$14*95*Assumptions!$B$16)-((Assumptions!$B$20*12*Assumptions!$B$21+Assumptions!$B$22)))/(1+Assumptions!$B$25)^2+((ROUND(Assumptions!$B$6*(1+Assumptions!$B$27)^2,0)*0.256*(Assumptions!$B$10-Assumptions!$B$11)*Assumptions!$B$14*95*Assumptions!$B$16)-((Assumptions!$B$20*12*Assumptions!$B$21+Assumptions!$B$22)))/(1+Assumptions!$B$25)^3+((ROUND(Assumptions!$B$6*(1+Assumptions!$B$27)^3,0)*0.256*(Assumptions!$B$10-Assumptions!$B$11)*Assumptions!$B$14*95*Assumptions!$B$16)-((Assumptions!$B$20*12*Assumptions!$B$21+Assumptions!$B$22)))/(1+Assumptions!$B$25)^4+((ROUND(Assumptions!$B$6*(1+Assumptions!$B$27)^4,0)*0.256*(Assumptions!$B$10-Assumptions!$B$11)*Assumptions!$B$14*95*Assumptions!$B$16)-((Assumptions!$B$20*12*Assumptions!$B$21+Assumptions!$B$22)))/(1+Assumptions!$B$25)^5 -> 328106.26 | F5: =((ROUND(Assumptions!$B$6*(1+Assumptions!$B$27)^0,0)*0.3*(Assumptions!$B$10-Assumptions!$B$11)*Assumptions!$B$14*95*Assumptions!$B$16)-((Assumptions!$B$20*12*Assumptions!$B$21+Assumptions!$B$22)+Assumptions!$B$19))/(1+Assumptions!$B$25)^1+((ROUND(Assumptions!$B$6*(1+Assumptions!$B$27)^1,0)*0.3*(Assumptions!$B$10-Assumptions!$B$11)*Assumptions!$B$14*95*Assumptions!$B$16)-((Assumptions!$B$20*12*Assumptions!$B$21+Assumptions!$B$22)))/(1+Assumptions!$B$25)^2+((ROUND(Assumptions!$B$6*(1+Assumptions!$B$27)^2,0)*0.3*(Assumptions!$B$10-Assumptions!$B$11)*Assumptions!$B$14*95*Assumptions!$B$16)-((Assumptions!$B$20*12*Assumptions!$B$21+Assumptions!$B$22)))/(1+Assumptions!$B$25)^3+((ROUND(Assumptions!$B$6*(1+Assumptions!$B$27)^3,0)*0.3*(Assumptions!$B$10-Assumptions!$B$11)*Assumptions!$B$14*95*Assumptions!$B$16)-((Assumptions!$B$20*12*Assumptions!$B$21+Assumptions!$B$22)))/(1+Assumptions!$B$25)^4+((ROUND(Assumptions!$B$6*(1+Assumptions!$B$27)^4,0)*0.3*(Assumptions!$B$10-Assumptions!$B$11)*Assumptions!$B$14*95*Assumptions!$B$16)-((Assumptions!$B$20*12*Assumptions!$B$21+Assumptions!$B$22)))/(1+Assumptions!$B$25)^5 -> 402682.37 | G5: =((ROUND(Assumptions!$B$6*(1+Assumptions!$B$27)^0,0)*0.35*(Assumptions!$B$10-Assumptions!$B$11)*Assumptions!$B$14*95*Assumptions!$B$16)-((Assumptions!$B$20*12*Assumptions!$B$21+Assumptions!$B$22)+Assumptions!$B$19))/(1+Assumptions!$B$25)^1+((ROUND(Assumptions!$B$6*(1+Assumptions!$B$27)^1,0)*0.35*(Assumptions!$B$10-Assumptions!$B$11)*Assumptions!$B$14*95*Assumptions!$B$16)-((Assumptions!$B$20*12*Assumptions!$B$21+Assumptions!$B$22)))/(1+Assumptions!$B$25)^2+((ROUND(Assumptions!$B$6*(1+Assumptions!$B$27)^2,0)*0.35*(Assumptions!$B$10-Assumptions!$B$11)*Assumptions!$B$14*95*Assumptions!$B$16)-((Assumptions!$B$20*12*Assumptions!$B$21+Assumptions!$B$22)))/(1+Assumptions!$B$25)^3+((ROUND(Assumptions!$B$6*(1+Assumptions!$B$27)^3,0)*0.35*(Assumptions!$B$10-Assumptions!$B$11)*Assumptions!$B$14*95*Assumptions!$B$16)-((Assumptions!$B$20*12*Assumptions!$B$21+Assumptions!$B$22)))/(1+Assumptions!$B$25)^4+((ROUND(Assumptions!$B$6*(1+Assumptions!$B$27)^4,0)*0.35*(Assumptions!$B$10-Assumptions!$B$11)*Assumptions!$B$14*95*Assumptions!$B$16)-((Assumptions!$B$20*12*Assumptions!$B$21+Assumptions!$B$22)))/(1+Assumptions!$B$25)^5 -> 487427.96
A6: 120 | B6: =((ROUND(Assumptions!$B$6*(1+Assumptions!$B$27)^0,0)*0.1*(Assumptions!$B$10-Assumptions!$B$11)*Assumptions!$B$14*120*Assumptions!$B$16)-((Assumptions!$B$20*12*Assumptions!$B$21+Assumptions!$B$22)+Assumptions!$B$19))/(1+Assumptions!$B$25)^1+((ROUND(Assumptions!$B$6*(1+Assumptions!$B$27)^1,0)*0.1*(Assumptions!$B$10-Assumptions!$B$11)*Assumptions!$B$14*120*Assumptions!$B$16)-((Assumptions!$B$20*12*Assumptions!$B$21+Assumptions!$B$22)))/(1+Assumptions!$B$25)^2+((ROUND(Assumptions!$B$6*(1+Assumptions!$B$27)^2,0)*0.1*(Assumptions!$B$10-Assumptions!$B$11)*Assumptions!$B$14*120*Assumptions!$B$16)-((Assumptions!$B$20*12*Assumptions!$B$21+Assumptions!$B$22)))/(1+Assumptions!$B$25)^3+((ROUND(Assumptions!$B$6*(1+Assumptions!$B$27)^3,0)*0.1*(Assumptions!$B$10-Assumptions!$B$11)*Assumptions!$B$14*120*Assumptions!$B$16)-((Assumptions!$B$20*12*Assumptions!$B$21+Assumptions!$B$22)))/(1+Assumptions!$B$25)^4+((ROUND(Assumptions!$B$6*(1+Assumptions!$B$27)^4,0)*0.1*(Assumptions!$B$10-Assumptions!$B$11)*Assumptions!$B$14*120*Assumptions!$B$16)-((Assumptions!$B$20*12*Assumptions!$B$21+Assumptions!$B$22)))/(1+Assumptions!$B$25)^5 -> 108302.97 | C6: =((ROUND(Assumptions!$B$6*(1+Assumptions!$B$27)^0,0)*0.15*(Assumptions!$B$10-Assumptions!$B$11)*Assumptions!$B$14*120*Assumptions!$B$16)-((Assumptions!$B$20*12*Assumptions!$B$21+Assumptions!$B$22)+Assumptions!$B$19))/(1+Assumptions!$B$25)^1+((ROUND(Assumptions!$B$6*(1+Assumptions!$B$27)^1,0)*0.15*(Assumptions!$B$10-Assumptions!$B$11)*Assumptions!$B$14*120*Assumptions!$B$16)-((Assumptions!$B$20*12*Assumptions!$B$21+Assumptions!$B$22)))/(1+Assumptions!$B$25)^2+((ROUND(Assumptions!$B$6*(1+Assumptions!$B$27)^2,0)*0.15*(Assumptions!$B$10-Assumptions!$B$11)*Assumptions!$B$14*120*Assumptions!$B$16)-((Assumptions!$B$20*12*Assumptions!$B$21+Assumptions!$B$22)))/(1+Assumptions!$B$25)^3+((ROUND(Assumptions!$B$6*(1+Assumptions!$B$27)^3,0)*0.15*(Assumptions!$B$10-Assumptions!$B$11)*Assumptions!$B$14*120*Assumptions!$B$16)-((Assumptions!$B$20*12*Assumptions!$B$21+Assumptions!$B$22)))/(1+Assumptions!$B$25)^4+((ROUND(Assumptions!$B$6*(1+Assumptions!$B$27)^4,0)*0.15*(Assumptions!$B$10-Assumptions!$B$11)*Assumptions!$B$14*120*Assumptions!$B$16)-((Assumptions!$B$20*12*Assumptions!$B$21+Assumptions!$B$22)))/(1+Assumptions!$B$25)^5 -> 215350.03 | D6: =((ROUND(Assumptions!$B$6*(1+Assumptions!$B$27)^0,0)*0.2*(Assumptions!$B$10-Assumptions!$B$11)*Assumptions!$B$14*120*Assumptions!$B$16)-((Assumptions!$B$20*12*Assumptions!$B$21+Assumptions!$B$22)+Assumptions!$B$19))/(1+Assumptions!$B$25)^1+((ROUND(Assumptions!$B$6*(1+Assumptions!$B$27)^1,0)*0.2*(Assumptions!$B$10-Assumptions!$B$11)*Assumptions!$B$14*120*Assumptions!$B$16)-((Assumptions!$B$20*12*Assumptions!$B$21+Assumptions!$B$22)))/(1+Assumptions!$B$25)^2+((ROUND(Assumptions!$B$6*(1+Assumptions!$B$27)^2,0)*0.2*(Assumptions!$B$10-Assumptions!$B$11)*Assumptions!$B$14*120*Assumptions!$B$16)-((Assumptions!$B$20*12*Assumptions!$B$21+Assumptions!$B$22)))/(1+Assumptions!$B$25)^3+((ROUND(Assumptions!$B$6*(1+Assumptions!$B$27)^3,0)*0.2*(Assumptions!$B$10-Assumptions!$B$11)*Assumptions!$B$14*120*Assumptions!$B$16)-((Assumptions!$B$20*12*Assumptions!$B$21+Assumptions!$B$22)))/(1+Assumptions!$B$25)^4+((ROUND(Assumptions!$B$6*(1+Assumptions!$B$27)^4,0)*0.2*(Assumptions!$B$10-Assumptions!$B$11)*Assumptions!$B$14*120*Assumptions!$B$16)-((Assumptions!$B$20*12*Assumptions!$B$21+Assumptions!$B$22)))/(1+Assumptions!$B$25)^5 -> 322397.08 | E6: =((ROUND(Assumptions!$B$6*(1+Assumptions!$B$27)^0,0)*0.256*(Assumptions!$B$10-Assumptions!$B$11)*Assumptions!$B$14*120*Assumptions!$B$16)-((Assumptions!$B$20*12*Assumptions!$B$21+Assumptions!$B$22)+Assumptions!$B$19))/(1+Assumptions!$B$25)^1+((ROUND(Assumptions!$B$6*(1+Assumptions!$B$27)^1,0)*0.256*(Assumptions!$B$10-Assumptions!$B$11)*Assumptions!$B$14*120*Assumptions!$B$16)-((Assumptions!$B$20*12*Assumptions!$B$21+Assumptions!$B$22)))/(1+Assumptions!$B$25)^2+((ROUND(Assumptions!$B$6*(1+Assumptions!$B$27)^2,0)*0.256*(Assumptions!$B$10-Assumptions!$B$11)*Assumptions!$B$14*120*Assumptions!$B$16)-((Assumptions!$B$20*12*Assumptions!$B$21+Assumptions!$B$22)))/(1+Assumptions!$B$25)^3+((ROUND(Assumptions!$B$6*(1+Assumptions!$B$27)^3,0)*0.256*(Assumptions!$B$10-Assumptions!$B$11)*Assumptions!$B$14*120*Assumptions!$B$16)-((Assumptions!$B$20*12*Assumptions!$B$21+Assumptions!$B$22)))/(1+Assumptions!$B$25)^4+((ROUND(Assumptions!$B$6*(1+Assumptions!$B$27)^4,0)*0.256*(Assumptions!$B$10-Assumptions!$B$11)*Assumptions!$B$14*120*Assumptions!$B$16)-((Assumptions!$B$20*12*Assumptions!$B$21+Assumptions!$B$22)))/(1+Assumptions!$B$25)^5 -> 442289.78 | F6: =((ROUND(Assumptions!$B$6*(1+Assumptions!$B$27)^0,0)*0.3*(Assumptions!$B$10-Assumptions!$B$11)*Assumptions!$B$14*120*Assumptions!$B$16)-((Assumptions!$B$20*12*Assumptions!$B$21+Assumptions!$B$22)+Assumptions!$B$19))/(1+Assumptions!$B$25)^1+((ROUND(Assumptions!$B$6*(1+Assumptions!$B$27)^1,0)*0.3*(Assumptions!$B$10-Assumptions!$B$11)*Assumptions!$B$14*120*Assumptions!$B$16)-((Assumptions!$B$20*12*Assumptions!$B$21+Assumptions!$B$22)))/(1+Assumptions!$B$25)^2+((ROUND(Assumptions!$B$6*(1+Assumptions!$B$27)^2,0)*0.3*(Assumptions!$B$10-Assumptions!$B$11)*Assumptions!$B$14*120*Assumptions!$B$16)-((Assumptions!$B$20*12*Assumptions!$B$21+Assumptions!$B$22)))/(1+Assumptions!$B$25)^3+((ROUND(Assumptions!$B$6*(1+Assumptions!$B$27)^3,0)*0.3*(Assumptions!$B$10-Assumptions!$B$11)*Assumptions!$B$14*120*Assumptions!$B$16)-((Assumptions!$B$20*12*Assumptions!$B$21+Assumptions!$B$22)))/(1+Assumptions!$B$25)^4+((ROUND(Assumptions!$B$6*(1+Assumptions!$B$27)^4,0)*0.3*(Assumptions!$B$10-Assumptions!$B$11)*Assumptions!$B$14*120*Assumptions!$B$16)-((Assumptions!$B$20*12*Assumptions!$B$21+Assumptions!$B$22)))/(1+Assumptions!$B$25)^5 -> 536491.19 | G6: =((ROUND(Assumptions!$B$6*(1+Assumptions!$B$27)^0,0)*0.35*(Assumptions!$B$10-Assumptions!$B$11)*Assumptions!$B$14*120*Assumptions!$B$16)-((Assumptions!$B$20*12*Assumptions!$B$21+Assumptions!$B$22)+Assumptions!$B$19))/(1+Assumptions!$B$25)^1+((ROUND(Assumptions!$B$6*(1+Assumptions!$B$27)^1,0)*0.35*(Assumptions!$B$10-Assumptions!$B$11)*Assumptions!$B$14*120*Assumptions!$B$16)-((Assumptions!$B$20*12*Assumptions!$B$21+Assumptions!$B$22)))/(1+Assumptions!$B$25)^2+((ROUND(Assumptions!$B$6*(1+Assumptions!$B$27)^2,0)*0.35*(Assumptions!$B$10-Assumptions!$B$11)*Assumptions!$B$14*120*Assumptions!$B$16)-((Assumptions!$B$20*12*Assumptions!$B$21+Assumptions!$B$22)))/(1+Assumptions!$B$25)^3+((ROUND(Assumptions!$B$6*(1+Assumptions!$B$27)^3,0)*0.35*(Assumptions!$B$10-Assumptions!$B$11)*Assumptions!$B$14*120*Assumptions!$B$16)-((Assumptions!$B$20*12*Assumptions!$B$21+Assumptions!$B$22)))/(1+Assumptions!$B$25)^4+((ROUND(Assumptions!$B$6*(1+Assumptions!$B$27)^4,0)*0.35*(Assumptions!$B$10-Assumptions!$B$11)*Assumptions!$B$14*120*Assumptions!$B$16)-((Assumptions!$B$20*12*Assumptions!$B$21+Assumptions!$B$22)))/(1+Assumptions!$B$25)^5 -> 643538.25
A7: 145 | B7: =((ROUND(Assumptions!$B$6*(1+Assumptions!$B$27)^0,0)*0.1*(Assumptions!$B$10-Assumptions!$B$11)*Assumptions!$B$14*145*Assumptions!$B$16)-((Assumptions!$B$20*12*Assumptions!$B$21+Assumptions!$B$22)+Assumptions!$B$19))/(1+Assumptions!$B$25)^1+((ROUND(Assumptions!$B$6*(1+Assumptions!$B$27)^1,0)*0.1*(Assumptions!$B$10-Assumptions!$B$11)*Assumptions!$B$14*145*Assumptions!$B$16)-((Assumptions!$B$20*12*Assumptions!$B$21+Assumptions!$B$22)))/(1+Assumptions!$B$25)^2+((ROUND(Assumptions!$B$6*(1+Assumptions!$B$27)^2,0)*0.1*(Assumptions!$B$10-Assumptions!$B$11)*Assumptions!$B$14*145*Assumptions!$B$16)-((Assumptions!$B$20*12*Assumptions!$B$21+Assumptions!$B$22)))/(1+Assumptions!$B$25)^3+((ROUND(Assumptions!$B$6*(1+Assumptions!$B$27)^3,0)*0.1*(Assumptions!$B$10-Assumptions!$B$11)*Assumptions!$B$14*145*Assumptions!$B$16)-((Assumptions!$B$20*12*Assumptions!$B$21+Assumptions!$B$22)))/(1+Assumptions!$B$25)^4+((ROUND(Assumptions!$B$6*(1+Assumptions!$B$27)^4,0)*0.1*(Assumptions!$B$10-Assumptions!$B$11)*Assumptions!$B$14*145*Assumptions!$B$16)-((Assumptions!$B$20*12*Assumptions!$B$21+Assumptions!$B$22)))/(1+Assumptions!$B$25)^5 -> 152905.91 | C7: =((ROUND(Assumptions!$B$6*(1+Assumptions!$B$27)^0,0)*0.15*(Assumptions!$B$10-Assumptions!$B$11)*Assumptions!$B$14*145*Assumptions!$B$16)-((Assumptions!$B$20*12*Assumptions!$B$21+Assumptions!$B$22)+Assumptions!$B$19))/(1+Assumptions!$B$25)^1+((ROUND(Assumptions!$B$6*(1+Assumptions!$B$27)^1,0)*0.15*(Assumptions!$B$10-Assumptions!$B$11)*Assumptions!$B$14*145*Assumptions!$B$16)-((Assumptions!$B$20*12*Assumptions!$B$21+Assumptions!$B$22)))/(1+Assumptions!$B$25)^2+((ROUND(Assumptions!$B$6*(1+Assumptions!$B$27)^2,0)*0.15*(Assumptions!$B$10-Assumptions!$B$11)*Assumptions!$B$14*145*Assumptions!$B$16)-((Assumptions!$B$20*12*Assumptions!$B$21+Assumptions!$B$22)))/(1+Assumptions!$B$25)^3+((ROUND(Assumptions!$B$6*(1+Assumptions!$B$27)^3,0)*0.15*(Assumptions!$B$10-Assumptions!$B$11)*Assumptions!$B$14*145*Assumptions!$B$16)-((Assumptions!$B$20*12*Assumptions!$B$21+Assumptions!$B$22)))/(1+Assumptions!$B$25)^4+((ROUND(Assumptions!$B$6*(1+Assumptions!$B$27)^4,0)*0.15*(Assumptions!$B$10-Assumptions!$B$11)*Assumptions!$B$14*145*Assumptions!$B$16)-((Assumptions!$B$20*12*Assumptions!$B$21+Assumptions!$B$22)))/(1+Assumptions!$B$25)^5 -> 282254.44 | D7: =((ROUND(Assumptions!$B$6*(1+Assumptions!$B$27)^0,0)*0.2*(Assumptions!$B$10-Assumptions!$B$11)*Assumptions!$B$14*145*Assumptions!$B$16)-((Assumptions!$B$20*12*Assumptions!$B$21+Assumptions!$B$22)+Assumptions!$B$19))/(1+Assumptions!$B$25)^1+((ROUND(Assumptions!$B$6*(1+Assumptions!$B$27)^1,0)*0.2*(Assumptions!$B$10-Assumptions!$B$11)*Assumptions!$B$14*145*Assumptions!$B$16)-((Assumptions!$B$20*12*Assumptions!$B$21+Assumptions!$B$22)))/(1+Assumptions!$B$25)^2+((ROUND(Assumptions!$B$6*(1+Assumptions!$B$27)^2,0)*0.2*(Assumptions!$B$10-Assumptions!$B$11)*Assumptions!$B$14*145*Assumptions!$B$16)-((Assumptions!$B$20*12*Assumptions!$B$21+Assumptions!$B$22)))/(1+Assumptions!$B$25)^3+((ROUND(Assumptions!$B$6*(1+Assumptions!$B$27)^3,0)*0.2*(Assumptions!$B$10-Assumptions!$B$11)*Assumptions!$B$14*145*Assumptions!$B$16)-((Assumptions!$B$20*12*Assumptions!$B$21+Assumptions!$B$22)))/(1+Assumptions!$B$25)^4+((ROUND(Assumptions!$B$6*(1+Assumptions!$B$27)^4,0)*0.2*(Assumptions!$B$10-Assumptions!$B$11)*Assumptions!$B$14*145*Assumptions!$B$16)-((Assumptions!$B$20*12*Assumptions!$B$21+Assumptions!$B$22)))/(1+Assumptions!$B$25)^5 -> 411602.96 | E7: =((ROUND(Assumptions!$B$6*(1+Assumptions!$B$27)^0,0)*0.256*(Assumptions!$B$10-Assumptions!$B$11)*Assumptions!$B$14*145*Assumptions!$B$16)-((Assumptions!$B$20*12*Assumptions!$B$21+Assumptions!$B$22)+Assumptions!$B$19))/(1+Assumptions!$B$25)^1+((ROUND(Assumptions!$B$6*(1+Assumptions!$B$27)^1,0)*0.256*(Assumptions!$B$10-Assumptions!$B$11)*Assumptions!$B$14*145*Assumptions!$B$16)-((Assumptions!$B$20*12*Assumptions!$B$21+Assumptions!$B$22)))/(1+Assumptions!$B$25)^2+((ROUND(Assumptions!$B$6*(1+Assumptions!$B$27)^2,0)*0.256*(Assumptions!$B$10-Assumptions!$B$11)*Assumptions!$B$14*145*Assumptions!$B$16)-((Assumptions!$B$20*12*Assumptions!$B$21+Assumptions!$B$22)))/(1+Assumptions!$B$25)^3+((ROUND(Assumptions!$B$6*(1+Assumptions!$B$27)^3,0)*0.256*(Assumptions!$B$10-Assumptions!$B$11)*Assumptions!$B$14*145*Assumptions!$B$16)-((Assumptions!$B$20*12*Assumptions!$B$21+Assumptions!$B$22)))/(1+Assumptions!$B$25)^4+((ROUND(Assumptions!$B$6*(1+Assumptions!$B$27)^4,0)*0.256*(Assumptions!$B$10-Assumptions!$B$11)*Assumptions!$B$14*145*Assumptions!$B$16)-((Assumptions!$B$20*12*Assumptions!$B$21+Assumptions!$B$22)))/(1+Assumptions!$B$25)^5 -> 556473.31 | F7: =((ROUND(Assumptions!$B$6*(1+Assumptions!$B$27)^0,0)*0.3*(Assumptions!$B$10-Assumptions!$B$11)*Assumptions!$B$14*145*Assumptions!$B$16)-((Assumptions!$B$20*12*Assumptions!$B$21+Assumptions!$B$22)+Assumptions!$B$19))/(1+Assumptions!$B$25)^1+((ROUND(Assumptions!$B$6*(1+Assumptions!$B$27)^1,0)*0.3*(Assumptions!$B$10-Assumptions!$B$11)*Assumptions!$B$14*145*Assumptions!$B$16)-((Assumptions!$B$20*12*Assumptions!$B$21+Assumptions!$B$22)))/(1+Assumptions!$B$25)^2+((ROUND(Assumptions!$B$6*(1+Assumptions!$B$27)^2,0)*0.3*(Assumptions!$B$10-Assumptions!$B$11)*Assumptions!$B$14*145*Assumptions!$B$16)-((Assumptions!$B$20*12*Assumptions!$B$21+Assumptions!$B$22)))/(1+Assumptions!$B$25)^3+((ROUND(Assumptions!$B$6*(1+Assumptions!$B$27)^3,0)*0.3*(Assumptions!$B$10-Assumptions!$B$11)*Assumptions!$B$14*145*Assumptions!$B$16)-((Assumptions!$B$20*12*Assumptions!$B$21+Assumptions!$B$22)))/(1+Assumptions!$B$25)^4+((ROUND(Assumptions!$B$6*(1+Assumptions!$B$27)^4,0)*0.3*(Assumptions!$B$10-Assumptions!$B$11)*Assumptions!$B$14*145*Assumptions!$B$16)-((Assumptions!$B$20*12*Assumptions!$B$21+Assumptions!$B$22)))/(1+Assumptions!$B$25)^5 -> 670300.01 | G7: =((ROUND(Assumptions!$B$6*(1+Assumptions!$B$27)^0,0)*0.35*(Assumptions!$B$10-Assumptions!$B$11)*Assumptions!$B$14*145*Assumptions!$B$16)-((Assumptions!$B$20*12*Assumptions!$B$21+Assumptions!$B$22)+Assumptions!$B$19))/(1+Assumptions!$B$25)^1+((ROUND(Assumptions!$B$6*(1+Assumptions!$B$27)^1,0)*0.35*(Assumptions!$B$10-Assumptions!$B$11)*Assumptions!$B$14*145*Assumptions!$B$16)-((Assumptions!$B$20*12*Assumptions!$B$21+Assumptions!$B$22)))/(1+Assumptions!$B$25)^2+((ROUND(Assumptions!$B$6*(1+Assumptions!$B$27)^2,0)*0.35*(Assumptions!$B$10-Assumptions!$B$11)*Assumptions!$B$14*145*Assumptions!$B$16)-((Assumptions!$B$20*12*Assumptions!$B$21+Assumptions!$B$22)))/(1+Assumptions!$B$25)^3+((ROUND(Assumptions!$B$6*(1+Assumptions!$B$27)^3,0)*0.35*(Assumptions!$B$10-Assumptions!$B$11)*Assumptions!$B$14*145*Assumptions!$B$16)-((Assumptions!$B$20*12*Assumptions!$B$21+Assumptions!$B$22)))/(1+Assumptions!$B$25)^4+((ROUND(Assumptions!$B$6*(1+Assumptions!$B$27)^4,0)*0.35*(Assumptions!$B$10-Assumptions!$B$11)*Assumptions!$B$14*145*Assumptions!$B$16)-((Assumptions!$B$20*12*Assumptions!$B$21+Assumptions!$B$22)))/(1+Assumptions!$B$25)^5 -> 799648.54
A8: 170 | B8: =((ROUND(Assumptions!$B$6*(1+Assumptions!$B$27)^0,0)*0.1*(Assumptions!$B$10-Assumptions!$B$11)*Assumptions!$B$14*170*Assumptions!$B$16)-((Assumptions!$B$20*12*Assumptions!$B$21+Assumptions!$B$22)+Assumptions!$B$19))/(1+Assumptions!$B$25)^1+((ROUND(Assumptions!$B$6*(1+Assumptions!$B$27)^1,0)*0.1*(Assumptions!$B$10-Assumptions!$B$11)*Assumptions!$B$14*170*Assumptions!$B$16)-((Assumptions!$B$20*12*Assumptions!$B$21+Assumptions!$B$22)))/(1+Assumptions!$B$25)^2+((ROUND(Assumptions!$B$6*(1+Assumptions!$B$27)^2,0)*0.1*(Assumptions!$B$10-Assumptions!$B$11)*Assumptions!$B$14*170*Assumptions!$B$16)-((Assumptions!$B$20*12*Assumptions!$B$21+Assumptions!$B$22)))/(1+Assumptions!$B$25)^3+((ROUND(Assumptions!$B$6*(1+Assumptions!$B$27)^3,0)*0.1*(Assumptions!$B$10-Assumptions!$B$11)*Assumptions!$B$14*170*Assumptions!$B$16)-((Assumptions!$B$20*12*Assumptions!$B$21+Assumptions!$B$22)))/(1+Assumptions!$B$25)^4+((ROUND(Assumptions!$B$6*(1+Assumptions!$B$27)^4,0)*0.1*(Assumptions!$B$10-Assumptions!$B$11)*Assumptions!$B$14*170*Assumptions!$B$16)-((Assumptions!$B$20*12*Assumptions!$B$21+Assumptions!$B$22)))/(1+Assumptions!$B$25)^5 -> 197508.85 | C8: =((ROUND(Assumptions!$B$6*(1+Assumptions!$B$27)^0,0)*0.15*(Assumptions!$B$10-Assumptions!$B$11)*Assumptions!$B$14*170*Assumptions!$B$16)-((Assumptions!$B$20*12*Assumptions!$B$21+Assumptions!$B$22)+Assumptions!$B$19))/(1+Assumptions!$B$25)^1+((ROUND(Assumptions!$B$6*(1+Assumptions!$B$27)^1,0)*0.15*(Assumptions!$B$10-Assumptions!$B$11)*Assumptions!$B$14*170*Assumptions!$B$16)-((Assumptions!$B$20*12*Assumptions!$B$21+Assumptions!$B$22)))/(1+Assumptions!$B$25)^2+((ROUND(Assumptions!$B$6*(1+Assumptions!$B$27)^2,0)*0.15*(Assumptions!$B$10-Assumptions!$B$11)*Assumptions!$B$14*170*Assumptions!$B$16)-((Assumptions!$B$20*12*Assumptions!$B$21+Assumptions!$B$22)))/(1+Assumptions!$B$25)^3+((ROUND(Assumptions!$B$6*(1+Assumptions!$B$27)^3,0)*0.15*(Assumptions!$B$10-Assumptions!$B$11)*Assumptions!$B$14*170*Assumptions!$B$16)-((Assumptions!$B$20*12*Assumptions!$B$21+Assumptions!$B$22)))/(1+Assumptions!$B$25)^4+((ROUND(Assumptions!$B$6*(1+Assumptions!$B$27)^4,0)*0.15*(Assumptions!$B$10-Assumptions!$B$11)*Assumptions!$B$14*170*Assumptions!$B$16)-((Assumptions!$B$20*12*Assumptions!$B$21+Assumptions!$B$22)))/(1+Assumptions!$B$25)^5 -> 349158.85 | D8: =((ROUND(Assumptions!$B$6*(1+Assumptions!$B$27)^0,0)*0.2*(Assumptions!$B$10-Assumptions!$B$11)*Assumptions!$B$14*170*Assumptions!$B$16)-((Assumptions!$B$20*12*Assumptions!$B$21+Assumptions!$B$22)+Assumptions!$B$19))/(1+Assumptions!$B$25)^1+((ROUND(Assumptions!$B$6*(1+Assumptions!$B$27)^1,0)*0.2*(Assumptions!$B$10-Assumptions!$B$11)*Assumptions!$B$14*170*Assumptions!$B$16)-((Assumptions!$B$20*12*Assumptions!$B$21+Assumptions!$B$22)))/(1+Assumptions!$B$25)^2+((ROUND(Assumptions!$B$6*(1+Assumptions!$B$27)^2,0)*0.2*(Assumptions!$B$10-Assumptions!$B$11)*Assumptions!$B$14*170*Assumptions!$B$16)-((Assumptions!$B$20*12*Assumptions!$B$21+Assumptions!$B$22)))/(1+Assumptions!$B$25)^3+((ROUND(Assumptions!$B$6*(1+Assumptions!$B$27)^3,0)*0.2*(Assumptions!$B$10-Assumptions!$B$11)*Assumptions!$B$14*170*Assumptions!$B$16)-((Assumptions!$B$20*12*Assumptions!$B$21+Assumptions!$B$22)))/(1+Assumptions!$B$25)^4+((ROUND(Assumptions!$B$6*(1+Assumptions!$B$27)^4,0)*0.2*(Assumptions!$B$10-Assumptions!$B$11)*Assumptions!$B$14*170*Assumptions!$B$16)-((Assumptions!$B$20*12*Assumptions!$B$21+Assumptions!$B$22)))/(1+Assumptions!$B$25)^5 -> 500808.84 | E8: =((ROUND(Assumptions!$B$6*(1+Assumptions!$B$27)^0,0)*0.256*(Assumptions!$B$10-Assumptions!$B$11)*Assumptions!$B$14*170*Assumptions!$B$16)-((Assumptions!$B$20*12*Assumptions!$B$21+Assumptions!$B$22)+Assumptions!$B$19))/(1+Assumptions!$B$25)^1+((ROUND(Assumptions!$B$6*(1+Assumptions!$B$27)^1,0)*0.256*(Assumptions!$B$10-Assumptions!$B$11)*Assumptions!$B$14*170*Assumptions!$B$16)-((Assumptions!$B$20*12*Assumptions!$B$21+Assumptions!$B$22)))/(1+Assumptions!$B$25)^2+((ROUND(Assumptions!$B$6*(1+Assumptions!$B$27)^2,0)*0.256*(Assumptions!$B$10-Assumptions!$B$11)*Assumptions!$B$14*170*Assumptions!$B$16)-((Assumptions!$B$20*12*Assumptions!$B$21+Assumptions!$B$22)))/(1+Assumptions!$B$25)^3+((ROUND(Assumptions!$B$6*(1+Assumptions!$B$27)^3,0)*0.256*(Assumptions!$B$10-Assumptions!$B$11)*Assumptions!$B$14*170*Assumptions!$B$16)-((Assumptions!$B$20*12*Assumptions!$B$21+Assumptions!$B$22)))/(1+Assumptions!$B$25)^4+((ROUND(Assumptions!$B$6*(1+Assumptions!$B$27)^4,0)*0.256*(Assumptions!$B$10-Assumptions!$B$11)*Assumptions!$B$14*170*Assumptions!$B$16)-((Assumptions!$B$20*12*Assumptions!$B$21+Assumptions!$B$22)))/(1+Assumptions!$B$25)^5 -> 670656.83 | F8: =((ROUND(Assumptions!$B$6*(1+Assumptions!$B$27)^0,0)*0.3*(Assumptions!$B$10-Assumptions!$B$11)*Assumptions!$B$14*170*Assumptions!$B$16)-((Assumptions!$B$20*12*Assumptions!$B$21+Assumptions!$B$22)+Assumptions!$B$19))/(1+Assumptions!$B$25)^1+((ROUND(Assumptions!$B$6*(1+Assumptions!$B$27)^1,0)*0.3*(Assumptions!$B$10-Assumptions!$B$11)*Assumptions!$B$14*170*Assumptions!$B$16)-((Assumptions!$B$20*12*Assumptions!$B$21+Assumptions!$B$22)))/(1+Assumptions!$B$25)^2+((ROUND(Assumptions!$B$6*(1+Assumptions!$B$27)^2,0)*0.3*(Assumptions!$B$10-Assumptions!$B$11)*Assumptions!$B$14*170*Assumptions!$B$16)-((Assumptions!$B$20*12*Assumptions!$B$21+Assumptions!$B$22)))/(1+Assumptions!$B$25)^3+((ROUND(Assumptions!$B$6*(1+Assumptions!$B$27)^3,0)*0.3*(Assumptions!$B$10-Assumptions!$B$11)*Assumptions!$B$14*170*Assumptions!$B$16)-((Assumptions!$B$20*12*Assumptions!$B$21+Assumptions!$B$22)))/(1+Assumptions!$B$25)^4+((ROUND(Assumptions!$B$6*(1+Assumptions!$B$27)^4,0)*0.3*(Assumptions!$B$10-Assumptions!$B$11)*Assumptions!$B$14*170*Assumptions!$B$16)-((Assumptions!$B$20*12*Assumptions!$B$21+Assumptions!$B$22)))/(1+Assumptions!$B$25)^5 -> 804108.83 | G8: =((ROUND(Assumptions!$B$6*(1+Assumptions!$B$27)^0,0)*0.35*(Assumptions!$B$10-Assumptions!$B$11)*Assumptions!$B$14*170*Assumptions!$B$16)-((Assumptions!$B$20*12*Assumptions!$B$21+Assumptions!$B$22)+Assumptions!$B$19))/(1+Assumptions!$B$25)^1+((ROUND(Assumptions!$B$6*(1+Assumptions!$B$27)^1,0)*0.35*(Assumptions!$B$10-Assumptions!$B$11)*Assumptions!$B$14*170*Assumptions!$B$16)-((Assumptions!$B$20*12*Assumptions!$B$21+Assumptions!$B$22)))/(1+Assumptions!$B$25)^2+((ROUND(Assumptions!$B$6*(1+Assumptions!$B$27)^2,0)*0.35*(Assumptions!$B$10-Assumptions!$B$11)*Assumptions!$B$14*170*Assumptions!$B$16)-((Assumptions!$B$20*12*Assumptions!$B$21+Assumptions!$B$22)))/(1+Assumptions!$B$25)^3+((ROUND(Assumptions!$B$6*(1+Assumptions!$B$27)^3,0)*0.35*(Assumptions!$B$10-Assumptions!$B$11)*Assumptions!$B$14*170*Assumptions!$B$16)-((Assumptions!$B$20*12*Assumptions!$B$21+Assumptions!$B$22)))/(1+Assumptions!$B$25)^4+((ROUND(Assumptions!$B$6*(1+Assumptions!$B$27)^4,0)*0.35*(Assumptions!$B$10-Assumptions!$B$11)*Assumptions!$B$14*170*Assumptions!$B$16)-((Assumptions!$B$20*12*Assumptions!$B$21+Assumptions!$B$22)))/(1+Assumptions!$B$25)^5 -> 955758.82
A9: 195 | B9: =((ROUND(Assumptions!$B$6*(1+Assumptions!$B$27)^0,0)*0.1*(Assumptions!$B$10-Assumptions!$B$11)*Assumptions!$B$14*195*Assumptions!$B$16)-((Assumptions!$B$20*12*Assumptions!$B$21+Assumptions!$B$22)+Assumptions!$B$19))/(1+Assumptions!$B$25)^1+((ROUND(Assumptions!$B$6*(1+Assumptions!$B$27)^1,0)*0.1*(Assumptions!$B$10-Assumptions!$B$11)*Assumptions!$B$14*195*Assumptions!$B$16)-((Assumptions!$B$20*12*Assumptions!$B$21+Assumptions!$B$22)))/(1+Assumptions!$B$25)^2+((ROUND(Assumptions!$B$6*(1+Assumptions!$B$27)^2,0)*0.1*(Assumptions!$B$10-Assumptions!$B$11)*Assumptions!$B$14*195*Assumptions!$B$16)-((Assumptions!$B$20*12*Assumptions!$B$21+Assumptions!$B$22)))/(1+Assumptions!$B$25)^3+((ROUND(Assumptions!$B$6*(1+Assumptions!$B$27)^3,0)*0.1*(Assumptions!$B$10-Assumptions!$B$11)*Assumptions!$B$14*195*Assumptions!$B$16)-((Assumptions!$B$20*12*Assumptions!$B$21+Assumptions!$B$22)))/(1+Assumptions!$B$25)^4+((ROUND(Assumptions!$B$6*(1+Assumptions!$B$27)^4,0)*0.1*(Assumptions!$B$10-Assumptions!$B$11)*Assumptions!$B$14*195*Assumptions!$B$16)-((Assumptions!$B$20*12*Assumptions!$B$21+Assumptions!$B$22)))/(1+Assumptions!$B$25)^5 -> 242111.79 | C9: =((ROUND(Assumptions!$B$6*(1+Assumptions!$B$27)^0,0)*0.15*(Assumptions!$B$10-Assumptions!$B$11)*Assumptions!$B$14*195*Assumptions!$B$16)-((Assumptions!$B$20*12*Assumptions!$B$21+Assumptions!$B$22)+Assumptions!$B$19))/(1+Assumptions!$B$25)^1+((ROUND(Assumptions!$B$6*(1+Assumptions!$B$27)^1,0)*0.15*(Assumptions!$B$10-Assumptions!$B$11)*Assumptions!$B$14*195*Assumptions!$B$16)-((Assumptions!$B$20*12*Assumptions!$B$21+Assumptions!$B$22)))/(1+Assumptions!$B$25)^2+((ROUND(Assumptions!$B$6*(1+Assumptions!$B$27)^2,0)*0.15*(Assumptions!$B$10-Assumptions!$B$11)*Assumptions!$B$14*195*Assumptions!$B$16)-((Assumptions!$B$20*12*Assumptions!$B$21+Assumptions!$B$22)))/(1+Assumptions!$B$25)^3+((ROUND(Assumptions!$B$6*(1+Assumptions!$B$27)^3,0)*0.15*(Assumptions!$B$10-Assumptions!$B$11)*Assumptions!$B$14*195*Assumptions!$B$16)-((Assumptions!$B$20*12*Assumptions!$B$21+Assumptions!$B$22)))/(1+Assumptions!$B$25)^4+((ROUND(Assumptions!$B$6*(1+Assumptions!$B$27)^4,0)*0.15*(Assumptions!$B$10-Assumptions!$B$11)*Assumptions!$B$14*195*Assumptions!$B$16)-((Assumptions!$B$20*12*Assumptions!$B$21+Assumptions!$B$22)))/(1+Assumptions!$B$25)^5 -> 416063.26 | D9: =((ROUND(Assumptions!$B$6*(1+Assumptions!$B$27)^0,0)*0.2*(Assumptions!$B$10-Assumptions!$B$11)*Assumptions!$B$14*195*Assumptions!$B$16)-((Assumptions!$B$20*12*Assumptions!$B$21+Assumptions!$B$22)+Assumptions!$B$19))/(1+Assumptions!$B$25)^1+((ROUND(Assumptions!$B$6*(1+Assumptions!$B$27)^1,0)*0.2*(Assumptions!$B$10-Assumptions!$B$11)*Assumptions!$B$14*195*Assumptions!$B$16)-((Assumptions!$B$20*12*Assumptions!$B$21+Assumptions!$B$22)))/(1+Assumptions!$B$25)^2+((ROUND(Assumptions!$B$6*(1+Assumptions!$B$27)^2,0)*0.2*(Assumptions!$B$10-Assumptions!$B$11)*Assumptions!$B$14*195*Assumptions!$B$16)-((Assumptions!$B$20*12*Assumptions!$B$21+Assumptions!$B$22)))/(1+Assumptions!$B$25)^3+((ROUND(Assumptions!$B$6*(1+Assumptions!$B$27)^3,0)*0.2*(Assumptions!$B$10-Assumptions!$B$11)*Assumptions!$B$14*195*Assumptions!$B$16)-((Assumptions!$B$20*12*Assumptions!$B$21+Assumptions!$B$22)))/(1+Assumptions!$B$25)^4+((ROUND(Assumptions!$B$6*(1+Assumptions!$B$27)^4,0)*0.2*(Assumptions!$B$10-Assumptions!$B$11)*Assumptions!$B$14*195*Assumptions!$B$16)-((Assumptions!$B$20*12*Assumptions!$B$21+Assumptions!$B$22)))/(1+Assumptions!$B$25)^5 -> 590014.72 | E9: =((ROUND(Assumptions!$B$6*(1+Assumptions!$B$27)^0,0)*0.256*(Assumptions!$B$10-Assumptions!$B$11)*Assumptions!$B$14*195*Assumptions!$B$16)-((Assumptions!$B$20*12*Assumptions!$B$21+Assumptions!$B$22)+Assumptions!$B$19))/(1+Assumptions!$B$25)^1+((ROUND(Assumptions!$B$6*(1+Assumptions!$B$27)^1,0)*0.256*(Assumptions!$B$10-Assumptions!$B$11)*Assumptions!$B$14*195*Assumptions!$B$16)-((Assumptions!$B$20*12*Assumptions!$B$21+Assumptions!$B$22)))/(1+Assumptions!$B$25)^2+((ROUND(Assumptions!$B$6*(1+Assumptions!$B$27)^2,0)*0.256*(Assumptions!$B$10-Assumptions!$B$11)*Assumptions!$B$14*195*Assumptions!$B$16)-((Assumptions!$B$20*12*Assumptions!$B$21+Assumptions!$B$22)))/(1+Assumptions!$B$25)^3+((ROUND(Assumptions!$B$6*(1+Assumptions!$B$27)^3,0)*0.256*(Assumptions!$B$10-Assumptions!$B$11)*Assumptions!$B$14*195*Assumptions!$B$16)-((Assumptions!$B$20*12*Assumptions!$B$21+Assumptions!$B$22)))/(1+Assumptions!$B$25)^4+((ROUND(Assumptions!$B$6*(1+Assumptions!$B$27)^4,0)*0.256*(Assumptions!$B$10-Assumptions!$B$11)*Assumptions!$B$14*195*Assumptions!$B$16)-((Assumptions!$B$20*12*Assumptions!$B$21+Assumptions!$B$22)))/(1+Assumptions!$B$25)^5 -> 784840.36 | F9: =((ROUND(Assumptions!$B$6*(1+Assumptions!$B$27)^0,0)*0.3*(Assumptions!$B$10-Assumptions!$B$11)*Assumptions!$B$14*195*Assumptions!$B$16)-((Assumptions!$B$20*12*Assumptions!$B$21+Assumptions!$B$22)+Assumptions!$B$19))/(1+Assumptions!$B$25)^1+((ROUND(Assumptions!$B$6*(1+Assumptions!$B$27)^1,0)*0.3*(Assumptions!$B$10-Assumptions!$B$11)*Assumptions!$B$14*195*Assumptions!$B$16)-((Assumptions!$B$20*12*Assumptions!$B$21+Assumptions!$B$22)))/(1+Assumptions!$B$25)^2+((ROUND(Assumptions!$B$6*(1+Assumptions!$B$27)^2,0)*0.3*(Assumptions!$B$10-Assumptions!$B$11)*Assumptions!$B$14*195*Assumptions!$B$16)-((Assumptions!$B$20*12*Assumptions!$B$21+Assumptions!$B$22)))/(1+Assumptions!$B$25)^3+((ROUND(Assumptions!$B$6*(1+Assumptions!$B$27)^3,0)*0.3*(Assumptions!$B$10-Assumptions!$B$11)*Assumptions!$B$14*195*Assumptions!$B$16)-((Assumptions!$B$20*12*Assumptions!$B$21+Assumptions!$B$22)))/(1+Assumptions!$B$25)^4+((ROUND(Assumptions!$B$6*(1+Assumptions!$B$27)^4,0)*0.3*(Assumptions!$B$10-Assumptions!$B$11)*Assumptions!$B$14*195*Assumptions!$B$16)-((Assumptions!$B$20*12*Assumptions!$B$21+Assumptions!$B$22)))/(1+Assumptions!$B$25)^5 -> 937917.65 | G9: =((ROUND(Assumptions!$B$6*(1+Assumptions!$B$27)^0,0)*0.35*(Assumptions!$B$10-Assumptions!$B$11)*Assumptions!$B$14*195*Assumptions!$B$16)-((Assumptions!$B$20*12*Assumptions!$B$21+Assumptions!$B$22)+Assumptions!$B$19))/(1+Assumptions!$B$25)^1+((ROUND(Assumptions!$B$6*(1+Assumptions!$B$27)^1,0)*0.35*(Assumptions!$B$10-Assumptions!$B$11)*Assumptions!$B$14*195*Assumptions!$B$16)-((Assumptions!$B$20*12*Assumptions!$B$21+Assumptions!$B$22)))/(1+Assumptions!$B$25)^2+((ROUND(Assumptions!$B$6*(1+Assumptions!$B$27)^2,0)*0.35*(Assumptions!$B$10-Assumptions!$B$11)*Assumptions!$B$14*195*Assumptions!$B$16)-((Assumptions!$B$20*12*Assumptions!$B$21+Assumptions!$B$22)))/(1+Assumptions!$B$25)^3+((ROUND(Assumptions!$B$6*(1+Assumptions!$B$27)^3,0)*0.35*(Assumptions!$B$10-Assumptions!$B$11)*Assumptions!$B$14*195*Assumptions!$B$16)-((Assumptions!$B$20*12*Assumptions!$B$21+Assumptions!$B$22)))/(1+Assumptions!$B$25)^4+((ROUND(Assumptions!$B$6*(1+Assumptions!$B$27)^4,0)*0.35*(Assumptions!$B$10-Assumptions!$B$11)*Assumptions!$B$14*195*Assumptions!$B$16)-((Assumptions!$B$20*12*Assumptions!$B$21+Assumptions!$B$22)))/(1+Assumptions!$B$25)^5 -> 1111869.1
A12: Highlighted cell is the base case: the 25.6% null share measured in the study and a $145/hr loaded rate. Each cell discounts five years of cash flow directly, so it stays correct if the Value Model changes.
